Workbook

Sheet RECAPITULATIF
A1: 📋 RÉCAPITULATIF — ORDRE DES OPÉRATIONS DANS EXCEL
A3: Ordre | B3: Action | C3: Feuille Excel | D3: Section mémoire | E3: Statut
A4: 1 | B4: Insertion des données brutes non filtrées | C4: DONNEES BRUTES non filtrées | D4: — | E4: ✅ Automatisé
A5: 2 | B5: Vérifier les 2 filtres appliqués (Q1≠Jamais, Q29=Neutre) et concerne l'audit | C5: DONNEES_SOURCE | D5: 4.3.2 | E5: ✅ Automatisé
A6: 3 | B6: Variables inversées Q11_inv, Q22_inv, Q25_inv, Q26_inv, Q8_norm | C6: 0_PREPARATION | D6: 4.2.1 | E6: ✅ Calculé
A7: 4 | B7: 5 scores composites (SUP, SFU, SRP, SMF, SS) | C7: 0_PREPARATION | D7: 4.2.1 | E7: ✅ Calculé
A8: 5 | B8: Regroupement Q33 → Q33_groupe (3 niveaux) | C8: 0_PREPARATION | D8: 5.1 | E8: ✅ Calculé
A9: 6 | B9: Tableaux de fréquences Q31→Q36 + graphiques | C9: 5.1_PROFIL_ECHANTILLON | D9: 5.1 | E9: ✅ Calculé
A10: 7 | B10: Statistiques descriptives des 5 scores + Q1 + Q30 | C10: 5.2_STATS_DESC_CRONBACH | D10: 5.2 | E10: ✅ Calculé
A11: 8 | B11: Alpha de Cronbach pour les 5 scores (×5) | C11: 5.2_STATS_DESC_CRONBACH | D11: 5.2 | E11: ✅ Calculé
A12: 9 | B12: Corrélations Spearman H1, H2, H3, H4a, H4b | C12: 5.3_TEST_HYPOTHESES | D12: 5.3 | E12: ✅ Calculé
A13: 10 | B13: Régressions OLS (H1+H2 conjointe, H4b) | C13: 5.3_TEST_HYPOTHESES | D13: 5.3 | E13: ✅ Calculé
A14: 11 | B14: Sous-groupes Q19 pour H4a (formés vs peu formés) | C14: 5.3_TEST_HYPOTHESES | D14: 5.3 | E14: ✅ Calculé
A15: 12 | B15: Kruskal-Wallis + Mann-Whitney (grade, cabinet) | C15: 5.4_ANALYSES_COMPLEM | D15: 5.4 | E15: ✅ Calculé
... A17: 14 | B17: Rédiger la discussion à partir des guides | C17: 5.5_GUIDE_DISCUSSION | D17: 5.5 | E17: 📝 À rédiger
B20: 📊 FEUILLES D'HYPOTHÈSES CRÉÉES
A21: Ordre | B21: Action | C21: Feuille Excel | D21: Section mémoire | E21: Statut
A22: 15 | B22: Test H1 : SUP → Q1 (Utilité perçue → Usage) - Spearman détaillé par items Q6/Q7 | C22: H1_SUP_Q1 | D22: 5.3 | E22: ✅ Calculé
A23: 16 | B23: Test H2 : SFU → Q1 (Facilité d'usage → Usage) - Spearman + composantes Q9/Q10/Q11 | C23: H2_SFU_Q1 | D23: 5.3 | E23: ✅ Calculé
A24: 17 | B24: Test H3 : SRP → Q17/Q1 (Risques perçus → Frein/Usage) - H3a et H3a-2 | C24: H3_SRP | D24: 5.3 | E24: ✅ Calculé
A25: 18 | B25: Test H4a : Modération SMF sur SRP → Q1 (Terciles compétence) | C25: H4a_MODERATION | D25: 5.3 | E25: ✅ Calculé
A26: 19 | B26: Test H4b : Scepticisme et biais d'automatisation | C26: H4b_SCEPTICISME | D26: 5.3 | E26: ✅ Calculé
B28: 📈 RÉSUMÉ DES RÉSULTATS DES HYPOTHÈSES
A29: Hypothèse | B29: Test | C29: ρ Spearman | D29: p-value | E29: Verdict
A30: H1: SUP → Q1 | B30: Spearman | C30: ='5.3_HYPOTHESES'!C21 -> 0.16799573 | D30: ='5.3_HYPOTHESES'!D21 -> 0.17417627 | E30: INFIRMÉE (globalement)
A31: H2: SFU → Q1 | B31: Spearman | C31: =H2_SFU_Q1!C29 -> 0.32492787 | D31: =H2_SFU_Q1!F29 -> 0.0073005317 | E31: CONFIRMÉE *
A32: H3a: SRP → Q17 | B32: Spearman | C32: =H3_SRP!C32 -> 0.30950561 | D32: =H3_SRP!F32 -> 0.010814038 | E32: CONFIRMÉE *
A33: H3a-2: SRP → Q1 | B33: Spearman | C33: =H3_SRP!C33 -> -0.23098832 | D33: =H3_SRP!F33 -> 0.060018257 | E33: CONFIRMÉE *
A34: H4a: Modération | B34: Gradient terciles | C34: =CONCATENATE(ROUND(H4a_MODERATION!D25,2)," → ",ROUND(H4a_MODERATION!D26,2)," → ",ROUND(H4a_MODERATION!D27,2)) -> -0,42 → -0,27 → 0,03 | D34: Gradient ✓ | E34: CONFIRMÉE (direction)
A35: H4b-1: SMF → SS | B35: Spearman | C35: =H4b_SCEPTICISME!E19 -> 0.18957621 | D35: =H4b_SCEPTICISME!H19 -> 0.12441186 | E35: INFIRMÉE
A36: H4b-2: SRP → SS | B36: Spearman | C36: =H4b_SCEPTICISME!E20 -> 0.11261127 | D36: =H4b_SCEPTICISME!H20 -> 0.36424451 | E36: INFIRMÉE
B38: 🔬 TESTS DÉSAGRÉGÉS SIGNIFICATIFS
A39: Test | B39: ρ | C39: p-value | D39: Sig. | E39: Interprétation
A40: Q7_Rédaction → Q1 | B40: =H1_SUP_Q1!E51 -> 0.32557697 | C40: =H1_SUP_Q1!H51 -> 0.0071776759 | D40: ** | E40: Utilité qualité rédaction → usage
A41: Q10 (Intégration) → Q1 | B41: =H2_SFU_Q1!C31 -> 0.49220464 | C41: =H2_SFU_Q1!F31 -> 2.3313129e-05 | D41: *** | E41: Intégration workflow = facteur clé
A42: Q15 (Responsabilité) → Q17 | B42: =H3_SRP!C37 -> 0.30449358 | C42: =H3_SRP!F37 -> 0.012235357 | D42: * | E42: Risque responsabilité = principal frein
A43: Q20 (Orienter) → Q1 | B43: =H4a_MODERATION!E34 -> 0.3785463 | C43: =H4a_MODERATION!H34 -> 0.0015849524 | D43: ** | E43: Compétence prompting → usage
A44: Q21 (Détecter) → Q1 | B44: =H4a_MODERATION!E35 -> 0.24221211 | C44: =H4a_MODERATION!H35 -> 0.048291532 | D44: * | E44: Compétence détection → usage
B46: ⚠️ BIAIS D'AUTOMATISATION DÉTECTÉ (H4b)
A47: Signal | B47: ρ | C47: p-value | D47: Sig. | E47: Mécanisme
A48: Q21 → SS | B48: =H4b_SCEPTICISME!E27 -> 0.27752373 | C48: =H4b_SCEPTICISME!H27 -> 0.022981405 | D48: * | E48: Compétence protège le jugement ✓
A49: Q12 → Q23 | B49: =H4b_SCEPTICISME!E28 -> 0.3119768 | C49: =H4b_SCEPTICISME!H28 -> 0.010167639 | D49: * | E49: Conscience hallucinations → vigilance ✓
A50: Q1 → Q24 | B50: =H4b_SCEPTICISME!E29 -> 0.28200723 | C50: =H4b_SCEPTICISME!H29 -> 0.020776026 | D50: * | E50: Usage intense = se croit sceptique
A51: Q1 → Q25_inv | B51: =H4b_SCEPTICISME!E30 -> -0.27105279 | C51: =H4b_SCEPTICISME!H30 -> 0.026512435 | D51: * | E51: Usage intense = influencé par l'IAG
B53: 📊 GRADIENT H4a PAR TERCILE SMF
A54: Tercile | B54: N | C54: ρ(SRP→Q1) | D54: p-value | E54: Interprétation
A55: Bas (peu compétents) | B55: =H4a_MODERATION!C25 -> 21 | C55: =H4a_MODERATION!D25 -> -0.41561294 | D55: =H4a_MODERATION!G25 -> 0.060965841 | E55: Effet inhibiteur fort .
A56: Moyen | B56: =H4a_MODERATION!C26 -> 24 | C56: =H4a_MODERATION!D26 -> -0.27407503 | D56: =H4a_MODERATION!G26 -> 0.19497724 | E56: Effet modéré NS
A57: Élevé (très compétents) | B57: =H4a_MODERATION!C27 -> 22 | C57: =H4a_MODERATION!D27 -> 0.030447408 | D57: =H4a_MODERATION!G27 -> 0.89300287 | E57: Effet annulé ✓
A61: Point clé | B61: Résultat | C61: Référence feuille | D61: Implication théorique
A62: TAM partiel | B62: H1 infirmée globalement, H2 confirmée | C62: H1_SUP_Q1, H2_SFU_Q1 | D62: Facilité d'usage > Utilité perçue pour l'adoption
A63: Utilité sélective | B63: Q7_Rédaction significatif (ρ=0.33**) | C63: H1_SUP_Q1 | D63: H1 vraie pour tâches à fort enjeu professionnel
A64: Effet plafond | B64: Q6/Q7 Extraction, Résumé: médiane=4/5 | C64: H1_SUP_Q1 | D64: 80%+ trouvent l'IAG utile → variance insuffisante
A65: Effet grade | B65: SUP→Q1: ρ=0.40* (Junior) vs NS (Seniors) | C65: H1_SUP_Q1 | D65: TAM fonctionne chez juniors, pas chez seniors
A66: Risques = frein réel | B66: H3a et H3a-2 confirmées | C66: H3_SRP | D66: Responsabilité = risque dominant (ρ=0.30*)
A67: Modération H4a | B67: Gradient -0.42 → -0.27 → 0.00 | C67: H4a_MODERATION | D67: Maîtrise technique annule l'effet inhibiteur
A68: Biais d'automatisation | B68: 4 signaux significatifs détectés | C68: H4b_SCEPTICISME | D68: Confirme Munoko et al. (2020)
A69: Tension cognitive | B69: Q1→Q24 (ρ>0) ET Q1→Q25_inv (ρ<0) | C69: H4b_SCEPTICISME | D69: Se croit sceptique mais influencé par l'IAG

Sheet DONNEES BRUTES non filtrées
A1: Horodateur | B1: Q1. À quelle fréquence utilisez-vous l'IA générative dans le cadre de votre travail en audit ? | C1: Q2. Quel type d'IAG utilisez-vous principalement ? | D1: Q3. Quelles IAG utilisez vous dans le cadre de vos missions d'audit ? [Mistral] | E1: Q3. Quelles IAG utilisez vous dans le cadre de vos missions d'audit ? [Copilot] | F1: Q3. Quelles IAG utilisez vous dans le cadre de vos missions d'audit ? [ChatGPT] | G1: Q3. Quelles IAG utilisez vous dans le cadre de vos missions d'audit ? [Gemini] | H1: Q3. Quelles IAG utilisez vous dans le cadre de vos missions d'audit ? [Perplexity] | I1: Q3. Quelles IAG utilisez vous dans le cadre de vos missions d'audit ? [Grok] | J1: Q3. Quelles IAG utilisez vous dans le cadre de vos missions d'audit ? [Claude] | K1: Q3. Quelles IAG utilisez vous dans le cadre de vos missions d'audit ? [Outils IAG spécifiques cabinet] | L1: Q3. Quelles IAG utilisez vous dans le cadre de vos missions d'audit ? [Autres] | M1: Q4. Parmi ces tâches, cochez celles que vous avez déjà effectuées à l’aide de l’IA générative. | N1: Q5. Vous utilisez l'IA générative... | O1: Q6. Dans quelle mesure jugez-vous utile l’IA générative, pour améliorer la productivité, pour les activités suivantes ? [Extraction données (financières, juridiques, ...)] | P1: Q6. Dans quelle mesure jugez-vous utile l’IA générative, pour améliorer la productivité, pour les activités suivantes ? [Résumé données (financières, juridiques, ...)] | Q1: Q6. Dans quelle mesure jugez-vous utile l’IA générative, pour améliorer la productivité, pour les activités suivantes ? [Rédaction (rapports, synthèses, notes, mails)] | R1: Q6. Dans quelle mesure jugez-vous utile l’IA générative, pour améliorer la productivité, pour les activités suivantes ? [Rapprochement/Comparaison de documents] | S1: Q6. Dans quelle mesure jugez-vous utile l’IA générative, pour améliorer la productivité, pour les activités suivantes ? [Développement (scripts SQL, VBA)] | T1: Q6. Dans quelle mesure jugez-vous utile l’IA générative, pour améliorer la productivité, pour les activités suivantes ? [Détection de fraude] | U1: Q6. Dans quelle mesure jugez-vous utile l’IA générative, pour améliorer la productivité, pour les activités suivantes ? [Calcul du seuil de signification] | V1: Q6. Dans quelle mesure jugez-vous utile l’IA générative, pour améliorer la productivité, pour les activités suivantes ? [Revue d'estimations (provisions)] | W1: Q6. Dans quelle mesure jugez-vous utile l’IA générative, pour améliorer la productivité, pour les activités suivantes ? [Aide à la décision] | X1: Q6. Dans quelle mesure jugez-vous utile l’IA générative, pour améliorer la productivité, pour les activités suivantes ? [Préparation de données (format, structuration, harmonisation des valeurs)] | Y1: Q7. Dans quelle mesure jugez-vous utile l’IA générative, pour améliorer la qualité, pour les activités suivantes ? [Extraction données (financières, juridiques, ...)] | Z1: Q7. Dans quelle mesure jugez-vous utile l’IA générative, pour améliorer la qualité, pour les activités suivantes ? [Résumé données (financières, juridiques, ...)] | AA1: Q7. Dans quelle mesure jugez-vous utile l’IA générative, pour améliorer la qualité, pour les activités suivantes ? [Rédaction (rapports, synthèses, notes, mails)] | AB1: Q7. Dans quelle mesure jugez-vous utile l’IA générative, pour améliorer la qualité, pour les activités suivantes ? [Rapprochement/Comparaison de documents] | AC1: Q7. Dans quelle mesure jugez-vous utile l’IA générative, pour améliorer la qualité, pour les activités suivantes ? [Développement (scripts SQL, VBA)] | AD1: Q7. Dans quelle mesure jugez-vous utile l’IA générative, pour améliorer la qualité, pour les activités suivantes ? [Détection de fraude] | AE1: Q7. Dans quelle mesure jugez-vous utile l’IA générative, pour améliorer la qualité, pour les activités suivantes ? [Calcul du seuil de signification] | AF1: Q7. Dans quelle mesure jugez-vous utile l’IA générative, pour améliorer la qualité, pour les activités suivantes ? [Revue d'estimations (provisions)] | AG1: Q7. Dans quelle mesure jugez-vous utile l’IA générative, pour améliorer la qualité, pour les activités suivantes ? [Aide à la décision] | AH1: Q7. Dans quelle mesure jugez-vous utile l’IA générative, pour améliorer la qualité, pour les activités suivantes ? [Préparation de données (format, structuration, harmonisation des valeurs)] | AI1: Q8. "L'utilisation de l'IA générative me fait gagner du temps" | AJ1: Q9. Comment jugez-vous la prise en main des outils d'IA générative ? | AK1: Q10. "L'intégration de l'IA générative dans mon flux de travail quotidien se fait naturellement." | AL1: Q11. "Apprendre à utiliser l'IA générative efficacement requiert une formation" | AM1: Q12. L'IA générative peut produire des informations inexactes ou trompeuses dans le contexte de l'audit. | AN1: Q13. Partager des données avec l'IA générative présente des risques pour la confidentialité. | AO1: Q14. La nature opaque des modèles d'IA générative (« boîte noire ») rend difficile de comprendre et de justifier comment les résultats ont été produits en audit. | AP1: Q15. Je m'inquiète d'être tenu pour responsable si l'IAG fait une erreur dans mon travail. | AQ1: Q16 . Quel est le niveau d'importance de ce risque pour votre travail? [Hallucinations : Production d'informations fausses mais crédibles.] | AR1: Q16 . Quel est le niveau d'importance de ce risque pour votre travail? [Confidentialité : Risque de fuite ou d'usage illicite de données clients.] | AS1: Q16 . Quel est le niveau d'importance de ce risque pour votre travail? [Boîte noire : Opacité des algorithmes et difficulté à justifier un résultat.] | AT1: Q16 . Quel est le niveau d'importance de ce risque pour votre travail? [Responsabilité : Risque d'assumer seul les erreurs commises par l'IA.] | AU1: Q17. Ces risques m'empêchent d'augmenter mon usage de l'IAG | AV1: Q18. Si les risques étaient éliminés, j'utiliserais davantage l'IAG | AW1: Q19. Votre niveau global de formation (interne ou auto-apprentissage) ? | AX1: Q20. "Je me sens capable d'orienter les réponses de l'IAG pour limiter les risques d'imprécisions ou d'erreurs." | AY1: Q21. "Je me sens capable d'identifier les erreurs générées par l'IAG." | AZ1: Q22. Lorsque l’IAG vous propose un résultat, il vous arrive de vous y fier sans vérifier en détail par vous‑même. | BA1: Q23. À quelle fréquence vérifiez vous la source d'origine face à une réponse de l'IAG ? | BB1: Q24. Estimez-vous que votre jugement professionnel en audit reste fort malgré l'utilisation régulière de l'IAG? | BC1: Q25. "Il m'arrive de remettre en question mon jugement professionnel quand l'IAG me propose une conclusion différente de la mienne" | BD1: Q26. "En pratique, il m'arrive de conclure avant d'avoir réuni toutes les preuves que je jugerais idéalement nécessaires" | BE1: Q27. Prévoyez vous d'augmenter votre usage de l'IAG dans les 6 prochains mois ? | BF1: Q28. Probabilité d'augmenter votre usage de l'IAG si vous receviez une formation à l'avenir ? | BG1: Q29. Pour garantir la précision statistique des résultats, merci de sélectionner la réponse 'Neutre' ici. | BH1: Q30. Quelle est votre perception sur l'équilibre bénéfices-risques de l'IAG en audit ? | BI1: Q31. Tranche d'âge | BJ1: Q32. Genre | BK1: Q33. Votre niveau hiérarchique | BL1: Q34. Votre nombre d'années d'expérience | BM1: Q35. Votre cœur de métier | BN1: Q36. Taille de votre cabinet | BO1: Avant de terminer, souhaitez-vous partager votre opinion ou vos impressions sur l’IA générative ? (facultatif)
A2: 46035.409 | B2: 3. Rarement (1 à 3 fois par mois) | C2: Outils grand public (ex: ChatGPT, Gemini ) | E2: Version grand public | F2: Version grand public | G2: Version grand public | J2: Version entreprise | M2: Reformulation ou traduction de documents | N2: De manière VOLONTAIRE (vous avez choisi vous-même) | O2: 1. Pas du tout utile | P2: 2. Peu utile | Q2: 2. Peu utile | R2: 1. Pas du tout utile | S2: 2. Peu utile | T2: 1. Pas du tout utile | U2: 1. Pas du tout utile | V2: 1. Pas du tout utile | W2: 2. Peu utile | X2: 2. Peu utile | Y2: 1. Pas du tout utile | Z2: 1. Pas du tout utile | AA2: 2. Peu utile | AB2: 1. Pas du tout utile | AC2: 1. Pas du tout utile | AD2: 1. Pas du tout utile | AE2: 1. Pas du tout utile | AF2: 2. Peu utile | AG2: 2. Peu utile | AH2: 1. Pas du tout utile | AI2: 2 | AJ2: 5. Plutôt facile (Assez intuitif) | AK2: 5. Plutôt d'accord (S'intègre assez bien) | AL2: 2 | AM2: 7 | AN2: 7 | AO2: 4 | AP2: 7 | AQ2: 5. Très important | AR2: 5. Très important | AS2: 4. Important | AT2: 5. Très important | AU2: 4 | AV2: 5 | AW2: 4. Moyenne (Environ une journée de formation cumulée) | AX2: 7 | AY2: 7 | AZ2: 2. En désaccord (Je contrôle la quasi-totalité des éléments) | BA2: 6 | BB2: 7 | BC2: 1 | BD2: 1 | BE2: Je compte réduire l’utilisation de l’IA | BF2: 1 | BG2: 4. Neutre | BH2: 1 | BI2: 26-35 | BJ2: Femme | BK2: Senior | BL2: 2 - 3 ans | BM2: Audit Financier | BN2: Cabinet international | BO2: L’IA est une bonne tentative mais le cerveau humain reste meilleur, dans un métier d’audit financier qui est très sensible on peut utiliser l’IA pour nous informer sur des lois, de la comptabilité, des méthodes de calculs etc mais jamais pour émettre un rapport d’audit, le comissaire aux compte est un professionnel dans son domaine qui a fait plusieurs années d’études et d’expérience impossible qu’un rebot soit plus performant que lui.
A3: 46036.706 | B3: 5. Régulièrement (Plusieurs fois par semaine) | C3: Outils fournis/agréés par le cabinet (ex: Copilot sécurisé) | E3: Version grand public | M3: Recherche d'informations ou de points techniques, Rédaction (rapports, synthèses, notes, mails), Reformulation ou traduction de documents | N3: De manière VOLONTAIRE (vous avez choisi vous-même) | O3: 1. Pas du tout utile | P3: 2. Peu utile | Q3: 5. Très utile | R3: 2. Peu utile | S3: 2. Peu utile | T3: 1. Pas du tout utile | U3: 1. Pas du tout utile | V3: 1. Pas du tout utile | W3: 1. Pas du tout utile | X3: 3. Neutre | Y3: 1. Pas du tout utile | Z3: 2. Peu utile | AA3: 5. Très utile | AB3: 2. Peu utile | AC3: 2. Peu utile | AD3: 1. Pas du tout utile | AE3: 1. Pas du tout utile | AF3: 1. Pas du tout utile | AG3: 1. Pas du tout utile | AH3: 3. Neutre | AI3: 6 | AJ3: 5. Plutôt facile (Assez intuitif) | AK3: 6. D'accord (S'intègre facilement) | AL3: 4 | AM3: 7 | AN3: 4 | AO3: 7 | AP3: 7 | AQ3: 5. Très important | AR3: 4. Important | AS3: 4. Important | AT3: 5. Très important | AU3: 4 | AV3: 4 | AW3: 3. Faible (Moins de 5 heures de formation au total) | AX3: 5 | AY3: 5 | AZ3: 3. Plutôt en désaccord (Je procède à une revue importante) | BA3: 5 | BB3: 6 | BC3: 5 | BD3: 3 | BE3: Oui | BF3: 5 | BG3: 4. Neutre | BH3: 6 | BI3: 18-25 | BJ3: Homme | BK3: Junior | BL3: Moins de 2 ans | BM3: Audit Financier | BN3: Cabinet international
A4: 46036.707 | B4: 5. Régulièrement (Plusieurs fois par semaine) | C4: Outils fournis/agréés par le cabinet (ex: Copilot sécurisé) | E4: Version entreprise | F4: Version grand public | K4: Version entreprise | M4: Rapprochement/Comparaison de documents, Correction et mise en cohérence de documents, Rédaction (rapports, synthèses, notes, mails), Préparation de données (format, structuration, harmonisation des valeurs) | N4: De manière VOLONTAIRE (vous avez choisi vous-même) | O4: 4. Utile | P4: 4. Utile | Q4: 5. Très utile | R4: 2. Peu utile | S4: 2. Peu utile | T4: 3. Neutre | U4: 3. Neutre | V4: 3. Neutre | W4: 3. Neutre | X4: 4. Utile | Y4: 4. Utile | Z4: 4. Utile | AA4: 4. Utile | AB4: 4. Utile | AC4: 2. Peu utile | AD4: 2. Peu utile | AE4: 2. Peu utile | AF4: 2. Peu utile | AG4: 4. Utile | AH4: 4. Utile | AI4: 7 | AJ4: 5. Plutôt facile (Assez intuitif) | AK4: 1. Tout à fait en désaccord (Friction totale / Inutilisable) | AL4: 5 | AM4: 1 | AN4: 4 | AO4: 4 | AP4: 6 | AQ4: 4. Important | AR4: 4. Important | AS4: 4. Important | AT4: 4. Important | AU4: 5 | AV4: 5 | AW4: 5. Solide (Plusieurs jours de formation ou modules suivis) | AX4: 6 | AY4: 5 | AZ4: 4. Neutre (Le niveau de vérification dépend de la complexité) | BA4: 5 | BB4: 4 | BC4: 6 | BD4: 4 | BE4: Oui | BF4: 7 | BG4: 4. Neutre | BH4: 3 | BI4: 18-25 | BJ4: Femme | BK4: Junior | BL4: Moins de 2 ans | BM4: Audit Financier | BN4: Cabinet international
A5: 46036.712 | B5: 7. Très fréquemment (Plusieurs fois par jour) | C5: Usage mix des deux | E5: Version entreprise | F5: Version grand public | G5: Version grand public | K5: Version entreprise | M5: Automatisation et création de scripts (SQL, VBA), Recherche d'informations ou de points techniques, Analyse de données et génération d'insights, Rédaction (rapports, synthèses, notes, mails), Évaluation du contrôle interne, Préparation de données (format, structuration, harmonisation des valeurs) | N5: De manière VOLONTAIRE (vous avez choisi vous-même) | O5: 5. Très utile | P5: 5. Très utile | Q5: 5. Très utile | R5: 3. Neutre | S5: 5. Très utile | T5: 3. Neutre | U5: 3. Neutre | V5: 3. Neutre | W5: 4. Utile | X5: 5. Très utile | Y5: 5. Très utile | Z5: 4. Utile | AA5: 5. Très utile | AB5: 4. Utile | AC5: 5. Très utile | AD5: 3. Neutre | AE5: 3. Neutre | AF5: 3. Neutre | AG5: 3. Neutre | AH5: 5. Très utile | AI5: 7 | AJ5: 6. Facile (Maîtrise rapide) | AK5: 6. D'accord (S'intègre facilement) | AL5: 4 | AM5: 4 | AN5: 7 | AO5: 5 | AP5: 6 | AQ5: 3. Moyennement important | AR5: 5. Très important | AS5: 4. Important | AT5: 4. Important | AU5: 4 | AV5: 6 | AW5: 3. Faible (Moins de 5 heures de formation au total) | AX5: 5 | AY5: 4 | AZ5: 4. Neutre (Le niveau de vérification dépend de la complexité) | BA5: 4 | BB5: 6 | BC5: 6 | BD5: 4 | BE5: Oui | BF5: 6 | BG5: 4. Neutre | BH5: 5 | BI5: 18-25 | BJ5: Homme | BK5: Junior | BL5: Moins de 2 ans | BM5: Audit IT | BN5: Cabinet international
A6: 46036.713 | B6: 5. Régulièrement (Plusieurs fois par semaine) | C6: Outils fournis/agréés par le cabinet (ex: Copilot sécurisé) | E6: Version entreprise | M6: Reformulation ou traduction de documents, Préparation de données (format, structuration, harmonisation des valeurs), Recherche d'informations ou de points techniques | N6: De manière VOLONTAIRE (vous avez choisi vous-même) | O6: 5. Très utile | P6: 5. Très utile | Q6: 4. Utile | R6: 5. Très utile | S6: 5. Très utile | T6: 4. Utile | U6: 1. Pas du tout utile | V6: 4. Utile | W6: 4. Utile | X6: 5. Très utile | Y6: 5. Très utile | Z6: 5. Très utile | AA6: 5. Très utile | AB6: 5. Très utile | AC6: 5. Très utile | AD6: 5. Très utile | AE6: 5. Très utile | AF6: 5. Très utile | AG6: 5. Très utile | AH6: 5. Très utile | AI6: 6 | AJ6: 6. Facile (Maîtrise rapide) | AK6: 6. D'accord (S'intègre facilement) | AL6: 3 | AM6: 6 | AN6: 6 | AO6: 6 | AP6: 4 | AQ6: 5. Très important | AR6: 5. Très important | AS6: 5. Très important | AT6: 5. Très important | AU6: 6 | AV6: 7 | AW6: 1. Aucune | AX6: 5 | AY6: 6 | AZ6: 5. Plutôt d'accord (Je vérifie uniquement les points clés) | BA6: 4 | BB6: 6 | BC6: 5 | BD6: 2 | BE6: aucune idée | BF6: 4 | BG6: 4. Neutre | BH6: 5 | BI6: 18-25 | BJ6: Homme | BK6: Stagiaire | BL6: Moins de 2 ans | BM6: Audit Financier | BN6: Cabinet international
A7: 46036.716 | B7: 5. Régulièrement (Plusieurs fois par semaine) | C7: Outils fournis/agréés par le cabinet (ex: Copilot sécurisé) | E7: Version entreprise | M7: Reformulation ou traduction de documents, Rédaction (rapports, synthèses, notes, mails), Préparation de données (format, structuration, harmonisation des valeurs), Correction et mise en cohérence de documents | N7: De manière VOLONTAIRE (vous avez choisi vous-même) | O7: 3. Neutre | P7: 5. Très utile | Q7: 5. Très utile | R7: 3. Neutre | S7: 1. Pas du tout utile | T7: 1. Pas du tout utile | U7: 1. Pas du tout utile | V7: 1. Pas du tout utile | W7: 1. Pas du tout utile | X7: 4. Utile | Y7: 4. Utile | Z7: 5. Très utile | AA7: 5. Très utile | AB7: 3. Neutre | AC7: 1. Pas du tout utile | AD7: 1. Pas du tout utile | AE7: 1. Pas du tout utile | AF7: 1. Pas du tout utile | AG7: 1. Pas du tout utile | AH7: 1. Pas du tout utile | AI7: 5 | AJ7: 5. Plutôt facile (Assez intuitif) | AK7: 5. Plutôt d'accord (S'intègre assez bien) | AL7: 5 | AM7: 5 | AN7: 5 | AO7: 4 | AP7: 2 | AQ7: 5. Très important | AR7: 5. Très important | AS7: 5. Très important | AT7: 5. Très important | AU7: 4 | AV7: 5 | AW7: 4. Moyenne (Environ une journée de formation cumulée) | AX7: 6 | AY7: 6 | AZ7: 2. En désaccord (Je contrôle la quasi-totalité des éléments) | BA7: 6 | BB7: 6 | BC7: 5 | BD7: 2 | BE7: Non | BF7: 4 | BG7: 4. Neutre | BH7: 4 | BI7: 18-25 | BJ7: Femme | BK7: Junior | BL7: Moins de 2 ans | BM7: Audit Financier | BN7: Cabinet international
A8: 46036.721 | B8: 3. Rarement (1 à 3 fois par mois) | C8: Outils fournis/agréés par le cabinet (ex: Copilot sécurisé) | E8: Version entreprise | M8: Formules Excel, aide pour l'utilisation des outils Microsoft | N8: De manière RECOMMANDÉE (cabinet encourage, mais facultatif) | O8: 3. Neutre | P8: 5. Très utile | Q8: 4. Utile | R8: 4. Utile | S8: 3. Neutre | T8: 1. Pas du tout utile | U8: 1. Pas du tout utile | V8: 1. Pas du tout utile | W8: 3. Neutre | X8: 4. Utile | Y8: 3. Neutre | Z8: 4. Utile | AA8: 4. Utile | AB8: 4. Utile | AC8: 3. Neutre | AD8: 1. Pas du tout utile | AE8: 1. Pas du tout utile | AF8: 1. Pas du tout utile | AG8: 3. Neutre | AH8: 4. Utile | AI8: 5 | AJ8: 6. Facile (Maîtrise rapide) | AK8: 3. Plutôt en désaccord (Demande un effort conscient) | AL8: 6 | AM8: 7 | AN8: 6 | AO8: 6 | AP8: 2 | AQ8: 5. Très important | AR8: 5. Très important | AS8: 4. Important | AT8: 3. Moyennement important | AU8: 6 | AV8: 7 | AW8: 4. Moyenne (Environ une journée de formation cumulée) | AX8: 4 | AY8: 4 | AZ8: 2. En désaccord (Je contrôle la quasi-totalité des éléments) | BA8: 7 | BB8: 5 | BC8: 5 | BD8: 2 | BE8: Oui | BF8: 6 | BG8: 4. Neutre | BH8: 4 | BI8: 26-35 | BJ8: Femme | BK8: Junior | BL8: Moins de 2 ans | BM8: Audit Financier | BN8: Cabinet international
A9: 46036.725 | B9: 3. Rarement (1 à 3 fois par mois) | C9: Outils fournis/agréés par le cabinet (ex: Copilot sécurisé) | E9: Version entreprise | M9: Reformulation ou traduction de documents, Recherche d'informations ou de points techniques | N9: De manière RECOMMANDÉE (cabinet encourage, mais facultatif) | O9: 4. Utile | P9: 4. Utile | Q9: 2. Peu utile | R9: 2. Peu utile | S9: 3. Neutre | T9: 1. Pas du tout utile | U9: 1. Pas du tout utile | V9: 1. Pas du tout utile | W9: 2. Peu utile | X9: 4. Utile | Y9: 4. Utile | Z9: 3. Neutre | AA9: 2. Peu utile | AB9: 2. Peu utile | AC9: 2. Peu utile | AD9: 2. Peu utile | AE9: 1. Pas du tout utile | AF9: 2. Peu utile | AG9: 2. Peu utile | AH9: 4. Utile | AI9: 4 | AJ9: 6. Facile (Maîtrise rapide) | AK9: 5. Plutôt d'accord (S'intègre assez bien) | AL9: 3 | AM9: 7 | AN9: 3 | AO9: 7 | AP9: 7 | AQ9: 5. Très important | AR9: 5. Très important | AS9: 4. Important | AT9: 3. Moyennement important | AU9: 6 | AV9: 5 | AW9: 3. Faible (Moins de 5 heures de formation au total) | AX9: 5 | AY9: 5 | AZ9: 4. Neutre (Le niveau de vérification dépend de la complexité) | BA9: 5 | BB9: 4 | BC9: 5 | BD9: 2 | BE9: Non | BF9: 3 | BG9: 4. Neutre | BH9: 5 | BI9: 18-25 | BJ9: Homme | BK9: Alternant | BL9: Moins de 2 ans | BM9: Audit Financier | BN9: Cabinet international
A10: 46036.867 | B10: 4. Parfois (Environ une fois par semaine) | C10: Usage mix des deux | E10: Version entreprise | F10: Version grand public | M10: Revue d'estimations comptables (provisions, dépréciations), Reformulation ou traduction de documents, Rapprochement/Comparaison de documents, Aide à la décision, Rédaction (rapports, synthèses, notes, mails) | N10: De manière VOLONTAIRE (vous avez choisi vous-même) | O10: 2. Peu utile | P10: 4. Utile | Q10: 5. Très utile | R10: 3. Neutre | S10: 4. Utile | T10: 3. Neutre | U10: 3. Neutre | V10: 4. Utile | W10: 4. Utile | X10: 3. Neutre | Y10: 1. Pas du tout utile | Z10: 1. Pas du tout utile | AA10: 1. Pas du tout utile | AB10: 1. Pas du tout utile | AC10: 1. Pas du tout utile | AD10: 1. Pas du tout utile | AE10: 1. Pas du tout utile | AF10: 1. Pas du tout utile | AG10: 1. Pas du tout utile | AH10: 1. Pas du tout utile | AI10: 7 | AJ10: 7. Très facile (Instinctif / Sans aide) | AK10: 6. D'accord (S'intègre facilement) | AL10: 3 | AM10: 5 | AN10: 7 | AO10: 7 | AP10: 7 | AQ10: 4. Important | AR10: 4. Important | AS10: 4. Important | AT10: 4. Important | AU10: 5 | AV10: 7 | AW10: 6. Approfondie (Parcours certifiant ou auto-formation technique longue) | AX10: 4 | AY10: 4 | AZ10: 1. Pas du tout d’accord (Je vérifie systématiquement chaque détail) | BA10: 6 | BB10: 5 | BC10: 5 | BD10: 6 | BE10: Oui | BF10: 7 | BG10: 4. Neutre | BH10: NA | BI10: 18-25 | BJ10: Femme | BK10: Junior | BL10: Moins de 2 ans | BM10: Audit Financier | BN10: Cabinet international
A11: 46036.891 | B11: 4. Parfois (Environ une fois par semaine) | C11: Outils fournis/agréés par le cabinet (ex: Copilot sécurisé) | E11: Version entreprise | M11: Reformulation ou traduction de documents, Recherche d'informations ou de points techniques, Rédaction (rapports, synthèses, notes, mails) | N11: De manière VOLONTAIRE (vous avez choisi vous-même) | O11: 5. Très utile | P11: 4. Utile | Q11: 5. Très utile | R11: 3. Neutre | S11: 4. Utile | T11: 2. Peu utile | U11: 2. Peu utile | V11: 3. Neutre | W11: 3. Neutre | X11: 3. Neutre | Y11: 4. Utile | Z11: 5. Très utile | AA11: 5. Très utile | AB11: 3. Neutre | AC11: 4. Utile | AD11: 2. Peu utile | AE11: 2. Peu utile | AF11: 3. Neutre | AG11: 4. Utile | AH11: 3. Neutre | AI11: 7 | AJ11: 7. Très facile (Instinctif / Sans aide) | AK11: 5. Plutôt d'accord (S'intègre assez bien) | AL11: 3 | AM11: 7 | AN11: 7 | AO11: 1 | AP11: 7 | AQ11: 3. Moyennement important | AR11: 5. Très important | AS11: 1. Pas du tout important | AT11: 4. Important | AU11: 6 | AV11: 7 | AW11: 3. Faible (Moins de 5 heures de formation au total) | AX11: 5 | AY11: 6 | AZ11: 4. Neutre (Le niveau de vérification dépend de la complexité) | BA11: 5 | BB11: 6 | BC11: 2 | BD11: 2 | BE11: Oui | BF11: 7 | BG11: 4. Neutre | BH11: 5 | BI11: 18-25 | BJ11: Homme | BK11: Junior | BL11: Moins de 2 ans | BM11: Audit Financier | BN11: Cabinet local
A12: 46037.405 | B12: 7. Très fréquemment (Plusieurs fois par jour) | C12: Outils grand public (ex: ChatGPT, Gemini ) | F12: Version grand public | M12: Rédaction (rapports, synthèses, notes, mails), Préparation de données (format, structuration, harmonisation des valeurs), Correction et mise en cohérence de documents, Reformulation ou traduction de documents | N12: De manière VOLONTAIRE (vous avez choisi vous-même) | O12: 4. Utile | P12: 4. Utile | Q12: 5. Très utile | R12: 5. Très utile | S12: 3. Neutre | T12: 3. Neutre | U12: 3. Neutre | V12: 3. Neutre | W12: 4. Utile | X12: 5. Très utile | Y12: 4. Utile | Z12: 4. Utile | AA12: 5. Très utile | AB12: 5. Très utile | AC12: 3. Neutre | AD12: 3. Neutre | AE12: 3. Neutre | AF12: 3. Neutre | AG12: 4. Utile | AH12: 5. Très utile | AI12: 7 | AJ12: 7. Très facile (Instinctif / Sans aide) | AK12: 7. Tout à fait d'accord (Automatisme quotidien) | AL12: 4 | AM12: 6 | AN12: 4 | AO12: 4 | AP12: 1 | AQ12: 4. Important | AR12: 3. Moyennement important | AS12: 3. Moyennement important | AT12: 3. Moyennement important | AU12: 1 | AV12: 2 | AW12: 3. Faible (Moins de 5 heures de formation au total) | AX12: 7 | AY12: 6 | AZ12: 3. Plutôt en désaccord (Je procède à une revue importante) | BA12: 1 | BB12: 4 | BC12: 4 | BD12: 4 | BE12: Oui | BF12: 7 | BG12: 4. Neutre | BH12: 4 | BI12: +65 | BJ12: Homme | BK12: Manager | BL12: Plus de 10 ans | BM12: RECRUTEMENT | BN12: Cabinet local
A13: 46037.416 | B13: 7. Très fréquemment (Plusieurs fois par jour) | C13: Usage mix des deux | E13: Version entreprise | F13: Version grand public | G13: Version grand public | J13: Version entreprise | K13: Version entreprise | M13: Évaluation du contrôle interne, Automatisation et création de scripts (SQL, VBA), Reformulation ou traduction de documents, Rédaction (rapports, synthèses, notes, mails) | N13: De manière VOLONTAIRE (vous avez choisi vous-même) | O13: 1. Pas du tout utile | P13: 3. Neutre | Q13: 5. Très utile | R13: 5. Très utile | S13: 5. Très utile | T13: 3. Neutre | U13: 2. Peu utile | V13: 2. Peu utile | W13: 1. Pas du tout utile | X13: 3. Neutre | Y13: 4. Utile | Z13: 4. Utile | AA13: 4. Utile | AB13: 4. Utile | AC13: 5. Très utile | AD13: 2. Peu utile | AE13: 2. Peu utile | AF13: 4. Utile | AG13: 3. Neutre | AH13: 4. Utile | AI13: 5 | AJ13: 7. Très facile (Instinctif / Sans aide) | AK13: 6. D'accord (S'intègre facilement) | AL13: 5 | AM13: 7 | AN13: 7 | AO13: 7 | AP13: 7 | AQ13: 5. Très important | AR13: 5. Très important | AS13: 5. Très important | AT13: 5. Très important | AU13: 4 | AV13: 6 | AW13: 3. Faible (Moins de 5 heures de formation au total) | AX13: 6 | AY13: 6 | AZ13: 4. Neutre (Le niveau de vérification dépend de la complexité) | BA13: 7 | BB13: 7 | BC13: 7 | BD13: 2 | BE13: Oui | BF13: 7 | BG13: 4. Neutre | BH13: 7 | BI13: 18-25 | BJ13: Homme | BK13: Junior | BL13: 2 - 3 ans | BM13: Audit Financier | BN13: Cabinet local
A14: 46037.658 | B14: 7. Très fréquemment (Plusieurs fois par jour) | C14: Usage mix des deux | D14: Version grand public | E14: Version entreprise | F14: Version grand public, Version entreprise | G14: Version entreprise | I14: Version grand public | J14: Version entreprise | M14: Recherche d'informations ou de points techniques, Correction et mise en cohérence de documents, Analyse de données et génération d'insights, Rédaction (rapports, synthèses, notes, mails), Reformulation ou traduction de documents | N14: De manière RECOMMANDÉE (cabinet encourage, mais facultatif) | O14: 1. Pas du tout utile | P14: 4. Utile | Q14: 5. Très utile | R14: 5. Très utile | S14: 5. Très utile | T14: 3. Neutre | U14: 3. Neutre | V14: 3. Neutre | W14: 4. Utile | X14: 3. Neutre | Y14: 3. Neutre | Z14: 4. Utile | AA14: 5. Très utile | AB14: 4. Utile | AC14: 4. Utile | AD14: 3. Neutre | AE14: 3. Neutre | AF14: 3. Neutre | AG14: 3. Neutre | AH14: 3. Neutre | AI14: 7 | AJ14: 7. Très facile (Instinctif / Sans aide) | AK14: 7. Tout à fait d'accord (Automatisme quotidien) | AL14: 2 | AM14: 7 | AN14: 7 | AO14: 5 | AP14: 6 | AQ14: 5. Très important | AR14: 5. Très important | AS14: 4. Important | AT14: 4. Important | AU14: 1 | AV14: 4 | AW14: 6. Approfondie (Parcours certifiant ou auto-formation technique longue) | AX14: 7 | AY14: 7 | AZ14: 1. Pas du tout d’accord (Je vérifie systématiquement chaque détail) | BA14: 6 | BB14: 6 | BC14: 7 | BD14: 1 | BE14: Oui | BF14: 7 | BG14: 4. Neutre | BH14: 7 | BI14: 26-35 | BJ14: Homme | BK14: Senior Manager | BL14: Plus de 10 ans | BM14: Audit IT | BN14: Cabinet international | BO14: Pour moi l'IA générative est comme un super stagiaire : il ne peut pas être responsable et on doit vérifier son travail (car il y a probablement des erreurs). Le plus grand risque selon moi est pour les personnes avec peu d'expérience "métier", qui vont s'appuyer sur l'IA sans être en capacité d'identifier les erreurs.
A15: 46038.388 | B15: 6. Quotidiennement (Une fois par jour) | C15: Outils fournis/agréés par le cabinet (ex: Copilot sécurisé) | E15: Version entreprise | M15: Reformulation ou traduction de documents, Rédaction (rapports, synthèses, notes, mails), Automatisation et création de scripts (SQL, VBA) | N15: De manière RECOMMANDÉE (cabinet encourage, mais facultatif) | O15: 5. Très utile | P15: 5. Très utile | Q15: 5. Très utile | R15: 3. Neutre | S15: 5. Très utile | T15: 2. Peu utile | U15: 2. Peu utile | V15: 2. Peu utile | W15: 3. Neutre | X15: 4. Utile | Y15: 3. Neutre | Z15: 5. Très utile | AA15: 5. Très utile | AB15: 4. Utile | AC15: 5. Très utile | AD15: 3. Neutre | AE15: 1. Pas du tout utile | AF15: 2. Peu utile | AG15: 3. Neutre | AH15: 4. Utile | AI15: 6 | AJ15: 7. Très facile (Instinctif / Sans aide) | AK15: 6. D'accord (S'intègre facilement) | AL15: 2 | AM15: 7 | AN15: 4 | AO15: 7 | AP15: 6 | AQ15: 4. Important | AR15: 5. Très important | AS15: 3. Moyennement important | AT15: 5. Très important | AU15: 4 | AV15: 7 | AW15: 6. Approfondie (Parcours certifiant ou auto-formation technique longue) | AX15: 5 | AY15: 3 | AZ15: 4. Neutre (Le niveau de vérification dépend de la complexité) | BA15: 5 | BB15: 4 | BC15: 6 | BD15: 3 | BE15: Non | BF15: 2 | BG15: 4. Neutre | BH15: 6 | BI15: 18-25 | BJ15: Homme | BK15: Junior | BL15: 6 - 7 ans | BM15: Audit Financier | BN15: Cabinet régional
A16: 46038.531 | B16: 5. Régulièrement (Plusieurs fois par semaine) | C16: Usage mix des deux | E16: Version grand public | M16: Recherche d'informations ou de points techniques, Aide à la décision, Rédaction (rapports, synthèses, notes, mails), Reformulation ou traduction de documents, Correction et mise en cohérence de documents | N16: De manière RECOMMANDÉE (cabinet encourage, mais facultatif) | O16: 1. Pas du tout utile | P16: 5. Très utile | Q16: 5. Très utile | R16: 1. Pas du tout utile | S16: 1. Pas du tout utile | T16: 1. Pas du tout utile | U16: 1. Pas du tout utile | V16: 1. Pas du tout utile | W16: 5. Très utile | X16: 3. Neutre | Y16: 1. Pas du tout utile | Z16: 1. Pas du tout utile | AA16: 5. Très utile | AB16: 4. Utile | AC16: 1. Pas du tout utile | AD16: 1. Pas du tout utile | AE16: 1. Pas du tout utile | AF16: 1. Pas du tout utile | AG16: 5. Très utile | AH16: 3. Neutre | AI16: 5 | AJ16: 6. Facile (Maîtrise rapide) | AK16: 6. D'accord (S'intègre facilement) | AL16: 3 | AM16: 6 | AN16: 4 | AO16: 6 | AP16: 5 | AQ16: 5. Très important | AR16: 3. Moyennement important | AS16: 3. Moyennement important | AT16: 3. Moyennement important | AU16: 2 | AV16: 7 | AW16: 5. Solide (Plusieurs jours de formation ou modules suivis) | AX16: 5 | AY16: 5 | AZ16: 5. Plutôt d'accord (Je vérifie uniquement les points clés) | BA16: 5 | BB16: 5 | BC16: 4 | BD16: 6 | BE16: Oui | BF16: 6 | BG16: 6. D’accord | BH16: 5 | BI16: 18-25 | BJ16: Homme | BK16: Junior | BL16: Moins de 2 ans | BM16: Audit Financier | BN16: Cabinet local
A17: 46038.983 | B17: 3. Rarement (1 à 3 fois par mois) | C17: Usage mix des deux | F17: Version grand public | G17: Version grand public | H17: Version grand public | K17: Version entreprise | M17: Rédaction (rapports, synthèses, notes, mails), Recherche d'informations ou de points techniques, Revue d'estimations comptables (provisions, dépréciations), Évaluation du contrôle interne, Aide à la décision | N17: De manière VOLONTAIRE (vous avez choisi vous-même) | O17: 3. Neutre | P17: 5. Très utile | Q17: 5. Très utile | R17: 4. Utile | S17: 3. Neutre | T17: 2. Peu utile | U17: 2. Peu utile | V17: 4. Utile | W17: 4. Utile | X17: 3. Neutre | Y17: 2. Peu utile | Z17: 4. Utile | AA17: 5. Très utile | AB17: 5. Très utile | AC17: 4. Utile | AD17: 3. Neutre | AE17: 3. Neutre | AF17: 3. Neutre | AG17: 4. Utile | AH17: 3. Neutre | AI17: 4 | AJ17: 4. Ni facile, ni difficile (Prise en main normale) | AK17: 5. Plutôt d'accord (S'intègre assez bien) | AL17: 6 | AM17: 6 | AN17: 7 | AO17: 6 | AP17: 3 | AQ17: 5. Très important | AR17: 5. Très important | AS17: 3. Moyennement important | AT17: 3. Moyennement important | AU17: 4 | AV17: 5 | AW17: 5. Solide (Plusieurs jours de formation ou modules suivis) | AX17: 6 | AY17: 6 | AZ17: 4. Neutre (Le niveau de vérification dépend de la complexité) | BA17: 6 | BB17: 4 | BC17: 3 | BD17: 5 | BE17: Non | BF17: 7 | BG17: 4. Neutre | BH17: 3 | BI17: 18-25 | BJ17: Femme | BK17: Junior | BL17: 2 - 3 ans | BM17: Audit Financier | BN17: Cabinet international
A18: 46039.411 | B18: 7. Très fréquemment (Plusieurs fois par jour) | C18: Outils fournis/agréés par le cabinet (ex: Copilot sécurisé) | E18: Version entreprise | K18: Version entreprise | M18: Reformulation ou traduction de documents, Rédaction (rapports, synthèses, notes, mails), Automatisation et création de scripts (SQL, VBA) | N18: De manière VOLONTAIRE (vous avez choisi vous-même) | O18: 4. Utile | P18: 5. Très utile | Q18: 4. Utile | R18: 2. Peu utile | S18: 5. Très utile | T18: 3. Neutre | U18: 3. Neutre | V18: 2. Peu utile | W18: 3. Neutre | X18: 4. Utile | Y18: 4. Utile | Z18: 3. Neutre | AA18: 3. Neutre | AB18: 2. Peu utile | AC18: 5. Très utile | AD18: 3. Neutre | AE18: 2. Peu utile | AF18: 2. Peu utile | AG18: 2. Peu utile | AH18: 4. Utile | AI18: 5 | AJ18: 6. Facile (Maîtrise rapide) | AK18: 6. D'accord (S'intègre facilement) | AL18: 3 | AM18: 7 | AN18: 7 | AO18: 3 | AP18: 7 | AQ18: 4. Important | AR18: 5. Très important | AS18: 3. Moyennement important | AT18: 4. Important | AU18: 5 | AV18: 7 | AW18: 4. Moyenne (Environ une journée de formation cumulée) | AX18: 6 | AY18: 6 | AZ18: 3. Plutôt en désaccord (Je procède à une revue importante) | BA18: 4 | BB18: 5 | BC18: 4 | BD18: 5 | BE18: Oui | BF18: 5 | BG18: 4. Neutre | BH18: 6 | BI18: 26-35 | BJ18: Homme | BK18: Senior | BL18: 4 - 5 ans | BM18: Audit IT | BN18: Cabinet international
A19: 46040.715 | B19: 5. Régulièrement (Plusieurs fois par semaine) | C19: Outils grand public (ex: ChatGPT, Gemini ) | D19: Version grand public | E19: Version grand public | F19: Version entreprise | G19: Version grand public | H19: Version grand public | I19: Version grand public | J19: Version grand public | K19: Version entreprise | L19: Version grand public | M19: Rapprochement/Comparaison de documents, Reformulation ou traduction de documents, Correction et mise en cohérence de documents, Évaluation du contrôle interne, Préparation de données (format, structuration, harmonisation des valeurs), Recherche d'informations ou de points techniques, Rédaction (rapports, synthèses, notes, mails) | N19: De manière VOLONTAIRE (vous avez choisi vous-même) | O19: 4. Utile | P19: 5. Très utile | Q19: 4. Utile | R19: 5. Très utile | S19: 3. Neutre | T19: 4. Utile | U19: 1. Pas du tout utile | V19: 3. Neutre | W19: 5. Très utile | X19: 5. Très utile | Y19: 5. Très utile | Z19: 5. Très utile | AA19: 4. Utile | AB19: 5. Très utile | AC19: 3. Neutre | AD19: 3. Neutre | AE19: 1. Pas du tout utile | AF19: 2. Peu utile | AG19: 4. Utile | AH19: 4. Utile | AI19: 6 | AJ19: 5. Plutôt facile (Assez intuitif) | AK19: 5. Plutôt d'accord (S'intègre assez bien) | AL19: 6 | AM19: 5 | AN19: 4 | AO19: 3 | AP19: 2 | AQ19: 5. Très important | AR19: 5. Très important | AS19: 4. Important | AT19: 4. Important | AU19: 2 | AV19: 4 | AW19: 4. Moyenne (Environ une journée de formation cumulée) | AX19: 5 | AY19: 5 | AZ19: 2. En désaccord (Je contrôle la quasi-totalité des éléments) | BA19: 6 | BB19: 6 | BC19: 7 | BD19: 6 | BE19: Oui | BF19: 6 | BG19: 4. Neutre | BH19: 6 | BI19: 26-35 | BJ19: Homme | BK19: Senior | BL19: 2 - 3 ans | BM19: Audit Financier | BN19: Cabinet international
A20: 46040.793 | B20: 5. Régulièrement (Plusieurs fois par semaine) | C20: Outils fournis/agréés par le cabinet (ex: Copilot sécurisé) | K20: Version entreprise | M20: Analyse de données et génération d'insights, Rapprochement/Comparaison de documents, Recherche d'informations ou de points techniques, Préparation de données (format, structuration, harmonisation des valeurs), Reformulation ou traduction de documents, Aide à la décision | N20: De manière VOLONTAIRE (vous avez choisi vous-même) | O20: 4. Utile | P20: 4. Utile | Q20: 3. Neutre | R20: 4. Utile | S20: 4. Utile | T20: 3. Neutre | U20: 3. Neutre | V20: 3. Neutre | W20: 4. Utile | X20: 4. Utile | Y20: 4. Utile | Z20: 4. Utile | AA20: 4. Utile | AB20: 4. Utile | AC20: 4. Utile | AD20: 3. Neutre | AE20: 3. Neutre | AF20: 3. Neutre | AG20: 4. Utile | AH20: 4. Utile | AI20: 2 | AJ20: 6. Facile (Maîtrise rapide) | AK20: 6. D'accord (S'intègre facilement) | AL20: 6 | AM20: 6 | AN20: 7 | AO20: 6 | AP20: 2 | AQ20: 5. Très important | AR20: 5. Très important | AS20: 5. Très important | AT20: 5. Très important | AU20: 5 | AV20: 7 | AW20: 6. Approfondie (Parcours certifiant ou auto-formation technique longue) | AX20: 6 | AY20: 6 | AZ20: 3. Plutôt en désaccord (Je procède à une revue importante) | BA20: 6 | BB20: 6 | BC20: 6 | BD20: 6 | BE20: Oui | BF20: 6 | BG20: 6. D’accord | BH20: 6 | BI20: 46-55 | BJ20: Homme | BK20: Associé | BL20: Plus de 10 ans | BM20: Audit Financier, Expertise comptable | BN20: Cabinet international
A21: 46041.502 | B21: 5. Régulièrement (Plusieurs fois par semaine) | C21: Outils fournis/agréés par le cabinet (ex: Copilot sécurisé) | E21: Version entreprise | M21: Rédaction (rapports, synthèses, notes, mails), Reformulation ou traduction de documents, Recherche d'informations ou de points techniques, Revue d'estimations comptables (provisions, dépréciations), Préparation de données (format, structuration, harmonisation des valeurs) | N21: De manière RECOMMANDÉE (cabinet encourage, mais facultatif) | O21: 4. Utile | P21: 5. Très utile | Q21: 5. Très utile | R21: 2. Peu utile | S21: 4. Utile | T21: 4. Utile | U21: 1. Pas du tout utile | V21: 3. Neutre | W21: 4. Utile | X21: 4. Utile | Y21: 4. Utile | Z21: 2. Peu utile | AA21: 2. Peu utile | AB21: 2. Peu utile | AC21: 4. Utile | AD21: 3. Neutre | AE21: 2. Peu utile | AF21: 3. Neutre | AG21: 3. Neutre | AH21: 3. Neutre | AI21: 6 | AJ21: 6. Facile (Maîtrise rapide) | AK21: 6. D'accord (S'intègre facilement) | AL21: 6 | AM21: 5 | AN21: 7 | AO21: 6 | AP21: 6 | AQ21: 4. Important | AR21: 4. Important | AS21: 3. Moyennement important | AT21: 3. Moyennement important | AU21: 6 | AV21: 5 | AW21: 4. Moyenne (Environ une journée de formation cumulée) | AX21: 5 | AY21: 5 | AZ21: 5. Plutôt d'accord (Je vérifie uniquement les points clés) | BA21: 6 | BB21: 5 | BC21: 5 | BD21: 5 | BE21: Oui | BF21: 6 | BG21: 5. Plutôt d’accord | BH21: 6 | BI21: 18-25 | BJ21: Homme | BK21: Junior | BL21: Moins de 2 ans | BM21: Audit Financier | BN21: Cabinet international
A22: 46042.408 | B22: 4. Parfois (Environ une fois par semaine) | C22: Outils fournis/agréés par le cabinet (ex: Copilot sécurisé) | E22: Version entreprise | G22: Version grand public | M22: Rédaction (rapports, synthèses, notes, mails), Reformulation ou traduction de documents, Recherche d'informations ou de points techniques | N22: De manière VOLONTAIRE (vous avez choisi vous-même) | O22: 4. Utile | P22: 4. Utile | Q22: 4. Utile | R22: 4. Utile | S22: 3. Neutre | T22: 4. Utile | U22: 2. Peu utile | V22: 4. Utile | W22: 3. Neutre | X22: 3. Neutre | Y22: 4. Utile | Z22: 4. Utile | AA22: 4. Utile | AB22: 4. Utile | AC22: 3. Neutre | AD22: 4. Utile | AE22: 2. Peu utile | AF22: 4. Utile | AG22: 3. Neutre | AH22: 3. Neutre | AI22: 4 | AJ22: 4. Ni facile, ni difficile (Prise en main normale) | AK22: 2. En désaccord (Difficile à intégrer au métier) | AL22: 6 | AM22: 7 | AN22: 7 | AO22: 3 | AP22: 5 | AQ22: 5. Très important | AR22: 5. Très important | AS22: 4. Important | AT22: 3. Moyennement important | AU22: 6 | AV22: 7 | AW22: 6. Approfondie (Parcours certifiant ou auto-formation technique longue) | AX22: 5 | AY22: 5 | AZ22: 3. Plutôt en désaccord (Je procède à une revue importante) | BA22: 6 | BB22: 4 | BC22: 5 | BD22: 2 | BE22: Conditionné à la politique du cabinet | BF22: 6 | BG22: 4. Neutre | BH22: 5 | BI22: 26-35 | BJ22: Homme | BK22: Superviseur | BL22: 6 - 7 ans | BM22: Audit Financier | BN22: National et membre d'un réseau
A23: 46043.86 | B23: 5. Régulièrement (Plusieurs fois par semaine) | C23: Outils grand public (ex: ChatGPT, Gemini ) | F23: Version entreprise | M23: Rédaction (rapports, synthèses, notes, mails), Analyse de données et génération d'insights, Reformulation ou traduction de documents, Recherche d'informations ou de points techniques | N23: De manière RECOMMANDÉE (cabinet encourage, mais facultatif) | O23: 4. Utile | P23: 4. Utile | Q23: 5. Très utile | R23: 2. Peu utile | S23: 3. Neutre | T23: 3. Neutre | U23: 3. Neutre | V23: 2. Peu utile | W23: 2. Peu utile | X23: 5. Très utile | Y23: 5. Très utile | Z23: 5. Très utile | AA23: 5. Très utile | AB23: 3. Neutre | AC23: 3. Neutre | AD23: 3. Neutre | AE23: 3. Neutre | AF23: 3. Neutre | AG23: 2. Peu utile | AH23: 5. Très utile | AI23: 6 | AJ23: 7. Très facile (Instinctif / Sans aide) | AK23: 6. D'accord (S'intègre facilement) | AL23: 3 | AM23: 5 | AN23: 6 | AO23: 5 | AP23: 2 | AQ23: 4. Important | AR23: 5. Très important | AS23: 3. Moyennement important | AT23: 1. Pas du tout important | AU23: 1 | AV23: 7 | AW23: 6. Approfondie (Parcours certifiant ou auto-formation technique longue) | AX23: 5 | AY23: 4 | AZ23: 4. Neutre (Le niveau de vérification dépend de la complexité) | BA23: 5 | BB23: 6 | BC23: 5 | BD23: 3 | BE23: Oui | BF23: 6 | BG23: 4. Neutre | BH23: 4 | BI23: 26-35 | BJ23: Femme | BK23: Senior | BL23: 4 - 5 ans | BM23: Audit Financier, Audit Interne, Audit acquisition | BN23: Cabinet local
A24: 46047.149 | B24: 7. Très fréquemment (Plusieurs fois par jour) | C24: Usage mix des deux | F24: Version grand public | M24: Correction et mise en cohérence de documents, Rapprochement/Comparaison de documents, Détermination du seuil de signification, Évaluation du contrôle interne, Recherche d'informations ou de points techniques, Rédaction (rapports, synthèses, notes, mails), Préparation de données (format, structuration, harmonisation des valeurs), Automatisation et création de scripts (SQL, VBA), Reformulation ou traduction de documents | N24: De manière VOLONTAIRE (vous avez choisi vous-même) | O24: 3. Neutre | P24: 3. Neutre | Q24: 3. Neutre | R24: 2. Peu utile | S24: 3. Neutre | T24: 3. Neutre | U24: 3. Neutre | V24: 3. Neutre | W24: 1. Pas du tout utile | X24: 3. Neutre | Y24: 3. Neutre | Z24: 3. Neutre | AA24: 3. Neutre | AB24: 1. Pas du tout utile | AC24: 3. Neutre | AD24: 3. Neutre | AE24: 3. Neutre | AF24: 1. Pas du tout utile | AG24: 1. Pas du tout utile | AH24: 3. Neutre | AI24: 7 | AJ24: 6. Facile (Maîtrise rapide) | AK24: 7. Tout à fait d'accord (Automatisme quotidien) | AL24: 2 | AM24: 7 | AN24: 1 | AO24: 7 | AP24: 7 | AQ24: 3. Moyennement important | AR24: 3. Moyennement important | AS24: 1. Pas du tout important | AT24: 1. Pas du tout important | AU24: 7 | AV24: 7 | AW24: 4. Moyenne (Environ une journée de formation cumulée) | AX24: 7 | AY24: 7 | AZ24: 4. Neutre (Le niveau de vérification dépend de la complexité) | BA24: 4 | BB24: 7 | BC24: 7 | BD24: 1 | BE24: Non | BF24: 7 | BG24: 4. Neutre | BH24: 7 | BI24: 46-55 | BJ24: Homme | BK24: Manager | BL24: Plus de 10 ans | BM24: Audit Financier, Audit IT, Audit Interne | BN24: Cabinet international
A25: 46047.747 | B25: 3. Rarement (1 à 3 fois par mois) | C25: Usage mix des deux | E25: Version entreprise | F25: Version grand public | M25: Recherche d'informations ou de points techniques, Rédaction (rapports, synthèses, notes, mails) | N25: De manière VOLONTAIRE (vous avez choisi vous-même) | O25: 5. Très utile | P25: 2. Peu utile | Q25: 4. Utile | R25: 5. Très utile | S25: 4. Utile | T25: 4. Utile | U25: 1. Pas du tout utile | V25: 1. Pas du tout utile | W25: 1. Pas du tout utile | X25: 1. Pas du tout utile | Y25: 5. Très utile | Z25: 4. Utile | AA25: 4. Utile | AB25: 5. Très utile | AC25: 5. Très utile | AD25: 4. Utile | AE25: 2. Peu utile | AF25: 2. Peu utile | AG25: 2. Peu utile | AH25: 4. Utile | AI25: 5 | AJ25: 6. Facile (Maîtrise rapide) | AK25: 3. Plutôt en désaccord (Demande un effort conscient) | AL25: 3 | AM25: 7 | AN25: 7 | AO25: 7 | AP25: 7 | AQ25: 5. Très important | AR25: 5. Très important | AS25: 5. Très important | AT25: 5. Très important | AU25: 7 | AV25: 7 | AW25: 2. Très limitée (Quelques vidéos ou articles consultés) | AX25: 5 | AY25: 7 | AZ25: 2. En désaccord (Je contrôle la quasi-totalité des éléments) | BA25: 7 | BB25: 4 | BC25: 2 | BD25: 2 | BE25: Non | BF25: 1 | BG25: 4. Neutre | BH25: 1 | BI25: 26-35 | BJ25: Femme | BK25: Junior | BL25: 2 - 3 ans | BM25: Audit Financier | BN25: Cabinet régional
A26: 46049.81 | B26: 2. Très rarement (Moins d'une fois par mois) | C26: Outils grand public (ex: ChatGPT, Gemini ) | F26: Version grand public | M26: Rédaction (rapports, synthèses, notes, mails) | N26: De manière VOLONTAIRE (vous avez choisi vous-même) | O26: 3. Neutre | P26: 3. Neutre | Q26: 3. Neutre | R26: 2. Peu utile | S26: 2. Peu utile | T26: 3. Neutre | U26: 2. Peu utile | V26: 3. Neutre | W26: 2. Peu utile | X26: 2. Peu utile | Y26: 2. Peu utile | Z26: 2. Peu utile | AA26: 2. Peu utile | AB26: 2. Peu utile | AC26: 2. Peu utile | AD26: 2. Peu utile | AE26: 2. Peu utile | AF26: 2. Peu utile | AG26: 2. Peu utile | AH26: 2. Peu utile | AI26: 5 | AJ26: 5. Plutôt facile (Assez intuitif) | AK26: 5. Plutôt d'accord (S'intègre assez bien) | AL26: 5 | AM26: 6 | AN26: 6 | AO26: 5 | AP26: 5 | AQ26: 3. Moyennement important | AR26: 3. Moyennement important | AS26: 3. Moyennement important | AT26: 3. Moyennement important | AU26: 4 | AV26: 6 | AW26: 2. Très limitée (Quelques vidéos ou articles consultés) | AX26: 4 | AY26: 4 | AZ26: 4. Neutre (Le niveau de vérification dépend de la complexité) | BA26: 4 | BB26: 5 | BC26: 5 | BD26: 3 | BE26: Oui | BF26: 5 | BG26: 4. Neutre | BH26: 5 | BI26: 26-35 | BJ26: Homme | BK26: Senior | BL26: 4 - 5 ans | BM26: Audit Financier | BN26: Cabinet international
A27: 46050.55 | B27: 7. Très fréquemment (Plusieurs fois par jour) | C27: Outils fournis/agréés par le cabinet (ex: Copilot sécurisé) | K27: Version entreprise | M27: Automatisation et création de scripts (SQL, VBA), Rédaction (rapports, synthèses, notes, mails), Reformulation ou traduction de documents, Correction et mise en cohérence de documents, Rapprochement/Comparaison de documents | N27: De manière RECOMMANDÉE (cabinet encourage, mais facultatif) | O27: 5. Très utile | P27: 5. Très utile | Q27: 5. Très utile | R27: 5. Très utile | S27: 5. Très utile | T27: 1. Pas du tout utile | U27: 1. Pas du tout utile | V27: 1. Pas du tout utile | W27: 1. Pas du tout utile | X27: 4. Utile | Y27: 5. Très utile | Z27: 5. Très utile | AA27: 5. Très utile | AB27: 5. Très utile | AC27: 5. Très utile | AD27: 1. Pas du tout utile | AE27: 1. Pas du tout utile | AF27: 1. Pas du tout utile | AG27: 1. Pas du tout utile | AH27: 5. Très utile | AI27: 6 | AJ27: 5. Plutôt facile (Assez intuitif) | AK27: 6. D'accord (S'intègre facilement) | AL27: 2 | AM27: 2 | AN27: 3 | AO27: 3 | AP27: 6 | AQ27: 3. Moyennement important | AR27: 2. Peu important | AS27: 3. Moyennement important | AT27: 4. Important | AU27: 4 | AV27: 7 | AW27: 2. Très limitée (Quelques vidéos ou articles consultés) | AX27: 6 | AY27: 5 | AZ27: 2. En désaccord (Je contrôle la quasi-totalité des éléments) | BA27: 6 | BB27: 7 | BC27: 7 | BD27: 6 | BE27: Oui | BF27: 4 | BG27: 4. Neutre | BH27: 7 | BI27: 18-25 | BJ27: Femme | BK27: Junior | BL27: Moins de 2 ans | BM27: Audit Financier | BN27: Cabinet international
A28: 46050.558 | B28: 5. Régulièrement (Plusieurs fois par semaine) | C28: Outils fournis/agréés par le cabinet (ex: Copilot sécurisé) | E28: Version entreprise | F28: Version grand public | M28: Rapprochement/Comparaison de documents, Aide à la décision, Recherche d'informations ou de points techniques, Évaluation du contrôle interne, Rédaction (rapports, synthèses, notes, mails), Automatisation et création de scripts (SQL, VBA), Analyse de données et génération d'insights | N28: De manière VOLONTAIRE (vous avez choisi vous-même) | O28: 3. Neutre | P28: 3. Neutre | Q28: 3. Neutre | R28: 3. Neutre | S28: 3. Neutre | T28: 3. Neutre | U28: 3. Neutre | V28: 3. Neutre | W28: 3. Neutre | X28: 3. Neutre | Y28: 3. Neutre | Z28: 4. Utile | AA28: 4. Utile | AB28: 4. Utile | AC28: 4. Utile | AD28: 3. Neutre | AE28: 3. Neutre | AF28: 3. Neutre | AG28: 4. Utile | AH28: 3. Neutre | AI28: 6 | AJ28: 5. Plutôt facile (Assez intuitif) | AK28: 6. D'accord (S'intègre facilement) | AL28: 3 | AM28: 5 | AN28: 6 | AO28: 6 | AP28: 4 | AQ28: 4. Important | AR28: 4. Important | AS28: 3. Moyennement important | AT28: 4. Important | AU28: 6 | AV28: 6 | AW28: 2. Très limitée (Quelques vidéos ou articles consultés) | AX28: 6 | AY28: 3 | AZ28: 2. En désaccord (Je contrôle la quasi-totalité des éléments) | BA28: 6 | BB28: 3 | BC28: 5 | BD28: 2 | BE28: Non | BF28: 2 | BG28: 4. Neutre | BH28: 5 | BI28: 18-25 | BJ28: Femme | BK28: Junior | BL28: Moins de 2 ans | BM28: Audit IT | BN28: Cabinet international | BO28: L’IA générative offre un fort potentiel pour gagner du temps et stimuler la créativité, mais elle doit être utilisée avec discernement pour garantir la fiabilité et préserver la confidentialité.
A29: 46050.558 | B29: 7. Très fréquemment (Plusieurs fois par jour) | C29: Outils fournis/agréés par le cabinet (ex: Copilot sécurisé) | E29: Version entreprise | M29: Préparation de données (format, structuration, harmonisation des valeurs), Aide à la décision, Automatisation et création de scripts (SQL, VBA), Reformulation ou traduction de documents | N29: De manière VOLONTAIRE (vous avez choisi vous-même) | O29: 4. Utile | P29: 4. Utile | Q29: 4. Utile | R29: 3. Neutre | S29: 5. Très utile | T29: 3. Neutre | U29: 2. Peu utile | V29: 2. Peu utile | W29: 3. Neutre | X29: 5. Très utile | Y29: 4. Utile | Z29: 4. Utile | AA29: 4. Utile | AB29: 3. Neutre | AC29: 5. Très utile | AD29: 3. Neutre | AE29: 2. Peu utile | AF29: 2. Peu utile | AG29: 3. Neutre | AH29: 5. Très utile | AI29: 5 | AJ29: 6. Facile (Maîtrise rapide) | AK29: 7. Tout à fait d'accord (Automatisme quotidien) | AL29: 4 | AM29: 7 | AN29: 7 | AO29: 2 | AP29: 7 | AQ29: 5. Très important | AR29: 2. Peu important | AS29: 2. Peu important | AT29: 4. Important | AU29: 2 | AV29: 4 | AW29: 5. Solide (Plusieurs jours de formation ou modules suivis) | AX29: 6 | AY29: 6 | AZ29: 3. Plutôt en désaccord (Je procède à une revue importante) | BA29: 5 | BB29: 5 | BC29: 5 | BD29: 5 | BE29: Oui | BF29: 2 | BG29: 4. Neutre | BH29: 5 | BI29: 18-25 | BJ29: Homme | BK29: Senior | BL29: 4 - 5 ans | BM29: Audit IT | BN29: Cabinet international | BO29: C'est top mais il est essentiel de conserver son sens critique et ne pas suivre bêtement les réponses de l'IA. Le risque est de perdre en questionnement, perdre en raisonnement, perdre en intelligence.
A30: 46051.57 | B30: 5. Régulièrement (Plusieurs fois par semaine) | C30: Outils fournis/agréés par le cabinet (ex: Copilot sécurisé) | E30: Version entreprise | K30: Version entreprise | L30: Version entreprise | M30: Aide à la décision, Analyse de données et génération d'insights, Rédaction (rapports, synthèses, notes, mails), Reformulation ou traduction de documents, Recherche d'informations ou de points techniques, Rapprochement/Comparaison de documents, Automatisation et création de scripts (SQL, VBA) | N30: De manière RECOMMANDÉE (cabinet encourage, mais facultatif) | O30: 5. Très utile | P30: 4. Utile | Q30: 3. Neutre | R30: 4. Utile | S30: 5. Très utile | T30: 3. Neutre | U30: 1. Pas du tout utile | V30: 2. Peu utile | W30: 4. Utile | X30: 4. Utile | Y30: 4. Utile | Z30: 5. Très utile | AA30: 5. Très utile | AB30: 3. Neutre | AC30: 5. Très utile | AD30: 4. Utile | AE30: 1. Pas du tout utile | AF30: 1. Pas du tout utile | AG30: 4. Utile | AH30: 4. Utile | AI30: 5 | AJ30: 3. Plutôt difficile (Peu intuitif) | AK30: 5. Plutôt d'accord (S'intègre assez bien) | AL30: 6 | AM30: 6 | AN30: 3 | AO30: 3 | AP30: 6 | AQ30: 5. Très important | AR30: 4. Important | AS30: 3. Moyennement important | AT30: 3. Moyennement important | AU30: 5 | AV30: 6 | AW30: 6. Approfondie (Parcours certifiant ou auto-formation technique longue) | AX30: 5 | AY30: 5 | AZ30: 2. En désaccord (Je contrôle la quasi-totalité des éléments) | BA30: 6 | BB30: 6 | BC30: 6 | BD30: 3 | BE30: Oui | BF30: 5 | BG30: 4. Neutre | BH30: 5 | BI30: 36-45 | BJ30: Homme | BK30: Manager | BL30: Plus de 10 ans | BM30: Audit Financier | BN30: Cabinet international
A31: 46052.59 | B31: 2. Très rarement (Moins d'une fois par mois) | C31: Usage mix des deux | E31: Version entreprise | M31: Rédaction (rapports, synthèses, notes, mails), Préparation de données (format, structuration, harmonisation des valeurs) | N31: De manière VOLONTAIRE (vous avez choisi vous-même) | O31: 4. Utile | P31: 4. Utile | Q31: 4. Utile | R31: 4. Utile | S31: 4. Utile | T31: 4. Utile | U31: 4. Utile | V31: 4. Utile | W31: 4. Utile | X31: 4. Utile | Y31: 4. Utile | Z31: 4. Utile | AA31: 4. Utile | AB31: 4. Utile | AC31: 4. Utile | AD31: 4. Utile | AE31: 4. Utile | AF31: 4. Utile | AG31: 3. Neutre | AH31: 3. Neutre | AI31: 6 | AJ31: 6. Facile (Maîtrise rapide) | AK31: 6. D'accord (S'intègre facilement) | AL31: 4 | AM31: 4 | AN31: 5 | AO31: 4 | AP31: 5 | AQ31: 3. Moyennement important | AR31: 3. Moyennement important | AS31: 3. Moyennement important | AT31: 4. Important | AU31: 5 | AV31: 5 | AW31: 5. Solide (Plusieurs jours de formation ou modules suivis) | AX31: 5 | AY31: 4 | AZ31: 4. Neutre (Le niveau de vérification dépend de la complexité) | BA31: 5 | BB31: 5 | BC31: 4 | BD31: 5 | BE31: Oui | BF31: 5 | BG31: 4. Neutre | BH31: 5 | BI31: 18-25 | BJ31: Homme | BK31: Junior | BL31: Moins de 2 ans | BM31: Audit Financier | BN31: Cabinet régional
A32: 46052.591 | B32: 2. Très rarement (Moins d'une fois par mois) | C32: Outils fournis/agréés par le cabinet (ex: Copilot sécurisé) | D32: Version entreprise | E32: Version entreprise | K32: Version entreprise | M32: Correction et mise en cohérence de documents, Recherche d'informations ou de points techniques, Automatisation et création de scripts (SQL, VBA) | N32: De manière VOLONTAIRE (vous avez choisi vous-même) | O32: 3. Neutre | P32: 4. Utile | Q32: 4. Utile | R32: 4. Utile | S32: 4. Utile | T32: 2. Peu utile | U32: 2. Peu utile | V32: 2. Peu utile | W32: 2. Peu utile | X32: 3. Neutre | Y32: 3. Neutre | Z32: 3. Neutre | AA32: 3. Neutre | AB32: 3. Neutre | AC32: 3. Neutre | AD32: 1. Pas du tout utile | AE32: 1. Pas du tout utile | AF32: 1. Pas du tout utile | AG32: 1. Pas du tout utile | AH32: 1. Pas du tout utile | AI32: 5 | AJ32: 3. Plutôt difficile (Peu intuitif) | AK32: 5. Plutôt d'accord (S'intègre assez bien) | AL32: 7 | AM32: 7 | AN32: 7 | AO32: 5 | AP32: 7 | AQ32: 5. Très important | AR32: 5. Très important | AS32: 3. Moyennement important | AT32: 3. Moyennement important | AU32: 5 | AV32: 5 | AW32: 3. Faible (Moins de 5 heures de formation au total) | AX32: 6 | AY32: 5 | AZ32: 3. Plutôt en désaccord (Je procède à une revue importante) | BA32: 7 | BB32: 4 | BC32: 3 | BD32: 2 | BE32: Non | BF32: 7 | BG32: 4. Neutre | BH32: 5 | BI32: 18-25 | BJ32: Homme | BK32: Junior | BL32: Moins de 2 ans | BM32: Audit Financier, Audit RSE | BN32: Cabinet international
A33: 46052.747 | B33: 6. Quotidiennement (Une fois par jour) | C33: Outils fournis/agréés par le cabinet (ex: Copilot sécurisé) | E33: Version entreprise | M33: Recherche d'informations ou de points techniques, Reformulation ou traduction de documents, Rédaction (rapports, synthèses, notes, mails) | N33: De manière RECOMMANDÉE (cabinet encourage, mais facultatif) | O33: 2. Peu utile | P33: 5. Très utile | Q33: 5. Très utile | R33: 3. Neutre | S33: 5. Très utile | T33: 2. Peu utile | U33: 3. Neutre | V33: 3. Neutre | W33: 2. Peu utile | X33: 4. Utile | Y33: 2. Peu utile | Z33: 4. Utile | AA33: 5. Très utile | AB33: 3. Neutre | AC33: 5. Très utile | AD33: 3. Neutre | AE33: 3. Neutre | AF33: 2. Peu utile | AG33: 2. Peu utile | AH33: 3. Neutre | AI33: 5 | AJ33: 5. Plutôt facile (Assez intuitif) | AK33: 5. Plutôt d'accord (S'intègre assez bien) | AL33: 5 | AM33: 5 | AN33: 4 | AO33: 4 | AP33: 6 | AQ33: 4. Important | AR33: 5. Très important | AS33: 3. Moyennement important | AT33: 4. Important | AU33: 3 | AV33: 5 | AW33: 4. Moyenne (Environ une journée de formation cumulée) | AX33: 5 | AY33: 5 | AZ33: 2. En désaccord (Je contrôle la quasi-totalité des éléments) | BA33: 4 | BB33: 6 | BC33: 4 | BD33: 2 | BE33: Non | BF33: 7 | BG33: 4. Neutre | BH33: 6 | BI33: 18-25 | BJ33: Homme | BK33: Junior | BL33: Moins de 2 ans | BM33: Audit Financier | BN33: Cabinet international
A34: 46055.284 | B34: 1. Jamais | BI34: 26-35 | BJ34: Homme | BK34: Junior | BL34: 2 - 3 ans | BM34: Audit Financier | BN34: Cabinet international | BO34: L'IA doit et être intégré à l'audit.
A35: 46064.495 | B35: 5. Régulièrement (Plusieurs fois par semaine) | C35: Outils fournis/agréés par le cabinet (ex: Copilot sécurisé) | E35: Version entreprise | K35: Version entreprise | M35: Rédaction (rapports, synthèses, notes, mails), Recherche d'informations ou de points techniques, Aide à la décision, Reformulation ou traduction de documents, Automatisation et création de scripts (SQL, VBA) | N35: De manière VOLONTAIRE (vous avez choisi vous-même) | O35: 3. Neutre | P35: 4. Utile | Q35: 5. Très utile | R35: 4. Utile | S35: 4. Utile | T35: 3. Neutre | U35: 3. Neutre | V35: 3. Neutre | W35: 4. Utile | X35: 3. Neutre | Y35: 3. Neutre | Z35: 5. Très utile | AA35: 5. Très utile | AB35: 5. Très utile | AC35: 4. Utile | AD35: 4. Utile | AE35: 3. Neutre | AF35: 4. Utile | AG35: 4. Utile | AH35: 4. Utile | AI35: 5 | AJ35: 6. Facile (Maîtrise rapide) | AK35: 6. D'accord (S'intègre facilement) | AL35: 5 | AM35: 6 | AN35: 7 | AO35: 6 | AP35: 6 | AQ35: 4. Important | AR35: 4. Important | AS35: 4. Important | AT35: 4. Important | AU35: 3 | AV35: 6 | AW35: 5. Solide (Plusieurs jours de formation ou modules suivis) | AX35: 4 | AY35: 5 | AZ35: 4. Neutre (Le niveau de vérification dépend de la complexité) | BA35: 5 | BB35: 5 | BC35: 3 | BD35: 3 | BE35: Non | BF35: 5 | BG35: 4. Neutre | BH35: 5 | BI35: 18-25 | BJ35: Femme | BK35: Fonction support | BL35: 2 - 3 ans | BM35: Product Owner Recherche et Developpement | BN35: Cabinet international
A36: 46064.572 | B36: 7. Très fréquemment (Plusieurs fois par jour) | C36: Outils fournis/agréés par le cabinet (ex: Copilot sécurisé) | E36: Version entreprise | M36: Automatisation et création de scripts (SQL, VBA), Reformulation ou traduction de documents, Rédaction (rapports, synthèses, notes, mails), Correction et mise en cohérence de documents | N36: De manière VOLONTAIRE (vous avez choisi vous-même) | O36: 4. Utile | P36: 5. Très utile | Q36: 5. Très utile | R36: 4. Utile | S36: 4. Utile | T36: 1. Pas du tout utile | U36: 1. Pas du tout utile | V36: 3. Neutre | W36: 3. Neutre | X36: 4. Utile | Y36: 4. Utile | Z36: 4. Utile | AA36: 4. Utile | AB36: 5. Très utile | AC36: 4. Utile | AD36: 1. Pas du tout utile | AE36: 1. Pas du tout utile | AF36: 3. Neutre | AG36: 4. Utile | AH36: 4. Utile | AI36: 7 | AJ36: 6. Facile (Maîtrise rapide) | AK36: 6. D'accord (S'intègre facilement) | AL36: 4 | AM36: 6 | AN36: 7 | AO36: 5 | AP36: 3 | AQ36: 4. Important | AR36: 5. Très important | AS36: 5. Très important | AT36: 3. Moyennement important | AU36: 3 | AV36: 7 | AW36: 2. Très limitée (Quelques vidéos ou articles consultés) | AX36: 6 | AY36: 6 | AZ36: 5. Plutôt d'accord (Je vérifie uniquement les points clés) | BA36: 5 | BB36: 6 | BC36: 5 | BD36: 1 | BE36: Oui | BF36: 7 | BG36: 4. Neutre | BH36: 7 | BI36: 18-25 | BJ36: Homme | BK36: Junior | BL36: 2 - 3 ans | BM36: Audit Financier | BN36: Cabinet international
A37: 46064.576 | B37: 6. Quotidiennement (Une fois par jour) | C37: Outils fournis/agréés par le cabinet (ex: Copilot sécurisé) | E37: Version entreprise | M37: Rédaction (rapports, synthèses, notes, mails), Recherche d'informations ou de points techniques, Reformulation ou traduction de documents | N37: De manière VOLONTAIRE (vous avez choisi vous-même) | O37: 5. Très utile | P37: 5. Très utile | Q37: 5. Très utile | R37: 4. Utile | S37: 3. Neutre | T37: 3. Neutre | U37: 2. Peu utile | V37: 3. Neutre | W37: 3. Neutre | X37: 3. Neutre | Y37: 4. Utile | Z37: 4. Utile | AA37: 5. Très utile | AB37: 4. Utile | AC37: 3. Neutre | AD37: 3. Neutre | AE37: 3. Neutre | AF37: 3. Neutre | AG37: 3. Neutre | AH37: 4. Utile | AI37: 6 | AJ37: 5. Plutôt facile (Assez intuitif) | AK37: 6. D'accord (S'intègre facilement) | AL37: 5 | AM37: 5 | AN37: 6 | AO37: 5 | AP37: 3 | AQ37: 4. Important | AR37: 5. Très important | AS37: 4. Important | AT37: 3. Moyennement important | AU37: 6 | AV37: 6 | AW37: 1. Aucune | AX37: 3 | AY37: 6 | AZ37: 4. Neutre (Le niveau de vérification dépend de la complexité) | BA37: 4 | BB37: 6 | BC37: 3 | BD37: 4 | BE37: Non | BF37: 5 | BG37: 4. Neutre | BH37: 5 | BI37: 18-25 | BJ37: Femme | BK37: Junior | BL37: Moins de 2 ans | BM37: Audit Financier | BN37: Cabinet international
A38: 46064.577 | B38: 4. Parfois (Environ une fois par semaine) | C38: Outils fournis/agréés par le cabinet (ex: Copilot sécurisé) | E38: Version entreprise | M38: Recherche d'informations ou de points techniques, Rédaction (rapports, synthèses, notes, mails), Résumé d'un document | N38: De manière VOLONTAIRE (vous avez choisi vous-même) | O38: 3. Neutre | P38: 5. Très utile | Q38: 5. Très utile | R38: 3. Neutre | S38: 3. Neutre | T38: 3. Neutre | U38: 3. Neutre | V38: 3. Neutre | W38: 3. Neutre | X38: 3. Neutre | Y38: 3. Neutre | Z38: 5. Très utile | AA38: 4. Utile | AB38: 3. Neutre | AC38: 3. Neutre | AD38: 3. Neutre | AE38: 3. Neutre | AF38: 3. Neutre | AG38: 3. Neutre | AH38: 3. Neutre | AI38: 7 | AJ38: 6. Facile (Maîtrise rapide) | AK38: 5. Plutôt d'accord (S'intègre assez bien) | AL38: 3 | AM38: 7 | AN38: 7 | AO38: 7 | AP38: 4 | AQ38: 5. Très important | AR38: 5. Très important | AS38: 5. Très important | AT38: 5. Très important | AU38: 3 | AV38: 3 | AW38: 2. Très limitée (Quelques vidéos ou articles consultés) | AX38: 1 | AY38: 5 | AZ38: 6. D'accord (Je fais globalement confiance au résultat) | BA38: 2 | BB38: 4 | BC38: 5 | BD38: 3 | BE38: Non | BF38: 3 | BG38: 4. Neutre | BH38: 5 | BI38: 18-25 | BJ38: Homme | BK38: Junior | BL38: 2 - 3 ans | BM38: Audit Financier | BN38: Cabinet international
A39: 46064.581 | B39: 7. Très fréquemment (Plusieurs fois par jour) | C39: Outils fournis/agréés par le cabinet (ex: Copilot sécurisé) | E39: Version entreprise | K39: Version entreprise | M39: Rédaction (rapports, synthèses, notes, mails), Préparation de données (format, structuration, harmonisation des valeurs), Revue d'estimations comptables (provisions, dépréciations), Reformulation ou traduction de documents, Évaluation du contrôle interne, Rapprochement/Comparaison de documents, Correction et mise en cohérence de documents, Recherche d'informations ou de points techniques, Analyse de données et génération d'insights | N39: De manière RECOMMANDÉE (cabinet encourage, mais facultatif) | O39: 5. Très utile | P39: 4. Utile | Q39: 5. Très utile | R39: 5. Très utile | S39: 5. Très utile | T39: 3. Neutre | U39: 2. Peu utile | V39: 3. Neutre | W39: 3. Neutre | X39: 4. Utile | Y39: 5. Très utile | Z39: 5. Très utile | AA39: 5. Très utile | AB39: 5. Très utile | AC39: 5. Très utile | AD39: 4. Utile | AE39: 3. Neutre | AF39: 3. Neutre | AG39: 3. Neutre | AH39: 4. Utile | AI39: 6 | AJ39: 6. Facile (Maîtrise rapide) | AK39: 6. D'accord (S'intègre facilement) | AL39: 3 | AM39: 5 | AN39: 4 | AO39: 4 | AP39: 2 | AQ39: 4. Important | AR39: 2. Peu important | AS39: 3. Moyennement important | AT39: 3. Moyennement important | AU39: 2 | AV39: 7 | AW39: 4. Moyenne (Environ une journée de formation cumulée) | AX39: 6 | AY39: 6 | AZ39: 2. En désaccord (Je contrôle la quasi-totalité des éléments) | BA39: 6 | BB39: 5 | BC39: 5 | BD39: 2 | BE39: Oui | BF39: 7 | BG39: 4. Neutre | BH39: 7 | BI39: 18-25 | BJ39: Homme | BK39: Junior | BL39: Moins de 2 ans | BM39: Audit Financier | BN39: Cabinet international
A40: 46064.59 | B40: 5. Régulièrement (Plusieurs fois par semaine) | C40: Outils fournis/agréés par le cabinet (ex: Copilot sécurisé) | E40: Version entreprise | M40: Recherche d'informations ou de points techniques, Rédaction (rapports, synthèses, notes, mails), Reformulation ou traduction de documents | N40: De manière VOLONTAIRE (vous avez choisi vous-même) | O40: 2. Peu utile | P40: 2. Peu utile | Q40: 5. Très utile | R40: 5. Très utile | S40: 3. Neutre | T40: 1. Pas du tout utile | U40: 3. Neutre | V40: 1. Pas du tout utile | W40: 3. Neutre | X40: 3. Neutre | Y40: 3. Neutre | Z40: 4. Utile | AA40: 4. Utile | AB40: 4. Utile | AC40: 3. Neutre | AD40: 3. Neutre | AE40: 3. Neutre | AF40: 3. Neutre | AG40: 4. Utile | AH40: 3. Neutre | AI40: 6 | AJ40: 5. Plutôt facile (Assez intuitif) | AK40: 6. D'accord (S'intègre facilement) | AL40: 5 | AM40: 7 | AN40: 6 | AO40: 5 | AP40: 4 | AQ40: 4. Important | AR40: 5. Très important | AS40: 4. Important | AT40: 3. Moyennement important | AU40: 6 | AV40: 6 | AW40: 2. Très limitée (Quelques vidéos ou articles consultés) | AX40: 5 | AY40: 5 | AZ40: 6. D'accord (Je fais globalement confiance au résultat) | BA40: 7 | BB40: 7 | BC40: 2 | BD40: 1 | BE40: Non | BF40: 5 | BG40: 4. Neutre | BH40: 5 | BI40: 18-25 | BJ40: Femme | BK40: Junior | BL40: 2 - 3 ans | BM40: Audit Financier, Audit RSE | BN40: Cabinet international | BO40: Je l'utilise essentiellement pour retravailler un texte/reformuler/traduire mais quasiment jamais pour conclure sur des travaux, pour donner un avis, essentiellement de la mise en forme et rédaction
A41: 46064.936 | B41: 5. Régulièrement (Plusieurs fois par semaine) | C41: Outils grand public (ex: ChatGPT, Gemini ) | F41: Version grand public | J41: Version grand public | K41: Version grand public | M41: Rédaction (rapports, synthèses, notes, mails), Reformulation ou traduction de documents, Analyse de données et génération d'insights | N41: De manière RECOMMANDÉE (cabinet encourage, mais facultatif) | O41: 2. Peu utile | P41: 4. Utile | Q41: 4. Utile | R41: 1. Pas du tout utile | S41: 4. Utile | T41: 3. Neutre | U41: 3. Neutre | V41: 3. Neutre | W41: 4. Utile | X41: 3. Neutre | Y41: 1. Pas du tout utile | Z41: 4. Utile | AA41: 4. Utile | AB41: 1. Pas du tout utile | AC41: 4. Utile | AD41: 1. Pas du tout utile | AE41: 1. Pas du tout utile | AF41: 1. Pas du tout utile | AG41: 4. Utile | AH41: 4. Utile | AI41: 6 | AJ41: 5. Plutôt facile (Assez intuitif) | AK41: 5. Plutôt d'accord (S'intègre assez bien) | AL41: 4 | AM41: 6 | AN41: 7 | AO41: 4 | AP41: 5 | AQ41: 5. Très important | AR41: 5. Très important | AS41: 4. Important | AT41: 4. Important | AU41: 6 | AV41: 6 | AW41: 4. Moyenne (Environ une journée de formation cumulée) | AX41: 5 | AY41: 5 | AZ41: 2. En désaccord (Je contrôle la quasi-totalité des éléments) | BA41: 5 | BB41: 6 | BC41: 6 | BD41: 3 | BE41: Oui | BF41: 6 | BG41: 4. Neutre | BH41: 3 | BI41: 26-35 | BJ41: Homme | BK41: Senior | BL41: 4 - 5 ans | BM41: Audit Financier | BN41: Cabinet local
A42: 46065.417 | B42: 7. Très fréquemment (Plusieurs fois par jour) | C42: Usage mix des deux | F42: Version grand public | K42: Version entreprise | L42: Version entreprise | M42: Rédaction (rapports, synthèses, notes, mails), Recherche d'informations ou de points techniques, Reformulation ou traduction de documents | N42: De manière VOLONTAIRE (vous avez choisi vous-même) | O42: 5. Très utile | P42: 5. Très utile | Q42: 5. Très utile | R42: 3. Neutre | S42: 5. Très utile | T42: 4. Utile | U42: 2. Peu utile | V42: 2. Peu utile | W42: 4. Utile | X42: 4. Utile | Y42: 5. Très utile | Z42: 5. Très utile | AA42: 5. Très utile | AB42: 4. Utile | AC42: 5. Très utile | AD42: 3. Neutre | AE42: 3. Neutre | AF42: 4. Utile | AG42: 4. Utile | AH42: 5. Très utile | AI42: 7 | AJ42: 6. Facile (Maîtrise rapide) | AK42: 6. D'accord (S'intègre facilement) | AL42: 3 | AM42: 7 | AN42: 3 | AO42: 5 | AP42: 2 | AQ42: 2. Peu important | AR42: 2. Peu important | AS42: 4. Important | AT42: 2. Peu important | AU42: 2 | AV42: 1 | AW42: 1. Aucune | AX42: 7 | AY42: 7 | AZ42: 1. Pas du tout d’accord (Je vérifie systématiquement chaque détail) | BA42: 6 | BB42: 7 | BC42: 4 | BD42: 1 | BE42: Non | BF42: 2 | BG42: 4. Neutre | BH42: 7 | BI42: 26-35 | BJ42: Femme | BK42: Associé | BL42: Plus de 10 ans | BM42: Expertise | BN42: Cabinet local
A43: 46065.418 | B43: 4. Parfois (Environ une fois par semaine) | C43: Outils grand public (ex: ChatGPT, Gemini ) | G43: Version entreprise | M43: Reformulation ou traduction de documents, Recherche d'informations ou de points techniques, Rédaction (rapports, synthèses, notes, mails) | N43: De manière VOLONTAIRE (vous avez choisi vous-même) | O43: 2. Peu utile | P43: 2. Peu utile | Q43: 4. Utile | R43: 2. Peu utile | S43: 4. Utile | T43: 2. Peu utile | U43: 2. Peu utile | V43: 2. Peu utile | W43: 4. Utile | X43: 2. Peu utile | Y43: 2. Peu utile | Z43: 2. Peu utile | AA43: 4. Utile | AB43: 2. Peu utile | AC43: 2. Peu utile | AD43: 2. Peu utile | AE43: 2. Peu utile | AF43: 2. Peu utile | AG43: 4. Utile | AH43: 4. Utile | AI43: 6 | AJ43: 4. Ni facile, ni difficile (Prise en main normale) | AK43: 4. Ni d'accord, ni en désaccord | AL43: 7 | AM43: 7 | AN43: 7 | AO43: 7 | AP43: 7 | AQ43: 5. Très important | AR43: 5. Très important | AS43: 5. Très important | AT43: 5. Très important | AU43: 7 | AV43: 7 | AW43: 3. Faible (Moins de 5 heures de formation au total) | AX43: 7 | AY43: 3 | AZ43: 4. Neutre (Le niveau de vérification dépend de la complexité) | BA43: 7 | BB43: 7 | BC43: 7 | BD43: 7 | BE43: Oui | BF43: 5 | BG43: 4. Neutre | BH43: 4 | BI43: 36-45 | BJ43: Homme | BK43: Associé | BL43: Plus de 10 ans | BM43: expertise comptable/conseil dirigeant | BN43: Cabinet régional
A44: 46065.424 | B44: 3. Rarement (1 à 3 fois par mois) | C44: Outils grand public (ex: ChatGPT, Gemini ) | F44: Version grand public | G44: Version grand public | M44: Rédaction (rapports, synthèses, notes, mails), Correction et mise en cohérence de documents, Reformulation ou traduction de documents, presentation powerpoint sur un theme | N44: De manière VOLONTAIRE (vous avez choisi vous-même) | O44: 3. Neutre | P44: 3. Neutre | Q44: 4. Utile | R44: 3. Neutre | S44: 3. Neutre | T44: 3. Neutre | U44: 3. Neutre | V44: 3. Neutre | W44: 3. Neutre | X44: 4. Utile | Y44: 3. Neutre | Z44: 3. Neutre | AA44: 3. Neutre | AB44: 3. Neutre | AC44: 3. Neutre | AD44: 3. Neutre | AE44: 3. Neutre | AF44: 3. Neutre | AG44: 3. Neutre | AH44: 3. Neutre | AI44: 5 | AJ44: 7. Très facile (Instinctif / Sans aide) | AK44: 5. Plutôt d'accord (S'intègre assez bien) | AL44: 6 | AM44: 7 | AN44: 7 | AO44: 7 | AP44: 7 | AQ44: 5. Très important | AR44: 5. Très important | AS44: 5. Très important | AT44: 5. Très important | AU44: 7 | AV44: 7 | AW44: 3. Faible (Moins de 5 heures de formation au total) | AX44: 3 | AY44: 3 | AZ44: 1. Pas du tout d’accord (Je vérifie systématiquement chaque détail) | BA44: 7 | BB44: 5 | BC44: 6 | BD44: 1 | BE44: Oui | BF44: 6 | BG44: 4. Neutre | BH44: 5 | BI44: 36-45 | BJ44: Femme | BK44: Associé | BL44: Plus de 10 ans | BM44: EC | BN44: Cabinet local
A45: 46065.424 | B45: 5. Régulièrement (Plusieurs fois par semaine) | C45: Outils grand public (ex: ChatGPT, Gemini ) | F45: Version entreprise | M45: Rédaction (rapports, synthèses, notes, mails), Reformulation ou traduction de documents, Recherche d'informations ou de points techniques | N45: De manière VOLONTAIRE (vous avez choisi vous-même) | O45: 5. Très utile | P45: 5. Très utile | Q45: 5. Très utile | R45: 3. Neutre | S45: 3. Neutre | T45: 3. Neutre | U45: 1. Pas du tout utile | V45: 1. Pas du tout utile | W45: 1. Pas du tout utile | X45: 4. Utile | Y45: 5. Très utile | Z45: 5. Très utile | AA45: 5. Très utile | AB45: 4. Utile | AC45: 3. Neutre | AD45: 3. Neutre | AE45: 3. Neutre | AF45: 3. Neutre | AG45: 4. Utile | AH45: 3. Neutre | AI45: 6 | AJ45: 6. Facile (Maîtrise rapide) | AK45: 6. D'accord (S'intègre facilement) | AL45: 6 | AM45: 7 | AN45: 7 | AO45: 7 | AP45: 7 | AQ45: 5. Très important | AR45: 5. Très important | AS45: 5. Très important | AT45: 5. Très important | AU45: 6 | AV45: 7 | AW45: 6. Approfondie (Parcours certifiant ou auto-formation technique longue) | AX45: 6 | AY45: 2 | AZ45: 5. Plutôt d'accord (Je vérifie uniquement les points clés) | BA45: 6 | BB45: 4 | BC45: 5 | BD45: 6 | BE45: Non | BF45: 5 | BG45: 4. Neutre | BH45: 5 | BI45: 26-35 | BJ45: Homme | BK45: Associé | BL45: 6 - 7 ans | BM45: Audit Financier | BN45: Cabinet local
A46: 46065.432 | B46: 2. Très rarement (Moins d'une fois par mois) | C46: Outils fournis/agréés par le cabinet (ex: Copilot sécurisé) | E46: Version entreprise | F46: Version entreprise | H46: Version entreprise | M46: Rapprochement/Comparaison de documents, Reformulation ou traduction de documents, Rédaction (rapports, synthèses, notes, mails), Détection de la fraude, Préparation de données (format, structuration, harmonisation des valeurs) | N46: De manière VOLONTAIRE (vous avez choisi vous-même) | O46: 4. Utile | P46: 4. Utile | Q46: 4. Utile | R46: 3. Neutre | S46: 2. Peu utile | T46: 3. Neutre | U46: 2. Peu utile | V46: 2. Peu utile | W46: 3. Neutre | X46: 4. Utile | Y46: 4. Utile | Z46: 4. Utile | AA46: 4. Utile | AB46: 2. Peu utile | AC46: 2. Peu utile | AD46: 3. Neutre | AE46: 2. Peu utile | AF46: 3. Neutre | AG46: 4. Utile | AH46: 4. Utile | AI46: 5 | AJ46: 4. Ni facile, ni difficile (Prise en main normale) | AK46: 6. D'accord (S'intègre facilement) | AL46: 5 | AM46: 5 | AN46: 4 | AO46: 5 | AP46: 4 | AQ46: 4. Important | AR46: 3. Moyennement important | AS46: 4. Important | AT46: 2. Peu important | AU46: 4 | AV46: 6 | AW46: 4. Moyenne (Environ une journée de formation cumulée) | AX46: 5 | AY46: 5 | AZ46: 3. Plutôt en désaccord (Je procède à une revue importante) | BA46: 6 | BB46: 5 | BC46: 5 | BD46: 5 | BE46: Oui | BF46: 6 | BG46: 4. Neutre | BH46: 5 | BI46: 56-65 | BJ46: Homme | BK46: Associé | BL46: Plus de 10 ans | BM46: expertise comptable | BN46: Cabinet local | BO46: non
A47: 46065.432 | B47: 4. Parfois (Environ une fois par semaine) | C47: Usage mix des deux | D47: Version grand public | E47: Version grand public | F47: Version grand public | J47: Version grand public | M47: Préparation de données (format, structuration, harmonisation des valeurs), Détection de la fraude, Reformulation ou traduction de documents, Analyse de données et génération d'insights, Rédaction (rapports, synthèses, notes, mails), Correction et mise en cohérence de documents, Recherche d'informations ou de points techniques, Aide à la décision | N47: De manière VOLONTAIRE (vous avez choisi vous-même) | O47: 4. Utile | P47: 5. Très utile | Q47: 5. Très utile | R47: 4. Utile | S47: 3. Neutre | T47: 4. Utile | U47: 3. Neutre | V47: 3. Neutre | W47: 4. Utile | X47: 3. Neutre | Y47: 4. Utile | Z47: 5. Très utile | AA47: 5. Très utile | AB47: 5. Très utile | AC47: 3. Neutre | AD47: 4. Utile | AE47: 4. Utile | AF47: 3. Neutre | AG47: 3. Neutre | AH47: 4. Utile | AI47: 6 | AJ47: 5. Plutôt facile (Assez intuitif) | AK47: 5. Plutôt d'accord (S'intègre assez bien) | AL47: 5 | AM47: 7 | AN47: 7 | AO47: 7 | AP47: 7 | AQ47: 4. Important | AR47: 5. Très important | AS47: 4. Important | AT47: 4. Important | AU47: 5 | AV47: 7 | AW47: 3. Faible (Moins de 5 heures de formation au total) | AX47: 5 | AY47: 6 | AZ47: 2. En désaccord (Je contrôle la quasi-totalité des éléments) | BA47: 6 | BB47: 6 | BC47: 4 | BD47: 4 | BE47: Oui | BF47: 7 | BG47: 4. Neutre | BH47: 6 | BI47: 36-45 | BJ47: Homme | BK47: Manager | BL47: Plus de 10 ans | BM47: Audit Financier, Audit Interne | BN47: Cabinet local
A48: 46065.459 | B48: 5. Régulièrement (Plusieurs fois par semaine) | C48: Usage mix des deux | D48: Version grand public | E48: Version entreprise | F48: Version entreprise | G48: Version grand public | H48: Version entreprise | I48: Version grand public | M48: Reformulation ou traduction de documents, Rédaction (rapports, synthèses, notes, mails), Analyse de données et génération d'insights, Recherche d'informations ou de points techniques, Rapprochement/Comparaison de documents, Correction et mise en cohérence de documents, Aide à la décision | N48: De manière VOLONTAIRE (vous avez choisi vous-même) | O48: 4. Utile | P48: 5. Très utile | Q48: 5. Très utile | R48: 4. Utile | S48: 3. Neutre | T48: 4. Utile | U48: 4. Utile | V48: 3. Neutre | W48: 4. Utile | X48: 5. Très utile | Y48: 5. Très utile | Z48: 5. Très utile | AA48: 5. Très utile | AB48: 4. Utile | AC48: 3. Neutre | AD48: 3. Neutre | AE48: 3. Neutre | AF48: 2. Peu utile | AG48: 4. Utile | AH48: 4. Utile | AI48: 5 | AJ48: 3. Plutôt difficile (Peu intuitif) | AK48: 6. D'accord (S'intègre facilement) | AL48: 6 | AM48: 6 | AN48: 7 | AO48: 5 | AP48: 4 | AQ48: 4. Important | AR48: 5. Très important | AS48: 3. Moyennement important | AT48: 3. Moyennement important | AU48: 3 | AV48: 7 | AW48: 5. Solide (Plusieurs jours de formation ou modules suivis) | AX48: 5 | AY48: 6 | AZ48: 2. En désaccord (Je contrôle la quasi-totalité des éléments) | BA48: 5 | BB48: 5 | BC48: 5 | BD48: 2 | BE48: Oui | BF48: 7 | BG48: 4. Neutre | BH48: 6 | BI48: 46-55 | BJ48: Homme | BK48: Associé | BL48: Plus de 10 ans | BM48: Audit Financier | BN48: Cabinet régional
A49: 46065.461 | B49: 6. Quotidiennement (Une fois par jour) | C49: Usage mix des deux | D49: Version grand public | E49: Version entreprise | F49: Version entreprise | G49: Version grand public | H49: Version entreprise | M49: Automatisation et création de scripts (SQL, VBA), Aide à la décision, Rédaction (rapports, synthèses, notes, mails), Recherche d'informations ou de points techniques, Analyse de données et génération d'insights, Reformulation ou traduction de documents | N49: De manière RECOMMANDÉE (cabinet encourage, mais facultatif) | O49: 3. Neutre | P49: 4. Utile | Q49: 5. Très utile | R49: 5. Très utile | S49: 5. Très utile | T49: 3. Neutre | U49: 3. Neutre | V49: 3. Neutre | W49: 4. Utile | X49: 5. Très utile | Y49: 4. Utile | Z49: 4. Utile | AA49: 5. Très utile | AB49: 5. Très utile | AC49: 5. Très utile | AD49: 3. Neutre | AE49: 3. Neutre | AF49: 3. Neutre | AG49: 4. Utile | AH49: 5. Très utile | AI49: 7 | AJ49: 6. Facile (Maîtrise rapide) | AK49: 6. D'accord (S'intègre facilement) | AL49: 7 | AM49: 7 | AN49: 7 | AO49: 7 | AP49: 5 | AQ49: 5. Très important | AR49: 4. Important | AS49: 4. Important | AT49: 5. Très important | AU49: 6 | AV49: 7 | AW49: 7. Experte (Maîtrise totale / Capacité à former les autres) | AX49: 6 | AY49: 6 | AZ49: 4. Neutre (Le niveau de vérification dépend de la complexité) | BA49: 5 | BB49: 6 | BC49: 6 | BD49: 4 | BE49: Oui | BF49: 7 | BG49: 4. Neutre | BH49: 6 | BI49: 56-65 | BJ49: Homme | BK49: Associé | BL49: Plus de 10 ans | BM49: Audit Financier, Audit Interne | BN49: Cabinet régional
A50: 46065.482 | B50: 4. Parfois (Environ une fois par semaine) | C50: Usage mix des deux | D50: Version entreprise | E50: Version entreprise | G50: Version grand public | H50: Version grand public | M50: Automatisation et création de scripts (SQL, VBA), Analyse de données et génération d'insights, Recherche d'informations ou de points techniques, Reformulation ou traduction de documents | N50: De manière VOLONTAIRE (vous avez choisi vous-même) | O50: 4. Utile | P50: 4. Utile | Q50: 3. Neutre | R50: 4. Utile | S50: 5. Très utile | T50: 2. Peu utile | U50: 2. Peu utile | V50: 3. Neutre | W50: 3. Neutre | X50: 4. Utile | Y50: 4. Utile | Z50: 4. Utile | AA50: 3. Neutre | AB50: 3. Neutre | AC50: 5. Très utile | AD50: 3. Neutre | AE50: 2. Peu utile | AF50: 3. Neutre | AG50: 3. Neutre | AH50: 4. Utile | AI50: 4 | AJ50: 4. Ni facile, ni difficile (Prise en main normale) | AK50: 6. D'accord (S'intègre facilement) | AL50: 6 | AM50: 6 | AN50: 7 | AO50: 5 | AP50: 5 | AQ50: 2. Peu important | AR50: 4. Important | AS50: 3. Moyennement important | AT50: 2. Peu important | AU50: 3 | AV50: 4 | AW50: 5. Solide (Plusieurs jours de formation ou modules suivis) | AX50: 4 | AY50: 5 | AZ50: 3. Plutôt en désaccord (Je procède à une revue importante) | BA50: 6 | BB50: 6 | BC50: 4 | BD50: 2 | BE50: Oui | BF50: 7 | BG50: 4. Neutre | BH50: 6 | BI50: 46-55 | BJ50: Homme | BK50: Associé | BL50: Plus de 10 ans | BM50: Audit Financier | BN50: Cabinet régional | BO50: L'IA générative est utile, mais elle a 2 biais : l'hallucination et l'imprécision. En temps qu'auditeur nous avons l'habitude de résultat précis et reproductible. Les obtenir avec l'IAG est plus difficile. Mais le champ des possibles est énorme
A51: 46065.504 | B51: 5. Régulièrement (Plusieurs fois par semaine) | C51: Usage mix des deux | F51: Version entreprise | H51: Version grand public | J51: Version grand public | M51: Rédaction (rapports, synthèses, notes, mails), Reformulation ou traduction de documents, Rapprochement/Comparaison de documents, Recherche d'informations ou de points techniques, Automatisation et création de scripts (SQL, VBA) | N51: De manière VOLONTAIRE (vous avez choisi vous-même) | O51: 2. Peu utile | P51: 2. Peu utile | Q51: 5. Très utile | R51: 4. Utile | S51: 5. Très utile | T51: 3. Neutre | U51: 3. Neutre | V51: 3. Neutre | W51: 3. Neutre | X51: 4. Utile | Y51: 1. Pas du tout utile | Z51: 1. Pas du tout utile | AA51: 5. Très utile | AB51: 5. Très utile | AC51: 5. Très utile | AD51: 1. Pas du tout utile | AE51: 1. Pas du tout utile | AF51: 1. Pas du tout utile | AG51: 1. Pas du tout utile | AH51: 3. Neutre | AI51: 5 | AJ51: 5. Plutôt facile (Assez intuitif) | AK51: 5. Plutôt d'accord (S'intègre assez bien) | AL51: 7 | AM51: 7 | AN51: 7 | AO51: 5 | AP51: 6 | AQ51: 5. Très important | AR51: 5. Très important | AS51: 3. Moyennement important | AT51: 3. Moyennement important | AU51: 4 | AV51: 7 | AW51: 6. Approfondie (Parcours certifiant ou auto-formation technique longue) | AX51: 5 | AY51: 5 | AZ51: 3. Plutôt en désaccord (Je procède à une revue importante) | BA51: 6 | BB51: 6 | BC51: 3 | BD51: 1 | BE51: Oui | BF51: 4 | BG51: 4. Neutre | BH51: 4 | BI51: 36-45 | BJ51: Femme | BK51: Associé | BL51: Plus de 10 ans | BM51: Audit Financier, Audit RSE | BN51: Cabinet local
A52: 46065.528 | B52: 7. Très fréquemment (Plusieurs fois par jour) | C52: Outils fournis/agréés par le cabinet (ex: Copilot sécurisé) | F52: Version entreprise | M52: Reformulation ou traduction de documents, Recherche d'informations ou de points techniques, Préparation de données (format, structuration, harmonisation des valeurs), Aide à la décision, Rapprochement/Comparaison de documents, Analyse de données et génération d'insights, Correction et mise en cohérence de documents, Rédaction (rapports, synthèses, notes, mails), Automatisation et création de scripts (SQL, VBA) | N52: De manière RECOMMANDÉE (cabinet encourage, mais facultatif) | O52: 5. Très utile | P52: 5. Très utile | Q52: 5. Très utile | R52: 5. Très utile | S52: 5. Très utile | T52: 3. Neutre | U52: 3. Neutre | V52: 3. Neutre | W52: 4. Utile | X52: 5. Très utile | Y52: 5. Très utile | Z52: 5. Très utile | AA52: 5. Très utile | AB52: 5. Très utile | AC52: 5. Très utile | AD52: 5. Très utile | AE52: 4. Utile | AF52: 5. Très utile | AG52: 5. Très utile | AH52: 5. Très utile | AI52: 7 | AJ52: 6. Facile (Maîtrise rapide) | AK52: 4. Ni d'accord, ni en désaccord | AL52: 6 | AM52: 6 | AN52: 3 | AO52: 2 | AP52: 7 | AQ52: 5. Très important | AR52: 1. Pas du tout important | AS52: 2. Peu important | AT52: 5. Très important | AU52: 1 | AV52: 7 | AW52: 5. Solide (Plusieurs jours de formation ou modules suivis) | AX52: 6 | AY52: 7 | AZ52: 6. D'accord (Je fais globalement confiance au résultat) | BA52: 6 | BB52: 7 | BC52: 7 | BD52: 5 | BE52: Oui | BF52: 4 | BG52: 4. Neutre | BH52: 7 | BI52: 26-35 | BJ52: Homme | BK52: Associé | BL52: Plus de 10 ans | BM52: Audit Financier | BN52: Cabinet local
A53: 46065.622 | B53: 5. Régulièrement (Plusieurs fois par semaine) | C53: Outils grand public (ex: ChatGPT, Gemini ) | F53: Version entreprise | L53: Version grand public | M53: Préparation de données (format, structuration, harmonisation des valeurs), Évaluation du contrôle interne, Reformulation ou traduction de documents, Correction et mise en cohérence de documents, Rédaction (rapports, synthèses, notes, mails), Recherche d'informations ou de points techniques | N53: De manière VOLONTAIRE (vous avez choisi vous-même) | O53: 5. Très utile | P53: 5. Très utile | Q53: 5. Très utile | R53: 5. Très utile | S53: 3. Neutre | T53: 3. Neutre | U53: 3. Neutre | V53: 3. Neutre | W53: 3. Neutre | X53: 5. Très utile | Y53: 5. Très utile | Z53: 5. Très utile | AA53: 5. Très utile | AB53: 5. Très utile | AC53: 3. Neutre | AD53: 3. Neutre | AE53: 3. Neutre | AF53: 3. Neutre | AG53: 3. Neutre | AH53: 5. Très utile | AI53: 7 | AJ53: 5. Plutôt facile (Assez intuitif) | AK53: 6. D'accord (S'intègre facilement) | AL53: 4 | AM53: 7 | AN53: 7 | AO53: 6 | AP53: 7 | AQ53: 5. Très important | AR53: 5. Très important | AS53: 5. Très important | AT53: 5. Très important | AU53: 3 | AV53: 7 | AW53: 4. Moyenne (Environ une journée de formation cumulée) | AX53: 7 | AY53: 7 | AZ53: 4. Neutre (Le niveau de vérification dépend de la complexité) | BA53: 5 | BB53: 7 | BC53: 2 | BD53: 1 | BE53: Oui | BF53: 4 | BG53: 4. Neutre | BH53: 6 | BI53: 36-45 | BJ53: Homme | BK53: Manager | BL53: Plus de 10 ans | BM53: Audit Financier | BN53: Cabinet international
A54: 46065.637 | B54: 6. Quotidiennement (Une fois par jour) | C54: Usage mix des deux | D54: Version grand public | E54: Version grand public, Version entreprise | F54: Version grand public | G54: Version grand public | M54: Reformulation ou traduction de documents, Recherche d'informations ou de points techniques, Rédaction (rapports, synthèses, notes, mails), Correction et mise en cohérence de documents, Rapprochement/Comparaison de documents, Préparation de données (format, structuration, harmonisation des valeurs), Analyse de données et génération d'insights | N54: De manière VOLONTAIRE (vous avez choisi vous-même) | O54: 5. Très utile | P54: 5. Très utile | Q54: 4. Utile | R54: 5. Très utile | S54: 3. Neutre | T54: 3. Neutre | U54: 3. Neutre | V54: 3. Neutre | W54: 3. Neutre | X54: 3. Neutre | Y54: 5. Très utile | Z54: 5. Très utile | AA54: 4. Utile | AB54: 5. Très utile | AC54: 3. Neutre | AD54: 5. Très utile | AE54: 5. Très utile | AF54: 5. Très utile | AG54: 5. Très utile | AH54: 5. Très utile | AI54: 7 | AJ54: 6. Facile (Maîtrise rapide) | AK54: 7. Tout à fait d'accord (Automatisme quotidien) | AL54: 4 | AM54: 7 | AN54: 7 | AO54: 5 | AP54: 7 | AQ54: 5. Très important | AR54: 5. Très important | AS54: 3. Moyennement important | AT54: 5. Très important | AU54: 2 | AV54: 1 | AW54: 5. Solide (Plusieurs jours de formation ou modules suivis) | AX54: 7 | AY54: 7 | AZ54: 4. Neutre (Le niveau de vérification dépend de la complexité) | BA54: 5 | BB54: 4 | BC54: 4 | BD54: 5 | BE54: déjà bien utilisé | BF54: 7 | BG54: 4. Neutre | BH54: 5 | BI54: 36-45 | BJ54: Homme | BK54: Associé | BL54: Plus de 10 ans | BM54: Expertise comptable | BN54: Cabinet régional
A55: 46065.721 | B55: 5. Régulièrement (Plusieurs fois par semaine) | C55: Outils fournis/agréés par le cabinet (ex: Copilot sécurisé) | E55: Version entreprise | F55: Version grand public | K55: Version entreprise | M55: Reformulation ou traduction de documents, Rédaction (rapports, synthèses, notes, mails), Recherche d'informations ou de points techniques | N55: De manière VOLONTAIRE (vous avez choisi vous-même) | O55: 4. Utile | P55: 4. Utile | Q55: 4. Utile | R55: 4. Utile | S55: 3. Neutre | T55: 3. Neutre | U55: 3. Neutre | V55: 3. Neutre | W55: 3. Neutre | X55: 4. Utile | Y55: 4. Utile | Z55: 4. Utile | AA55: 4. Utile | AB55: 4. Utile | AC55: 3. Neutre | AD55: 3. Neutre | AE55: 3. Neutre | AF55: 3. Neutre | AG55: 3. Neutre | AH55: 4. Utile | AI55: 6 | AJ55: 4. Ni facile, ni difficile (Prise en main normale) | AK55: 5. Plutôt d'accord (S'intègre assez bien) | AL55: 5 | AM55: 6 | AN55: 6 | AO55: 5 | AP55: 6 | AQ55: 4. Important | AR55: 4. Important | AS55: 4. Important | AT55: 4. Important | AU55: 6 | AV55: 6 | AW55: 4. Moyenne (Environ une journée de formation cumulée) | AX55: 4 | AY55: 5 | AZ55: 3. Plutôt en désaccord (Je procède à une revue importante) | BA55: 5 | BB55: 5 | BC55: 3 | BD55: 1 | BE55: Oui | BF55: 6 | BG55: 4. Neutre | BH55: 5 | BI55: 36-45 | BJ55: Homme | BK55: Associé | BL55: Plus de 10 ans | BM55: Audit Financier | BN55: Cabinet local
A56: 46065.868 | B56: 6. Quotidiennement (Une fois par jour) | C56: Usage mix des deux | F56: Version entreprise | G56: Version entreprise | K56: Version entreprise | M56: Recherche d'informations ou de points techniques, Revue d'estimations comptables (provisions, dépréciations), Rédaction (rapports, synthèses, notes, mails), Correction et mise en cohérence de documents, Reformulation ou traduction de documents | N56: De manière VOLONTAIRE (vous avez choisi vous-même) | O56: 4. Utile | P56: 4. Utile | Q56: 4. Utile | R56: 4. Utile | S56: 2. Peu utile | T56: 2. Peu utile | U56: 2. Peu utile | V56: 2. Peu utile | W56: 1. Pas du tout utile | X56: 4. Utile | Y56: 3. Neutre | Z56: 4. Utile | AA56: 4. Utile | AB56: 4. Utile | AC56: 3. Neutre | AD56: 3. Neutre | AE56: 2. Peu utile | AF56: 3. Neutre | AG56: 2. Peu utile | AH56: 5. Très utile | AI56: 3 | AJ56: 5. Plutôt facile (Assez intuitif) | AK56: 5. Plutôt d'accord (S'intègre assez bien) | AL56: 6 | AM56: 6 | AN56: 4 | AO56: 6 | AP56: 5 | AQ56: 4. Important | AR56: 3. Moyennement important | AS56: 4. Important | AT56: 4. Important | AU56: 4 | AV56: 6 | AW56: 2. Très limitée (Quelques vidéos ou articles consultés) | AX56: 5 | AY56: 5 | AZ56: 4. Neutre (Le niveau de vérification dépend de la complexité) | BA56: 5 | BB56: 5 | BC56: 4 | BD56: 4 | BE56: Oui | BF56: 4 | BG56: 4. Neutre | BH56: 6 | BI56: 46-55 | BJ56: Homme | BK56: Associé | BL56: Plus de 10 ans | BM56: Audit Financier, Audit Interne | BN56: Cabinet régional
A57: 46066.609 | B57: 6. Quotidiennement (Une fois par jour) | C57: Outils grand public (ex: ChatGPT, Gemini ) | F57: Version grand public | G57: Version grand public | M57: Préparation de données (format, structuration, harmonisation des valeurs), Automatisation et création de scripts (SQL, VBA), Rédaction (rapports, synthèses, notes, mails), Recherche d'informations ou de points techniques | N57: De manière VOLONTAIRE (vous avez choisi vous-même) | O57: 4. Utile | P57: 4. Utile | Q57: 4. Utile | R57: 1. Pas du tout utile | S57: 5. Très utile | T57: 4. Utile | U57: 1. Pas du tout utile | V57: 1. Pas du tout utile | W57: 2. Peu utile | X57: 4. Utile | Y57: 4. Utile | Z57: 4. Utile | AA57: 5. Très utile | AB57: 1. Pas du tout utile | AC57: 2. Peu utile | AD57: 3. Neutre | AE57: 1. Pas du tout utile | AF57: 1. Pas du tout utile | AG57: 2. Peu utile | AH57: 3. Neutre | AI57: 6 | AJ57: 4. Ni facile, ni difficile (Prise en main normale) | AK57: 6. D'accord (S'intègre facilement) | AL57: 4 | AM57: 7 | AN57: 7 | AO57: 6 | AP57: 2 | AQ57: 4. Important | AR57: 5. Très important | AS57: 4. Important | AT57: 3. Moyennement important | AU57: 1 | AV57: 5 | AW57: 5. Solide (Plusieurs jours de formation ou modules suivis) | AX57: 7 | AY57: 7 | AZ57: 1. Pas du tout d’accord (Je vérifie systématiquement chaque détail) | BA57: 7 | BB57: 7 | BC57: 3 | BD57: 2 | BE57: Non | BF57: 2 | BG57: 4. Neutre | BH57: 5 | BI57: 18-25 | BJ57: Homme | BK57: Junior | BL57: 2 - 3 ans | BM57: Audit Financier, Consolidation | BN57: Cabinet local
A58: 46072.602 | B58: 1. Jamais | BI58: 18-25 | BJ58: Femme | BK58: Junior | BL58: Moins de 2 ans | BM58: Audit Financier | BN58: Cabinet local
A59: 46072.736 | B59: 4. Parfois (Environ une fois par semaine) | C59: Outils fournis/agréés par le cabinet (ex: Copilot sécurisé) | E59: Version entreprise | M59: Préparation de données (format, structuration, harmonisation des valeurs), Correction et mise en cohérence de documents | N59: De manière VOLONTAIRE (vous avez choisi vous-même) | O59: 4. Utile | P59: 5. Très utile | Q59: 5. Très utile | R59: 5. Très utile | S59: 4. Utile | T59: 4. Utile | U59: 5. Très utile | V59: 4. Utile | W59: 3. Neutre | X59: 4. Utile | Y59: 5. Très utile | Z59: 4. Utile | AA59: 5. Très utile | AB59: 5. Très utile | AC59: 4. Utile | AD59: 4. Utile | AE59: 4. Utile | AF59: 4. Utile | AG59: 3. Neutre | AH59: 5. Très utile | AI59: 6 | AJ59: 6. Facile (Maîtrise rapide) | AK59: 6. D'accord (S'intègre facilement) | AL59: 4 | AM59: 5 | AN59: 5 | AO59: 6 | AP59: 6 | AQ59: 4. Important | AR59: 2. Peu important | AS59: 4. Important | AT59: 4. Important | AU59: 2 | AV59: 6 | AW59: 2. Très limitée (Quelques vidéos ou articles consultés) | AX59: 6 | AY59: 5 | AZ59: 5. Plutôt d'accord (Je vérifie uniquement les points clés) | BA59: 2 | BB59: 5 | BC59: 5 | BD59: 3 | BE59: Oui | BF59: 6 | BG59: 4. Neutre | BH59: 5 | BI59: 18-25 | BJ59: Femme | BK59: Junior | BL59: Moins de 2 ans | BM59: Audit Financier | BN59: Cabinet international
A60: 46072.742 | B60: 5. Régulièrement (Plusieurs fois par semaine) | C60: Usage mix des deux | E60: Version entreprise | M60: Reformulation ou traduction de documents, Préparation de données (format, structuration, harmonisation des valeurs), Recherche d'informations ou de points techniques | N60: De manière VOLONTAIRE (vous avez choisi vous-même) | O60: 4. Utile | P60: 5. Très utile | Q60: 4. Utile | R60: 4. Utile | S60: 4. Utile | T60: 3. Neutre | U60: 3. Neutre | V60: 3. Neutre | W60: 4. Utile | X60: 5. Très utile | Y60: 5. Très utile | Z60: 5. Très utile | AA60: 5. Très utile | AB60: 5. Très utile | AC60: 3. Neutre | AD60: 4. Utile | AE60: 3. Neutre | AF60: 3. Neutre | AG60: 4. Utile | AH60: 4. Utile | AI60: 6 | AJ60: 7. Très facile (Instinctif / Sans aide) | AK60: 7. Tout à fait d'accord (Automatisme quotidien) | AL60: 5 | AM60: 6 | AN60: 7 | AO60: 7 | AP60: 4 | AQ60: 5. Très important | AR60: 5. Très important | AS60: 3. Moyennement important | AT60: 3. Moyennement important | AU60: 3 | AV60: 3 | AW60: 1. Aucune | AX60: 5 | AY60: 4 | AZ60: 2. En désaccord (Je contrôle la quasi-totalité des éléments) | BA60: 6 | BB60: 7 | BC60: 4 | BD60: 3 | BE60: Non | BF60: 5 | BG60: 4. Neutre | BH60: 6 | BI60: 36-45 | BJ60: Femme | BK60: Associé | BL60: Plus de 10 ans | BM60: Audit Financier | BN60: Cabinet international
A61: 46072.758 | B61: 5. Régulièrement (Plusieurs fois par semaine) | C61: Outils fournis/agréés par le cabinet (ex: Copilot sécurisé) | D61: Version entreprise | E61: Version entreprise | F61: Version grand public | G61: Version grand public | H61: Version grand public | I61: Version grand public | J61: Version grand public | K61: Version entreprise | L61: Version grand public | M61: Analyse de données et génération d'insights, Correction et mise en cohérence de documents, Rédaction (rapports, synthèses, notes, mails), Recherche d'informations ou de points techniques, Rapprochement/Comparaison de documents, Reformulation ou traduction de documents | N61: De manière VOLONTAIRE (vous avez choisi vous-même) | O61: 4. Utile | P61: 4. Utile | Q61: 4. Utile | R61: 4. Utile | S61: 3. Neutre | T61: 3. Neutre | U61: 1. Pas du tout utile | V61: 1. Pas du tout utile | W61: 1. Pas du tout utile | X61: 4. Utile | Y61: 4. Utile | Z61: 4. Utile | AA61: 4. Utile | AB61: 4. Utile | AC61: 3. Neutre | AD61: 3. Neutre | AE61: 1. Pas du tout utile | AF61: 1. Pas du tout utile | AG61: 1. Pas du tout utile | AH61: 4. Utile | AI61: 5 | AJ61: 4. Ni facile, ni difficile (Prise en main normale) | AK61: 5. Plutôt d'accord (S'intègre assez bien) | AL61: 4 | AM61: 7 | AN61: 7 | AO61: 4 | AP61: 3 | AQ61: 5. Très important | AR61: 5. Très important | AS61: 5. Très important | AT61: 5. Très important | AU61: 4 | AV61: 4 | AW61: 4. Moyenne (Environ une journée de formation cumulée) | AX61: 6 | AY61: 6 | AZ61: 2. En désaccord (Je contrôle la quasi-totalité des éléments) | BA61: 6 | BB61: 7 | BC61: 3 | BD61: 1 | BE61: Non | BF61: 5 | BG61: 4. Neutre | BH61: 3 | BI61: 18-25 | BJ61: Homme | BK61: Junior | BL61: Moins de 2 ans | BM61: Audit Financier | BN61: Cabinet international
A62: 46073.359 | B62: 5. Régulièrement (Plusieurs fois par semaine) | C62: Usage mix des deux | E62: Version entreprise | M62: Reformulation ou traduction de documents, Recherche d'informations ou de points techniques | N62: De manière VOLONTAIRE (vous avez choisi vous-même) | O62: 3. Neutre | P62: 5. Très utile | Q62: 5. Très utile | R62: 3. Neutre | S62: 4. Utile | T62: 2. Peu utile | U62: 1. Pas du tout utile | V62: 1. Pas du tout utile | W62: 3. Neutre | X62: 5. Très utile | Y62: 4. Utile | Z62: 4. Utile | AA62: 5. Très utile | AB62: 4. Utile | AC62: 4. Utile | AD62: 2. Peu utile | AE62: 1. Pas du tout utile | AF62: 1. Pas du tout utile | AG62: 4. Utile | AH62: 4. Utile | AI62: 5 | AJ62: 5. Plutôt facile (Assez intuitif) | AK62: 5. Plutôt d'accord (S'intègre assez bien) | AL62: 5 | AM62: 7 | AN62: 5 | AO62: 3 | AP62: 2 | AQ62: 5. Très important | AR62: 5. Très important | AS62: 3. Moyennement important | AT62: 5. Très important | AU62: 2 | AV62: 3 | AW62: 5. Solide (Plusieurs jours de formation ou modules suivis) | AX62: 5 | AY62: 5 | AZ62: 1. Pas du tout d’accord (Je vérifie systématiquement chaque détail) | BA62: 4 | BB62: 5 | BC62: 5 | BD62: 2 | BE62: Oui | BF62: 5 | BG62: 4. Neutre | BH62: 5 | BI62: 18-25 | BJ62: Homme | BK62: Junior | BL62: Moins de 2 ans | BM62: Audit Financier | BN62: Cabinet international
A63: 46073.436 | B63: 5. Régulièrement (Plusieurs fois par semaine) | C63: Outils fournis/agréés par le cabinet (ex: Copilot sécurisé) | E63: Version entreprise | F63: Version grand public | G63: Version grand public | M63: Recherche d'informations ou de points techniques | N63: De manière RECOMMANDÉE (cabinet encourage, mais facultatif) | O63: 4. Utile | P63: 5. Très utile | Q63: 5. Très utile | R63: 5. Très utile | S63: 5. Très utile | T63: 3. Neutre | U63: 3. Neutre | V63: 4. Utile | W63: 2. Peu utile | X63: 5. Très utile | Y63: 3. Neutre | Z63: 4. Utile | AA63: 4. Utile | AB63: 3. Neutre | AC63: 5. Très utile | AD63: 2. Peu utile | AE63: 2. Peu utile | AF63: 3. Neutre | AG63: 2. Peu utile | AH63: 3. Neutre | AI63: 6 | AJ63: 6. Facile (Maîtrise rapide) | AK63: 5. Plutôt d'accord (S'intègre assez bien) | AL63: 6 | AM63: 7 | AN63: 6 | AO63: 2 | AP63: 7 | AQ63: 5. Très important | AR63: 5. Très important | AS63: 3. Moyennement important | AT63: 4. Important | AU63: 5 | AV63: 5 | AW63: 4. Moyenne (Environ une journée de formation cumulée) | AX63: 5 | AY63: 5 | AZ63: 4. Neutre (Le niveau de vérification dépend de la complexité) | BA63: 3 | BB63: 5 | BC63: 3 | BD63: 4 | BE63: Non | BF63: 2 | BG63: 4. Neutre | BH63: 6 | BI63: 18-25 | BJ63: Homme | BK63: Junior | BL63: Moins de 2 ans | BM63: Audit Financier | BN63: Cabinet régional
A64: 46073.481 | B64: 4. Parfois (Environ une fois par semaine) | C64: Outils fournis/agréés par le cabinet (ex: Copilot sécurisé) | E64: Version entreprise | K64: Version entreprise | M64: Rédaction (rapports, synthèses, notes, mails), Reformulation ou traduction de documents | N64: De manière RECOMMANDÉE (cabinet encourage, mais facultatif) | O64: 4. Utile | P64: 5. Très utile | Q64: 5. Très utile | R64: 4. Utile | S64: 4. Utile | T64: 2. Peu utile | U64: 1. Pas du tout utile | V64: 1. Pas du tout utile | W64: 1. Pas du tout utile | X64: 4. Utile | Y64: 4. Utile | Z64: 4. Utile | AA64: 4. Utile | AB64: 4. Utile | AC64: 4. Utile | AD64: 2. Peu utile | AE64: 2. Peu utile | AF64: 1. Pas du tout utile | AG64: 1. Pas du tout utile | AH64: 2. Peu utile | AI64: 6 | AJ64: 6. Facile (Maîtrise rapide) | AK64: 5. Plutôt d'accord (S'intègre assez bien) | AL64: 2 | AM64: 7 | AN64: 5 | AO64: 6 | AP64: 7 | AQ64: 5. Très important | AR64: 3. Moyennement important | AS64: 3. Moyennement important | AT64: 5. Très important | AU64: 4 | AV64: 6 | AW64: 3. Faible (Moins de 5 heures de formation au total) | AX64: 5 | AY64: 5 | AZ64: 4. Neutre (Le niveau de vérification dépend de la complexité) | BA64: 6 | BB64: 6 | BC64: 7 | BD64: 4 | BE64: Oui | BF64: 6 | BG64: 4. Neutre | BH64: 6 | BI64: 18-25 | BJ64: Homme | BK64: Junior | BL64: Moins de 2 ans | BM64: Audit Financier | BN64: Cabinet international
A65: 46073.565 | B65: 7. Très fréquemment (Plusieurs fois par jour) | C65: Outils fournis/agréés par le cabinet (ex: Copilot sécurisé) | E65: Version entreprise | K65: Version entreprise | M65: Reformulation ou traduction de documents, Correction et mise en cohérence de documents, Rédaction (rapports, synthèses, notes, mails), Aide à la décision, Recherche d'informations ou de points techniques, Analyse de données et génération d'insights | N65: De manière VOLONTAIRE (vous avez choisi vous-même) | O65: 3. Neutre | P65: 5. Très utile | Q65: 4. Utile | R65: 3. Neutre | S65: 5. Très utile | T65: 3. Neutre | U65: 4. Utile | V65: 4. Utile | W65: 4. Utile | X65: 5. Très utile | Y65: 3. Neutre | Z65: 4. Utile | AA65: 4. Utile | AB65: 3. Neutre | AC65: 5. Très utile | AD65: 3. Neutre | AE65: 3. Neutre | AF65: 3. Neutre | AG65: 3. Neutre | AH65: 4. Utile | AI65: 6 | AJ65: 7. Très facile (Instinctif / Sans aide) | AK65: 7. Tout à fait d'accord (Automatisme quotidien) | AL65: 2 | AM65: 7 | AN65: 4 | AO65: 5 | AP65: 6 | AQ65: 5. Très important | AR65: 5. Très important | AS65: 3. Moyennement important | AT65: 5. Très important | AU65: 5 | AV65: 7 | AW65: 3. Faible (Moins de 5 heures de formation au total) | AX65: 6 | AY65: 5 | AZ65: 1. Pas du tout d’accord (Je vérifie systématiquement chaque détail) | BA65: 7 | BB65: 6 | BC65: 4 | BD65: 1 | BE65: Non | BF65: 5 | BG65: 4. Neutre | BH65: 5 | BI65: 26-35 | BJ65: Femme | BK65: Senior | BL65: 4 - 5 ans | BM65: Audit Financier | BN65: Cabinet régional
A66: 46074.475 | B66: 7. Très fréquemment (Plusieurs fois par jour) | C66: Outils fournis/agréés par le cabinet (ex: Copilot sécurisé) | E66: Version entreprise | M66: Rédaction (rapports, synthèses, notes, mails), Recherche d'informations ou de points techniques, Analyse de données et génération d'insights | N66: De manière RECOMMANDÉE (cabinet encourage, mais facultatif) | O66: 4. Utile | P66: 4. Utile | Q66: 4. Utile | R66: 4. Utile | S66: 3. Neutre | T66: 3. Neutre | U66: 2. Peu utile | V66: 2. Peu utile | W66: 2. Peu utile | X66: 3. Neutre | Y66: 4. Utile | Z66: 4. Utile | AA66: 4. Utile | AB66: 3. Neutre | AC66: 3. Neutre | AD66: 3. Neutre | AE66: 3. Neutre | AF66: 3. Neutre | AG66: 3. Neutre | AH66: 3. Neutre | AI66: 7 | AJ66: 5. Plutôt facile (Assez intuitif) | AK66: 6. D'accord (S'intègre facilement) | AL66: 6 | AM66: 7 | AN66: 2 | AO66: 5 | AP66: 5 | AQ66: 4. Important | AR66: 3. Moyennement important | AS66: 3. Moyennement important | AT66: 5. Très important | AU66: 3 | AV66: 3 | AW66: 4. Moyenne (Environ une journée de formation cumulée) | AX66: 5 | AY66: 5 | AZ66: 3. Plutôt en désaccord (Je procède à une revue importante) | BA66: 6 | BB66: 6 | BC66: 5 | BD66: 2 | BE66: Non | BF66: 6 | BG66: 4. Neutre | BH66: 7 | BI66: 18-25 | BJ66: Homme | BK66: Junior | BL66: Moins de 2 ans | BM66: Audit Financier | BN66: Cabinet international
A67: 46074.655 | B67: 5. Régulièrement (Plusieurs fois par semaine) | C67: Outils grand public (ex: ChatGPT, Gemini ) | F67: Version grand public | G67: Version grand public | M67: Rédaction (rapports, synthèses, notes, mails), Reformulation ou traduction de documents | N67: De manière VOLONTAIRE (vous avez choisi vous-même) | O67: 5. Très utile | P67: 5. Très utile | Q67: 5. Très utile | R67: 5. Très utile | S67: 3. Neutre | T67: 2. Peu utile | U67: 2. Peu utile | V67: 2. Peu utile | W67: 4. Utile | X67: 4. Utile | Y67: 5. Très utile | Z67: 5. Très utile | AA67: 5. Très utile | AB67: 4. Utile | AC67: 3. Neutre | AD67: 3. Neutre | AE67: 2. Peu utile | AF67: 2. Peu utile | AG67: 4. Utile | AH67: 4. Utile | AI67: 7 | AJ67: 7. Très facile (Instinctif / Sans aide) | AK67: 6. D'accord (S'intègre facilement) | AL67: 2 | AM67: 6 | AN67: 5 | AO67: 4 | AP67: 3 | AQ67: 5. Très important | AR67: 5. Très important | AS67: 4. Important | AT67: 4. Important | AU67: 1 | AV67: 7 | AW67: 5. Solide (Plusieurs jours de formation ou modules suivis) | AX67: 7 | AY67: 6 | AZ67: 1. Pas du tout d’accord (Je vérifie systématiquement chaque détail) | BA67: 7 | BB67: 7 | BC67: 5 | BD67: 1 | BE67: Oui | BF67: 7 | BG67: 4. Neutre | BH67: 7 | BI67: 26-35 | BJ67: Femme | BK67: Senior | BL67: 2 - 3 ans | BM67: Audit Financier, Audit Interne | BN67: Cabinet local
A68: 46075.012 | B68: 5. Régulièrement (Plusieurs fois par semaine) | C68: Outils fournis/agréés par le cabinet (ex: Copilot sécurisé) | F68: Version entreprise | M68: Détermination du seuil de signification, Aide à la décision, Évaluation du contrôle interne, Reformulation ou traduction de documents | N68: De manière RECOMMANDÉE (cabinet encourage, mais facultatif) | O68: 4. Utile | P68: 4. Utile | Q68: 4. Utile | R68: 4. Utile | S68: 4. Utile | T68: 4. Utile | U68: 4. Utile | V68: 4. Utile | W68: 4. Utile | X68: 4. Utile | Y68: 4. Utile | Z68: 4. Utile | AA68: 4. Utile | AB68: 4. Utile | AC68: 5. Très utile | AD68: 4. Utile | AE68: 4. Utile | AF68: 4. Utile | AG68: 4. Utile | AH68: 4. Utile | AI68: 3 | AJ68: 4. Ni facile, ni difficile (Prise en main normale) | AK68: 1. Tout à fait en désaccord (Friction totale / Inutilisable) | AL68: 1 | AM68: 1 | AN68: 1 | AO68: 3 | AP68: 5 | AQ68: 3. Moyennement important | AR68: 3. Moyennement important | AS68: 1. Pas du tout important | AT68: 2. Peu important | AU68: 1 | AV68: 5 | AW68: 4. Moyenne (Environ une journée de formation cumulée) | AX68: 5 | AY68: 4 | AZ68: 1. Pas du tout d’accord (Je vérifie systématiquement chaque détail) | BA68: 7 | BB68: 5 | BC68: 4 | BD68: 1 | BE68: Oui | BF68: 3 | BG68: 1. Pas du tout d’accord | BH68: 4 | BI68: 36-45 | BJ68: Homme | BK68: Senior | BL68: 4 - 5 ans | BM68: Audit Financier | BN68: Cabinet international
A69: 46075.476 | B69: 5. Régulièrement (Plusieurs fois par semaine) | C69: Outils fournis/agréés par le cabinet (ex: Copilot sécurisé) | E69: Version entreprise | M69: Analyse de données et génération d'insights, Recherche d'informations ou de points techniques, Reformulation ou traduction de documents, Rédaction (rapports, synthèses, notes, mails), Correction et mise en cohérence de documents | N69: De manière VOLONTAIRE (vous avez choisi vous-même) | O69: 4. Utile | P69: 5. Très utile | Q69: 5. Très utile | R69: 4. Utile | S69: 4. Utile | T69: 3. Neutre | U69: 3. Neutre | V69: 2. Peu utile | W69: 3. Neutre | X69: 4. Utile | Y69: 5. Très utile | Z69: 5. Très utile | AA69: 5. Très utile | AB69: 4. Utile | AC69: 4. Utile | AD69: 3. Neutre | AE69: 3. Neutre | AF69: 3. Neutre | AG69: 3. Neutre | AH69: 4. Utile | AI69: 5 | AJ69: 6. Facile (Maîtrise rapide) | AK69: 6. D'accord (S'intègre facilement) | AL69: 6 | AM69: 6 | AN69: 2 | AO69: 4 | AP69: 5 | AQ69: 4. Important | AR69: 5. Très important | AS69: 4. Important | AT69: 4. Important | AU69: 5 | AV69: 6 | AW69: 5. Solide (Plusieurs jours de formation ou modules suivis) | AX69: 5 | AY69: 5 | AZ69: 3. Plutôt en désaccord (Je procède à une revue importante) | BA69: 5 | BB69: 6 | BC69: 5 | BD69: 2 | BE69: Non | BF69: 5 | BG69: 4. Neutre | BH69: 5 | BI69: 18-25 | BJ69: Femme | BK69: Junior | BL69: Moins de 2 ans | BM69: Audit Financier | BN69: Cabinet international
A70: 46075.528 | B70: 6. Quotidiennement (Une fois par jour) | C70: Outils grand public (ex: ChatGPT, Gemini ) | E70: Version grand public | F70: Version grand public | M70: Correction et mise en cohérence de documents, Recherche d'informations ou de points techniques, Rédaction (rapports, synthèses, notes, mails), Reformulation ou traduction de documents, Automatisation et création de scripts (SQL, VBA) | N70: De manière VOLONTAIRE (vous avez choisi vous-même) | O70: 4. Utile | P70: 4. Utile | Q70: 4. Utile | R70: 4. Utile | S70: 5. Très utile | T70: 3. Neutre | U70: 3. Neutre | V70: 3. Neutre | W70: 3. Neutre | X70: 4. Utile | Y70: 5. Très utile | Z70: 5. Très utile | AA70: 4. Utile | AB70: 4. Utile | AC70: 5. Très utile | AD70: 3. Neutre | AE70: 3. Neutre | AF70: 3. Neutre | AG70: 3. Neutre | AH70: 5. Très utile | AI70: 6 | AJ70: 5. Plutôt facile (Assez intuitif) | AK70: 5. Plutôt d'accord (S'intègre assez bien) | AL70: 4 | AM70: 6 | AN70: 7 | AO70: 6 | AP70: 4 | AQ70: 5. Très important | AR70: 4. Important | AS70: 4. Important | AT70: 3. Moyennement important | AU70: 3 | AV70: 7 | AW70: 4. Moyenne (Environ une journée de formation cumulée) | AX70: 5 | AY70: 5 | AZ70: 2. En désaccord (Je contrôle la quasi-totalité des éléments) | BA70: 6 | BB70: 5 | BC70: 1 | BD70: 1 | BE70: Non | BF70: 5 | BG70: 4. Neutre | BH70: 4 | BI70: 26-35 | BJ70: Homme | BK70: Senior | BL70: 2 - 3 ans | BM70: Audit Financier, Audit Interne | BN70: Cabinet local
A71: 46075.596 | B71: 1. Jamais | BI71: 26-35 | BJ71: Homme | BK71: Junior | BL71: 4 - 5 ans | BM71: Audit Financier, Expertise comptable | BN71: Cabinet international
A72: 46076.477 | B72: 5. Régulièrement (Plusieurs fois par semaine) | C72: Usage mix des deux | D72: Version entreprise | E72: Version entreprise | K72: Version entreprise | M72: Correction et mise en cohérence de documents, Recherche d'informations ou de points techniques, Reformulation ou traduction de documents | N72: De manière RECOMMANDÉE (cabinet encourage, mais facultatif) | O72: 3. Neutre | P72: 3. Neutre | Q72: 3. Neutre | R72: 3. Neutre | S72: 3. Neutre | T72: 3. Neutre | U72: 3. Neutre | V72: 3. Neutre | W72: 3. Neutre | X72: 5. Très utile | Y72: 3. Neutre | Z72: 3. Neutre | AA72: 3. Neutre | AB72: 3. Neutre | AC72: 3. Neutre | AD72: 3. Neutre | AE72: 3. Neutre | AF72: 3. Neutre | AG72: 3. Neutre | AH72: 5. Très utile | AI72: 5 | AJ72: 5. Plutôt facile (Assez intuitif) | AK72: 5. Plutôt d'accord (S'intègre assez bien) | AL72: 5 | AM72: 7 | AN72: 7 | AO72: 5 | AP72: 7 | AQ72: 5. Très important | AR72: 5. Très important | AS72: 5. Très important | AT72: 5. Très important | AU72: 7 | AV72: 5 | AW72: 3. Faible (Moins de 5 heures de formation au total) | AX72: 6 | AY72: 5 | AZ72: 2. En désaccord (Je contrôle la quasi-totalité des éléments) | BA72: 6 | BB72: 7 | BC72: 4 | BD72: 5 | BE72: Oui | BF72: 6 | BG72: 4. Neutre | BH72: 5 | BI72: 36-45 | BJ72: Femme | BK72: Associé | BL72: Plus de 10 ans | BM72: Audit Financier | BN72: Cabinet régional
A73: 46076.663 | B73: 4. Parfois (Environ une fois par semaine) | C73: Usage mix des deux | E73: Version grand public | F73: Version grand public, Version entreprise | M73: Aide à la décision, Recherche d'informations ou de points techniques, Rapprochement/Comparaison de documents, Revue d'estimations comptables (provisions, dépréciations) | N73: De manière RECOMMANDÉE (cabinet encourage, mais facultatif) | O73: 4. Utile | P73: 4. Utile | Q73: 3. Neutre | R73: 4. Utile | S73: 3. Neutre | T73: 3. Neutre | U73: 3. Neutre | V73: 3. Neutre | W73: 4. Utile | X73: 4. Utile | Y73: 4. Utile | Z73: 4. Utile | AA73: 4. Utile | AB73: 4. Utile | AC73: 3. Neutre | AD73: 3. Neutre | AE73: 3. Neutre | AF73: 4. Utile | AG73: 4. Utile | AH73: 3. Neutre | AI73: 6 | AJ73: 4. Ni facile, ni difficile (Prise en main normale) | AK73: 5. Plutôt d'accord (S'intègre assez bien) | AL73: 4 | AM73: 7 | AN73: 7 | AO73: 7 | AP73: 5 | AQ73: 4. Important | AR73: 5. Très important | AS73: 4. Important | AT73: 4. Important | AU73: 5 | AV73: 5 | AW73: 2. Très limitée (Quelques vidéos ou articles consultés) | AX73: 5 | AY73: 5 | AZ73: 1. Pas du tout d’accord (Je vérifie systématiquement chaque détail) | BA73: 6 | BB73: 7 | BC73: 5 | BD73: 4 | BE73: Non | BF73: 5 | BG73: 4. Neutre | BH73: 6 | BI73: +65 | BJ73: Homme | BK73: Associé | BL73: Plus de 10 ans | BM73: Audit Financier | BN73: Cabinet local
A74: 46076.684 | B74: 6. Quotidiennement (Une fois par jour) | C74: Outils fournis/agréés par le cabinet (ex: Copilot sécurisé) | E74: Version entreprise | K74: Version entreprise | M74: Reformulation ou traduction de documents, Recherche d'informations ou de points techniques, Rapprochement/Comparaison de documents, Correction et mise en cohérence de documents | N74: De manière RECOMMANDÉE (cabinet encourage, mais facultatif) | O74: 5. Très utile | P74: 5. Très utile | Q74: 5. Très utile | R74: 5. Très utile | S74: 5. Très utile | T74: 5. Très utile | U74: 4. Utile | V74: 4. Utile | W74: 4. Utile | X74: 4. Utile | Y74: 4. Utile | Z74: 4. Utile | AA74: 4. Utile | AB74: 5. Très utile | AC74: 4. Utile | AD74: 4. Utile | AE74: 4. Utile | AF74: 5. Très utile | AG74: 4. Utile | AH74: 4. Utile | AI74: 7 | AJ74: 6. Facile (Maîtrise rapide) | AK74: 6. D'accord (S'intègre facilement) | AL74: 6 | AM74: 6 | AN74: 6 | AO74: 3 | AP74: 3 | AQ74: 4. Important | AR74: 4. Important | AS74: 3. Moyennement important | AT74: 4. Important | AU74: 4 | AV74: 4 | AW74: 6. Approfondie (Parcours certifiant ou auto-formation technique longue) | AX74: 5 | AY74: 4 | AZ74: 5. Plutôt d'accord (Je vérifie uniquement les points clés) | BA74: 6 | BB74: 5 | BC74: 5 | BD74: 5 | BE74: Oui | BF74: 6 | BG74: 6. D’accord | BH74: 6 | BI74: 36-45 | BJ74: Homme | BK74: Associé | BL74: Plus de 10 ans | BM74: Audit Financier | BN74: Cabinet international
A75: 46076.702 | B75: 6. Quotidiennement (Une fois par jour) | C75: Outils grand public (ex: ChatGPT, Gemini ) | F75: Version grand public | M75: Rédaction (rapports, synthèses, notes, mails), Recherche d'informations ou de points techniques | N75: De manière VOLONTAIRE (vous avez choisi vous-même) | O75: 3. Neutre | P75: 3. Neutre | Q75: 5. Très utile | R75: 3. Neutre | S75: 3. Neutre | T75: 3. Neutre | U75: 3. Neutre | V75: 3. Neutre | W75: 1. Pas du tout utile | X75: 3. Neutre | Y75: 3. Neutre | Z75: 3. Neutre | AA75: 5. Très utile | AB75: 3. Neutre | AC75: 3. Neutre | AD75: 3. Neutre | AE75: 3. Neutre | AF75: 3. Neutre | AG75: 1. Pas du tout utile | AH75: 3. Neutre | AI75: 5 | AJ75: 7. Très facile (Instinctif / Sans aide) | AK75: 7. Tout à fait d'accord (Automatisme quotidien) | AL75: 5 | AM75: 7 | AN75: 7 | AO75: 4 | AP75: 1 | AQ75: 1. Pas du tout important | AR75: 5. Très important | AS75: 1. Pas du tout important | AT75: 1. Pas du tout important | AU75: 1 | AV75: 1 | AW75: 7. Experte (Maîtrise totale / Capacité à former les autres) | AX75: 7 | AY75: 7 | AZ75: 1. Pas du tout d’accord (Je vérifie systématiquement chaque détail) | BA75: 7 | BB75: 7 | BC75: 1 | BD75: 1 | BE75: Non | BF75: 1 | BG75: 4. Neutre | BH75: 4 | BI75: 26-35 | BJ75: Femme | BK75: Associé | BL75: 8 - 10 ans | BM75: Audit Financier | BN75: Cabinet local
A76: 46076.738 | B76: 5. Régulièrement (Plusieurs fois par semaine) | C76: Usage mix des deux | E76: Version grand public | F76: Version grand public | K76: Version entreprise | M76: Recherche d'informations ou de points techniques, Rédaction (rapports, synthèses, notes, mails), Aide à la décision, Reformulation ou traduction de documents | N76: De manière RECOMMANDÉE (cabinet encourage, mais facultatif) | O76: 3. Neutre | P76: 4. Utile | Q76: 5. Très utile | R76: 4. Utile | S76: 3. Neutre | T76: 3. Neutre | U76: 3. Neutre | V76: 3. Neutre | W76: 4. Utile | X76: 3. Neutre | Y76: 4. Utile | Z76: 4. Utile | AA76: 5. Très utile | AB76: 4. Utile | AC76: 3. Neutre | AD76: 3. Neutre | AE76: 3. Neutre | AF76: 3. Neutre | AG76: 4. Utile | AH76: 4. Utile | AI76: 5 | AJ76: 3. Plutôt difficile (Peu intuitif) | AK76: 5. Plutôt d'accord (S'intègre assez bien) | AL76: 7 | AM76: 4 | AN76: 6 | AO76: 6 | AP76: 7 | AQ76: 5. Très important | AR76: 5. Très important | AS76: 5. Très important | AT76: 5. Très important | AU76: 4 | AV76: 6 | AW76: 3. Faible (Moins de 5 heures de formation au total) | AX76: 6 | AY76: 5 | AZ76: 3. Plutôt en désaccord (Je procède à une revue importante) | BA76: 4 | BB76: 6 | BC76: 6 | BD76: 3 | BE76: Cela dépendra de notre maitrise des outils de IAG | BF76: 6 | BG76: 4. Neutre | BH76: 6 | BI76: 46-55 | BJ76: Homme | BK76: Associé | BL76: Plus de 10 ans | BM76: EXPERTISE COMPTABLE ET COMMISSARIAT AUX COMPTES | BN76: Cabinet local
A77: 46076.757 | B77: 4. Parfois (Environ une fois par semaine) | C77: Outils fournis/agréés par le cabinet (ex: Copilot sécurisé) | F77: Version grand public | L77: Version entreprise | M77: Rapprochement/Comparaison de documents, Analyse de données et génération d'insights, Préparation de données (format, structuration, harmonisation des valeurs), Reformulation ou traduction de documents, Revue d'estimations comptables (provisions, dépréciations), Correction et mise en cohérence de documents | N77: De manière RECOMMANDÉE (cabinet encourage, mais facultatif) | O77: 4. Utile | P77: 5. Très utile | Q77: 4. Utile | R77: 5. Très utile | S77: 4. Utile | T77: 4. Utile | U77: 3. Neutre | V77: 5. Très utile | W77: 4. Utile | X77: 5. Très utile | Y77: 5. Très utile | Z77: 5. Très utile | AA77: 4. Utile | AB77: 5. Très utile | AC77: 4. Utile | AD77: 4. Utile | AE77: 3. Neutre | AF77: 4. Utile | AG77: 3. Neutre | AH77: 4. Utile | AI77: 5 | AJ77: 6. Facile (Maîtrise rapide) | AK77: 6. D'accord (S'intègre facilement) | AL77: 4 | AM77: 6 | AN77: 5 | AO77: 5 | AP77: 5 | AQ77: 4. Important | AR77: 5. Très important | AS77: 4. Important | AT77: 4. Important | AU77: 3 | AV77: 3 | AW77: 4. Moyenne (Environ une journée de formation cumulée) | AX77: 6 | AY77: 6 | AZ77: 2. En désaccord (Je contrôle la quasi-totalité des éléments) | BA77: 5 | BB77: 6 | BC77: 5 | BD77: 2 | BE77: Oui | BF77: 6 | BG77: 4. Neutre | BH77: 6 | BI77: 56-65 | BJ77: Homme | BK77: Associé | BL77: Plus de 10 ans | BM77: Audit Financier, Audit IT, Audit Interne | BN77: Cabinet international | BO77: Non
A78: 46076.758 | B78: 5. Régulièrement (Plusieurs fois par semaine) | C78: Outils grand public (ex: ChatGPT, Gemini ) | F78: Version entreprise | M78: Correction et mise en cohérence de documents, Reformulation ou traduction de documents | N78: De manière VOLONTAIRE (vous avez choisi vous-même) | O78: 1. Pas du tout utile | P78: 4. Utile | Q78: 3. Neutre | R78: 3. Neutre | S78: 3. Neutre | T78: 3. Neutre | U78: 3. Neutre | V78: 3. Neutre | W78: 3. Neutre | X78: 4. Utile | Y78: 1. Pas du tout utile | Z78: 4. Utile | AA78: 4. Utile | AB78: 3. Neutre | AC78: 3. Neutre | AD78: 3. Neutre | AE78: 3. Neutre | AF78: 3. Neutre | AG78: 3. Neutre | AH78: 3. Neutre | AI78: 3 | AJ78: 4. Ni facile, ni difficile (Prise en main normale) | AK78: 3. Plutôt en désaccord (Demande un effort conscient) | AL78: 7 | AM78: 7 | AN78: 7 | AO78: 7 | AP78: 7 | AQ78: 4. Important | AR78: 5. Très important | AS78: 3. Moyennement important | AT78: 5. Très important | AU78: 7 | AV78: 4 | AW78: 3. Faible (Moins de 5 heures de formation au total) | AX78: 2 | AY78: 2 | AZ78: 1. Pas du tout d’accord (Je vérifie systématiquement chaque détail) | BA78: 7 | BB78: 7 | BC78: 4 | BD78: 1 | BE78: Oui | BF78: 5 | BG78: 4. Neutre | BH78: 3 | BI78: 36-45 | BJ78: Homme | BK78: Associé | BL78: Plus de 10 ans | BM78: Audit Financier | BN78: Cabinet local
A79: 46076.885 | B79: 3. Rarement (1 à 3 fois par mois) | C79: Usage mix des deux | E79: Version entreprise | F79: Version entreprise | M79: Correction et mise en cohérence de documents, Reformulation ou traduction de documents | N79: De manière VOLONTAIRE (vous avez choisi vous-même) | O79: 5. Très utile | P79: 5. Très utile | Q79: 5. Très utile | R79: 5. Très utile | S79: 2. Peu utile | T79: 4. Utile | U79: 3. Neutre | V79: 3. Neutre | W79: 3. Neutre | X79: 5. Très utile | Y79: 5. Très utile | Z79: 5. Très utile | AA79: 4. Utile | AB79: 4. Utile | AC79: 4. Utile | AD79: 4. Utile | AE79: 4. Utile | AF79: 3. Neutre | AG79: 3. Neutre | AH79: 5. Très utile | AI79: 5 | AJ79: 5. Plutôt facile (Assez intuitif) | AK79: 5. Plutôt d'accord (S'intègre assez bien) | AL79: 6 | AM79: 7 | AN79: 7 | AO79: 7 | AP79: 5 | AQ79: 4. Important | AR79: 5. Très important | AS79: 5. Très important | AT79: 4. Important | AU79: 5 | AV79: 7 | AW79: 4. Moyenne (Environ une journée de formation cumulée) | AX79: 4 | AY79: 6 | AZ79: 1. Pas du tout d’accord (Je vérifie systématiquement chaque détail) | BA79: 7 | BB79: 6 | BC79: 5 | BD79: 5 | BE79: Oui | BF79: 7 | BG79: 4. Neutre | BH79: 5 | BI79: 36-45 | BJ79: Femme | BK79: Associé | BL79: Plus de 10 ans | BM79: Audit Financier | BN79: Cabinet local
A80: 46077.282 | B80: 1. Jamais | BI80: 36-45 | BJ80: Femme | BK80: Associé | BL80: Plus de 10 ans | BM80: Audit Financier, Expertise comptable | BN80: Cabinet local
A81: 46077.371 | B81: 5. Régulièrement (Plusieurs fois par semaine) | C81: Usage mix des deux | E81: Version grand public | F81: Version grand public | K81: Version entreprise | M81: Reformulation ou traduction de documents, Recherche d'informations ou de points techniques | N81: De manière VOLONTAIRE (vous avez choisi vous-même) | O81: 5. Très utile | P81: 4. Utile | Q81: 2. Peu utile | R81: 2. Peu utile | S81: 5. Très utile | T81: 1. Pas du tout utile | U81: 2. Peu utile | V81: 3. Neutre | W81: 3. Neutre | X81: 5. Très utile | Y81: 5. Très utile | Z81: 5. Très utile | AA81: 4. Utile | AB81: 3. Neutre | AC81: 5. Très utile | AD81: 3. Neutre | AE81: 3. Neutre | AF81: 2. Peu utile | AG81: 2. Peu utile | AH81: 5. Très utile | AI81: 6 | AJ81: 5. Plutôt facile (Assez intuitif) | AK81: 6. D'accord (S'intègre facilement) | AL81: 5 | AM81: 7 | AN81: 7 | AO81: 6 | AP81: 1 | AQ81: 4. Important | AR81: 5. Très important | AS81: 4. Important | AT81: 1. Pas du tout important | AU81: 7 | AV81: 7 | AW81: 1. Aucune | AX81: 6 | AY81: 6 | AZ81: 2. En désaccord (Je contrôle la quasi-totalité des éléments) | BA81: 6 | BB81: 7 | BC81: 5 | BD81: 6 | BE81: Oui | BF81: 5 | BG81: 4. Neutre | BH81: 4 | BI81: 26-35 | BJ81: Homme | BK81: Associé | BL81: 4 - 5 ans | BM81: Audit Financier | BN81: Cabinet local
A82: 46077.419 | B82: 5. Régulièrement (Plusieurs fois par semaine) | C82: Outils fournis/agréés par le cabinet (ex: Copilot sécurisé) | E82: Version entreprise | M82: Reformulation ou traduction de documents, Recherche d'informations ou de points techniques, Préparation de données (format, structuration, harmonisation des valeurs) | N82: De manière RECOMMANDÉE (cabinet encourage, mais facultatif) | O82: 5. Très utile | P82: 5. Très utile | Q82: 5. Très utile | R82: 3. Neutre | S82: 3. Neutre | T82: 3. Neutre | U82: 3. Neutre | V82: 3. Neutre | W82: 4. Utile | X82: 5. Très utile | Y82: 4. Utile | Z82: 4. Utile | AA82: 4. Utile | AB82: 3. Neutre | AC82: 3. Neutre | AD82: 3. Neutre | AE82: 3. Neutre | AF82: 3. Neutre | AG82: 3. Neutre | AH82: 4. Utile | AI82: 5 | AJ82: 6. Facile (Maîtrise rapide) | AK82: 6. D'accord (S'intègre facilement) | AL82: 6 | AM82: 6 | AN82: 6 | AO82: 6 | AP82: 6 | AQ82: 5. Très important | AR82: 5. Très important | AS82: 3. Moyennement important | AT82: 5. Très important | AU82: 5 | AV82: 7 | AW82: 4. Moyenne (Environ une journée de formation cumulée) | AX82: 4 | AY82: 4 | AZ82: 2. En désaccord (Je contrôle la quasi-totalité des éléments) | BA82: 5 | BB82: 2 | BC82: 4 | BD82: 4 | BE82: Oui | BF82: 6 | BG82: 4. Neutre | BH82: 5 | BI82: 18-25 | BJ82: Homme | BK82: Senior | BL82: 2 - 3 ans | BM82: Audit Financier | BN82: Cabinet international
A83: 46077.477 | B83: 4. Parfois (Environ une fois par semaine) | C83: Outils grand public (ex: ChatGPT, Gemini ) | F83: Version grand public | M83: Recherche d'informations ou de points techniques, Reformulation ou traduction de documents, Rédaction (rapports, synthèses, notes, mails), Préparation de données (format, structuration, harmonisation des valeurs) | N83: De manière VOLONTAIRE (vous avez choisi vous-même) | O83: 5. Très utile | P83: 4. Utile | Q83: 4. Utile | R83: 5. Très utile | S83: 3. Neutre | T83: 3. Neutre | U83: 2. Peu utile | V83: 2. Peu utile | W83: 2. Peu utile | X83: 5. Très utile | Y83: 4. Utile | Z83: 3. Neutre | AA83: 3. Neutre | AB83: 4. Utile | AC83: 3. Neutre | AD83: 3. Neutre | AE83: 2. Peu utile | AF83: 2. Peu utile | AG83: 3. Neutre | AH83: 4. Utile | AI83: 5 | AJ83: 4. Ni facile, ni difficile (Prise en main normale) | AK83: 5. Plutôt d'accord (S'intègre assez bien) | AL83: 5 | AM83: 6 | AN83: 6 | AO83: 6 | AP83: 4 | AQ83: 4. Important | AR83: 4. Important | AS83: 5. Très important | AT83: 4. Important | AU83: 5 | AV83: 7 | AW83: 2. Très limitée (Quelques vidéos ou articles consultés) | AX83: 5 | AY83: 4 | AZ83: 2. En désaccord (Je contrôle la quasi-totalité des éléments) | BA83: 6 | BB83: 4 | BC83: 4 | BD83: 2 | BE83: Oui | BF83: 6 | BG83: 4. Neutre | BH83: 4 | BI83: 56-65 | BJ83: Homme | BK83: Associé | BL83: Plus de 10 ans | BM83: Audit Financier | BN83: Cabinet local | BO83: opportunité qui doit être fortement encadré pour l utilisation en audit
A84: 46078.918 | B84: 6. Quotidiennement (Une fois par jour) | C84: Outils fournis/agréés par le cabinet (ex: Copilot sécurisé) | K84: Version entreprise | M84: Aide à la décision, Rédaction (rapports, synthèses, notes, mails), Recherche d'informations ou de points techniques | N84: De manière RECOMMANDÉE (cabinet encourage, mais facultatif) | O84: 2. Peu utile | P84: 2. Peu utile | Q84: 5. Très utile | R84: 4. Utile | S84: 3. Neutre | T84: 3. Neutre | U84: 3. Neutre | V84: 3. Neutre | W84: 3. Neutre | X84: 3. Neutre | Y84: 3. Neutre | Z84: 3. Neutre | AA84: 5. Très utile | AB84: 5. Très utile | AC84: 3. Neutre | AD84: 3. Neutre | AE84: 3. Neutre | AF84: 3. Neutre | AG84: 4. Utile | AH84: 3. Neutre | AI84: 7 | AJ84: 7. Très facile (Instinctif / Sans aide) | AK84: 6. D'accord (S'intègre facilement) | AL84: 3 | AM84: 7 | AN84: 7 | AO84: 4 | AP84: 7 | AQ84: 5. Très important | AR84: 5. Très important | AS84: 3. Moyennement important | AT84: 5. Très important | AU84: 7 | AV84: 7 | AW84: 2. Très limitée (Quelques vidéos ou articles consultés) | AX84: 7 | AY84: 7 | AZ84: 2. En désaccord (Je contrôle la quasi-totalité des éléments) | BA84: 7 | BB84: 4 | BC84: 7 | BD84: 1 | BE84: Non | BF84: 7 | BG84: 4. Neutre | BH84: 5 | BI84: 18-25 | BJ84: Femme | BK84: Junior | BL84: 2 - 3 ans | BM84: Audit Financier | BN84: Cabinet international
A85: 46078.922 | B85: 1. Jamais | BI85: 26-35 | BJ85: Homme | BK85: Junior | BL85: 4 - 5 ans | BM85: Expertise Comptable | BN85: Cabinet international
A86: 46079.309 | B86: 2. Très rarement (Moins d'une fois par mois) | C86: Outils grand public (ex: ChatGPT, Gemini ) | F86: Version grand public | G86: Version grand public | M86: Rédaction (rapports, synthèses, notes, mails) | N86: De manière VOLONTAIRE (vous avez choisi vous-même) | O86: 1. Pas du tout utile | P86: 2. Peu utile | Q86: 2. Peu utile | R86: 2. Peu utile | S86: 1. Pas du tout utile | T86: 1. Pas du tout utile | U86: 1. Pas du tout utile | V86: 2. Peu utile | W86: 2. Peu utile | X86: 2. Peu utile | Y86: 2. Peu utile | Z86: 2. Peu utile | AA86: 1. Pas du tout utile | AB86: 2. Peu utile | AC86: 1. Pas du tout utile | AD86: 1. Pas du tout utile | AE86: 1. Pas du tout utile | AF86: 2. Peu utile | AG86: 2. Peu utile | AH86: 1. Pas du tout utile | AI86: 1 | AJ86: 3. Plutôt difficile (Peu intuitif) | AK86: 3. Plutôt en désaccord (Demande un effort conscient) | AL86: 5 | AM86: 4 | AN86: 4 | AO86: 4 | AP86: 5 | AQ86: 2. Peu important | AR86: 1. Pas du tout important | AS86: 1. Pas du tout important | AT86: 2. Peu important | AU86: 4 | AV86: 4 | AW86: 4. Moyenne (Environ une journée de formation cumulée) | AX86: 4 | AY86: 5 | AZ86: 3. Plutôt en désaccord (Je procède à une revue importante) | BA86: 4 | BB86: 5 | BC86: 4 | BD86: 5 | BE86: Non | BF86: 4 | BG86: 4. Neutre | BH86: 4 | BI86: 26-35 | BJ86: Femme | BK86: Junior | BL86: 2 - 3 ans | BM86: Comptable | BN86: Cabinet régional

Sheet DONNEES_SOURCE
A1: Horodateur | B1: Q1. À quelle fréquence utilisez-vous l'IA générative dans le cadre de votre travail en audit ? | C1: Q2. Quel type d'IAG utilisez-vous principalement ? | D1: Q3. Quelles IAG utilisez vous dans le cadre de vos missions d'audit ? [Mistral] | E1: Q3. Quelles IAG utilisez vous dans le cadre de vos missions d'audit ? [Copilot] | F1: Q3. Quelles IAG utilisez vous dans le cadre de vos missions d'audit ? [ChatGPT] | G1: Q3. Quelles IAG utilisez vous dans le cadre de vos missions d'audit ? [Gemini] | H1: Q3. Quelles IAG utilisez vous dans le cadre de vos missions d'audit ? [Perplexity] | I1: Q3. Quelles IAG utilisez vous dans le cadre de vos missions d'audit ? [Grok] | J1: Q3. Quelles IAG utilisez vous dans le cadre de vos missions d'audit ? [Claude] | K1: Q3. Quelles IAG utilisez vous dans le cadre de vos missions d'audit ? [Outils IAG spécifiques cabinet] | L1: Q3. Quelles IAG utilisez vous dans le cadre de vos missions d'audit ? [Autres] | M1: Q4. Parmi ces tâches, cochez celles que vous avez déjà effectuées à l’aide de l’IA générative. | N1: Q5. Vous utilisez l'IA générative... | O1: Q6. Dans quelle mesure jugez-vous utile l’IA générative, pour améliorer la productivité, pour les activités suivantes ? [Extraction données (financières, juridiques, ...)] | P1: Q6. Dans quelle mesure jugez-vous utile l’IA générative, pour améliorer la productivité, pour les activités suivantes ? [Résumé données (financières, juridiques, ...)] | Q1: Q6. Dans quelle mesure jugez-vous utile l’IA générative, pour améliorer la productivité, pour les activités suivantes ? [Rédaction (rapports, synthèses, notes, mails)] | R1: Q6. Dans quelle mesure jugez-vous utile l’IA générative, pour améliorer la productivité, pour les activités suivantes ? [Rapprochement/Comparaison de documents] | S1: Q6. Dans quelle mesure jugez-vous utile l’IA générative, pour améliorer la productivité, pour les activités suivantes ? [Développement (scripts SQL, VBA)] | T1: Q6. Dans quelle mesure jugez-vous utile l’IA générative, pour améliorer la productivité, pour les activités suivantes ? [Détection de fraude] | U1: Q6. Dans quelle mesure jugez-vous utile l’IA générative, pour améliorer la productivité, pour les activités suivantes ? [Calcul du seuil de signification] | V1: Q6. Dans quelle mesure jugez-vous utile l’IA générative, pour améliorer la productivité, pour les activités suivantes ? [Revue d'estimations (provisions)] | W1: Q6. Dans quelle mesure jugez-vous utile l’IA générative, pour améliorer la productivité, pour les activités suivantes ? [Aide à la décision] | X1: Q6. Dans quelle mesure jugez-vous utile l’IA générative, pour améliorer la productivité, pour les activités suivantes ? [Préparation de données (format, structuration, harmonisation des valeurs)] | Y1: Q7. Dans quelle mesure jugez-vous utile l’IA générative, pour améliorer la qualité, pour les activités suivantes ? [Extraction données (financières, juridiques, ...)] | Z1: Q7. Dans quelle mesure jugez-vous utile l’IA générative, pour améliorer la qualité, pour les activités suivantes ? [Résumé données (financières, juridiques, ...)] | AA1: Q7. Dans quelle mesure jugez-vous utile l’IA générative, pour améliorer la qualité, pour les activités suivantes ? [Rédaction (rapports, synthèses, notes, mails)] | AB1: Q7. Dans quelle mesure jugez-vous utile l’IA générative, pour améliorer la qualité, pour les activités suivantes ? [Rapprochement/Comparaison de documents] | AC1: Q7. Dans quelle mesure jugez-vous utile l’IA générative, pour améliorer la qualité, pour les activités suivantes ? [Développement (scripts SQL, VBA)] | AD1: Q7. Dans quelle mesure jugez-vous utile l’IA générative, pour améliorer la qualité, pour les activités suivantes ? [Détection de fraude] | AE1: Q7. Dans quelle mesure jugez-vous utile l’IA générative, pour améliorer la qualité, pour les activités suivantes ? [Calcul du seuil de signification] | AF1: Q7. Dans quelle mesure jugez-vous utile l’IA générative, pour améliorer la qualité, pour les activités suivantes ? [Revue d'estimations (provisions)] | AG1: Q7. Dans quelle mesure jugez-vous utile l’IA générative, pour améliorer la qualité, pour les activités suivantes ? [Aide à la décision] | AH1: Q7. Dans quelle mesure jugez-vous utile l’IA générative, pour améliorer la qualité, pour les activités suivantes ? [Préparation de données (format, structuration, harmonisation des valeurs)] | AI1: Q8. "L'utilisation de l'IA générative me fait gagner du temps" | AJ1: Q9. Comment jugez-vous la prise en main des outils d'IA générative ? | AK1: Q10. "L'intégration de l'IA générative dans mon flux de travail quotidien se fait naturellement." | AL1: Q11. "Apprendre à utiliser l'IA générative efficacement requiert une formation" | AM1: Q12. L'IA générative peut produire des informations inexactes ou trompeuses dans le contexte de l'audit. | AN1: Q13. Partager des données avec l'IA générative présente des risques pour la confidentialité. | AO1: Q14. La nature opaque des modèles d'IA générative (« boîte noire ») rend difficile de comprendre et de justifier comment les résultats ont été produits en audit. | AP1: Q15. Je m'inquiète d'être tenu pour responsable si l'IAG fait une erreur dans mon travail. | AQ1: Q16 . Quel est le niveau d'importance de ce risque pour votre travail? [Hallucinations : Production d'informations fausses mais crédibles.] | AR1: Q16 . Quel est le niveau d'importance de ce risque pour votre travail? [Confidentialité : Risque de fuite ou d'usage illicite de données clients.] | AS1: Q16 . Quel est le niveau d'importance de ce risque pour votre travail? [Boîte noire : Opacité des algorithmes et difficulté à justifier un résultat.] | AT1: Q16 . Quel est le niveau d'importance de ce risque pour votre travail? [Responsabilité : Risque d'assumer seul les erreurs commises par l'IA.] | AU1: Q17. Ces risques m'empêchent d'augmenter mon usage de l'IAG | AV1: Q18. Si les risques étaient éliminés, j'utiliserais davantage l'IAG | AW1: Q19. Votre niveau global de formation (interne ou auto-apprentissage) ? | AX1: Q20. "Je me sens capable d'orienter les réponses de l'IAG pour limiter les risques d'imprécisions ou d'erreurs." | AY1: Q21. "Je me sens capable d'identifier les erreurs générées par l'IAG." | AZ1: Q22. Lorsque l’IAG vous propose un résultat, il vous arrive de vous y fier sans vérifier en détail par vous‑même. | BA1: Q23. À quelle fréquence vérifiez vous la source d'origine face à une réponse de l'IAG ? | BB1: Q24. Estimez-vous que votre jugement professionnel en audit reste fort malgré l'utilisation régulière de l'IAG? | BC1: Q25. "Il m'arrive de remettre en question mon jugement professionnel quand l'IAG me propose une conclusion différente de la mienne" | BD1: Q26. "En pratique, il m'arrive de conclure avant d'avoir réuni toutes les preuves que je jugerais idéalement nécessaires" | BE1: Q27. Prévoyez vous d'augmenter votre usage de l'IAG dans les 6 prochains mois ? | BF1: Q28. Probabilité d'augmenter votre usage de l'IAG si vous receviez une formation à l'avenir ? | BG1: Q29. Pour garantir la précision statistique des résultats, merci de sélectionner la réponse 'Neutre' ici. | BH1: Q30. Quelle est votre perception sur l'équilibre bénéfices-risques de l'IAG en audit ? | BI1: Q31. Tranche d'âge | BJ1: Q32. Genre | BK1: Q33. Votre niveau hiérarchique | BL1: Q34. Votre nombre d'années d'expérience | BM1: Q35. Votre cœur de métier | BN1: Q36. Taille de votre cabinet | BO1: Avant de terminer, souhaitez-vous partager votre opinion ou vos impressions sur l’IA générative ? (facultatif) | BP1: Q8_norm | BQ1: Q11_inv | BR1: Q22_inv | BS1: Q25_inv | BT1: Q26_inv | BU1: SUP | BV1: SFU | BW1: SRP | BX1: SMF | BY1: SS | BZ1: Q33_groupe | CA1: INCLUS_ANALYSE | CB1: Q1. À quelle fréquence utilisez-vous l'IA générative dans le cadre de votre travail en audit ? (num)
A2: {=_xlfn._xlws.FILTER( Form_Responses[], ('DONNEES BRUTES non filtrées'!BG2:BG86="4. Neutre") * ( ISNUMBER(SEARCH("audit",'DONNEES BRUTES non filtrées'!BM2:BM86)) + ISNUMBER(SEARCH("commissariat aux comptes",'DONNEES BRUTES non filtrées'!BM2:BM86)) + ISNUMBER(SEARCH("cac",'DONNEES BRUTES non filtrées'!BM2:BM86)) ) )} -> 46035.409 | B2: 3. Rarement (1 à 3 fois par mois) | C2: Outils grand public (ex: ChatGPT, Gemini ) | D2: 0 | E2: Version grand public | F2: Version grand public | G2: Version grand public | H2: 0 | I2: 0 | J2: Version entreprise | K2: 0 | L2: 0 | M2: Reformulation ou traduction de documents | N2: De manière VOLONTAIRE (vous avez choisi vous-même) | O2: 1. Pas du tout utile | P2: 2. Peu utile | Q2: 2. Peu utile | R2: 1. Pas du tout utile | S2: 2. Peu utile | T2: 1. Pas du tout utile | U2: 1. Pas du tout utile | V2: 1. Pas du tout utile | W2: 2. Peu utile | X2: 2. Peu utile | Y2: 1. Pas du tout utile | Z2: 1. Pas du tout utile | AA2: 2. Peu utile | AB2: 1. Pas du tout utile | AC2: 1. Pas du tout utile | AD2: 1. Pas du tout utile | AE2: 1. Pas du tout utile | AF2: 2. Peu utile | AG2: 2. Peu utile | AH2: 1. Pas du tout utile | AI2: 2 | AJ2: 5. Plutôt facile (Assez intuitif) | AK2: 5. Plutôt d'accord (S'intègre assez bien) | AL2: 2 | AM2: 7 | AN2: 7 | AO2: 4 | AP2: 7 | AQ2: 5. Très important | AR2: 5. Très important | AS2: 4. Important | AT2: 5. Très important | AU2: 4 | AV2: 5 | AW2: 4. Moyenne (Environ une journée de formation cumulée) | AX2: 7 | AY2: 7 | AZ2: 2. En désaccord (Je contrôle la quasi-totalité des éléments) | BA2: 6 | BB2: 7 | BC2: 1 | BD2: 1 | BE2: Je compte réduire l’utilisation de l’IA | BF2: 1 | BG2: 4. Neutre | BH2: 1 | BI2: 26-35 | BJ2: Femme | BK2: Senior | BL2: 2 - 3 ans | BM2: Audit Financier | BN2: Cabinet international | BO2: L’IA est une bonne tentative mais le cerveau humain reste meilleur, dans un métier d’audit financier qui est très sensible on peut utiliser l’IA pour nous informer sur des lois, de la comptabilité, des méthodes de calculs etc mais jamais pour émettre un rapport d’audit, le comissaire aux compte est un professionnel dans son domaine qui a fait plusieurs années d’études et d’expérience impossible qu’un rebot soit plus performant que lui. | BP2: =IF(ISNUMBER($AI$2),ROUND((((($AI$2-1)*(4/6))+1)),4),"") -> 1.6667 | BQ2: =IF(ISNUMBER($AL$2),8-$AL$2,"") -> 6 | BR2: =IFERROR(8-VALUE(LEFT($AZ$2,1)),"") -> 6 | BS2: =IF(ISNUMBER($BC$2),8-$BC$2,"") -> 7 | BT2: =IF(ISNUMBER($BD$2),8-$BD$2,"") -> 7 | BU2: =IFERROR(ROUND(AVERAGE(VALUE(LEFT($O$2,1)),VALUE(LEFT($P$2,1)),VALUE(LEFT($Q$2,1)),VALUE(LEFT($R$2,1)),VALUE(LEFT($S$2,1)),VALUE(LEFT($T$2,1)),VALUE(LEFT($U$2,1)),VALUE(LEFT($V$2,1)),VALUE(LEFT($W$2,1)),VALUE(LEFT($X$2,1)),VALUE(LEFT($Y$2,1)),VALUE(LEFT($Z$2,1)),VALUE(LEFT($AA$2,1)),VALUE(LEFT($AB$2,1)),VALUE(LEFT($AC$2,1)),VALUE(LEFT($AD$2,1)),VALUE(LEFT($AE$2,1)),VALUE(LEFT($AF$2,1)),VALUE(LEFT($AG$2,1)),VALUE(LEFT($AH$2,1)),$BP$2),4),"") -> 1.4127 | BV2: =IFERROR(ROUND(AVERAGE(VALUE(LEFT($AJ$2,1)),VALUE(LEFT($AK$2,1)),$BQ$2),4),"") -> 5.3333 | BW2: =IFERROR(ROUND(AVERAGE($AM$2,$AN$2,$AO$2,$AP$2),4),"") -> 6.25 | BX2: =IFERROR(ROUND(AVERAGE(VALUE(LEFT($AW$2,1)),$AX$2,$AY$2),4),"") -> 6 | BY2: =IFERROR(ROUND(AVERAGE($BR$2,$BA$2,$BB$2,$BS$2,$BT$2),4),"") -> 6.6 | BZ2: =IF(OR($BK$2="Junior",$BK$2="Stagiaire",$BK$2="Alternant"),"Junior",IF(OR($BK$2="Superviseur",$BK$2="Superviseur ",$BK$2="Senior",$BK$2="Senior Manager",$BK$2="Manager"),"Senior-Manager",IF(OR($BK$2="Associe",$BK$2="Associé"),"Associe","Autre"))) -> Senior-Manager | CA2: =AND(NOT(ISNUMBER(SEARCH("Jamais",$B$2))),$BG$2="4. Neutre") -> TRUE | CB2: =VALUE(LEFT(B2,1)) -> 3
A3: 46036.706 | B3: 5. Régulièrement (Plusieurs fois par semaine) | C3: Outils fournis/agréés par le cabinet (ex: Copilot sécurisé) | D3: 0 | E3: Version grand public | F3: 0 | G3: 0 | H3: 0 | I3: 0 | J3: 0 | K3: 0 | L3: 0 | M3: Recherche d'informations ou de points techniques, Rédaction (rapports, synthèses, notes, mails), Reformulation ou traduction de documents | N3: De manière VOLONTAIRE (vous avez choisi vous-même) | O3: 1. Pas du tout utile | P3: 2. Peu utile | Q3: 5. Très utile | R3: 2. Peu utile | S3: 2. Peu utile | T3: 1. Pas du tout utile | U3: 1. Pas du tout utile | V3: 1. Pas du tout utile | W3: 1. Pas du tout utile | X3: 3. Neutre | Y3: 1. Pas du tout utile | Z3: 2. Peu utile | AA3: 5. Très utile | AB3: 2. Peu utile | AC3: 2. Peu utile | AD3: 1. Pas du tout utile | AE3: 1. Pas du tout utile | AF3: 1. Pas du tout utile | AG3: 1. Pas du tout utile | AH3: 3. Neutre | AI3: 6 | AJ3: 5. Plutôt facile (Assez intuitif) | AK3: 6. D'accord (S'intègre facilement) | AL3: 4 | AM3: 7 | AN3: 4 | AO3: 7 | AP3: 7 | AQ3: 5. Très important | AR3: 4. Important | AS3: 4. Important | AT3: 5. Très important | AU3: 4 | AV3: 4 | AW3: 3. Faible (Moins de 5 heures de formation au total) | AX3: 5 | AY3: 5 | AZ3: 3. Plutôt en désaccord (Je procède à une revue importante) | BA3: 5 | BB3: 6 | BC3: 5 | BD3: 3 | BE3: Oui | BF3: 5 | BG3: 4. Neutre | BH3: 6 | BI3: 18-25 | BJ3: Homme | BK3: Junior | BL3: Moins de 2 ans | BM3: Audit Financier | BN3: Cabinet international | BO3: 0 | BP3: =IF(ISNUMBER($AI$3),ROUND((((($AI$3-1)*(4/6))+1)),4),"") -> 4.3333 | BQ3: =IF(ISNUMBER($AL$3),8-$AL$3,"") -> 4 | BR3: =IFERROR(8-VALUE(LEFT($AZ$3,1)),"") -> 5 | BS3: =IF(ISNUMBER($BC$3),8-$BC$3,"") -> 3 | BT3: =IF(ISNUMBER($BD$3),8-$BD$3,"") -> 5 | BU3: =IFERROR(ROUND(AVERAGE(VALUE(LEFT($O$3,1)),VALUE(LEFT($P$3,1)),VALUE(LEFT($Q$3,1)),VALUE(LEFT($R$3,1)),VALUE(LEFT($S$3,1)),VALUE(LEFT($T$3,1)),VALUE(LEFT($U$3,1)),VALUE(LEFT($V$3,1)),VALUE(LEFT($W$3,1)),VALUE(LEFT($X$3,1)),VALUE(LEFT($Y$3,1)),VALUE(LEFT($Z$3,1)),VALUE(LEFT($AA$3,1)),VALUE(LEFT($AB$3,1)),VALUE(LEFT($AC$3,1)),VALUE(LEFT($AD$3,1)),VALUE(LEFT($AE$3,1)),VALUE(LEFT($AF$3,1)),VALUE(LEFT($AG$3,1)),VALUE(LEFT($AH$3,1)),$BP$3),4),"") -> 2.0159 | BV3: =IFERROR(ROUND(AVERAGE(VALUE(LEFT($AJ$3,1)),VALUE(LEFT($AK$3,1)),$BQ$3),4),"") -> 5 | BW3: =IFERROR(ROUND(AVERAGE($AM$3,$AN$3,$AO$3,$AP$3),4),"") -> 6.25 | BX3: =IFERROR(ROUND(AVERAGE(VALUE(LEFT($AW$3,1)),$AX$3,$AY$3),4),"") -> 4.3333 | BY3: =IFERROR(ROUND(AVERAGE($BR$3,$BA$3,$BB$3,$BS$3,$BT$3),4),"") -> 4.8 | BZ3: =IF(OR($BK$3="Junior",$BK$3="Stagiaire",$BK$3="Alternant"),"Junior",IF(OR($BK$3="Superviseur",$BK$3="Superviseur ",$BK$3="Senior",$BK$3="Senior Manager",$BK$3="Manager"),"Senior-Manager",IF(OR($BK$3="Associe",$BK$3="Associé"),"Associe","Autre"))) -> Junior | CA3: =AND(NOT(ISNUMBER(SEARCH("Jamais",$B$3))),$BG$3="4. Neutre") -> TRUE | CB3: =VALUE(LEFT(B3,1)) -> 5
A4: 46036.707 | B4: 5. Régulièrement (Plusieurs fois par semaine) | C4: Outils fournis/agréés par le cabinet (ex: Copilot sécurisé) | D4: 0 | E4: Version entreprise | F4: Version grand public | G4: 0 | H4: 0 | I4: 0 | J4: 0 | K4: Version entreprise | L4: 0 | M4: Rapprochement/Comparaison de documents, Correction et mise en cohérence de documents, Rédaction (rapports, synthèses, notes, mails), Préparation de données (format, structuration, harmonisation des valeurs) | N4: De manière VOLONTAIRE (vous avez choisi vous-même) | O4: 4. Utile | P4: 4. Utile | Q4: 5. Très utile | R4: 2. Peu utile | S4: 2. Peu utile | T4: 3. Neutre | U4: 3. Neutre | V4: 3. Neutre | W4: 3. Neutre | X4: 4. Utile | Y4: 4. Utile | Z4: 4. Utile | AA4: 4. Utile | AB4: 4. Utile | AC4: 2. Peu utile | AD4: 2. Peu utile | AE4: 2. Peu utile | AF4: 2. Peu utile | AG4: 4. Utile | AH4: 4. Utile | AI4: 7 | AJ4: 5. Plutôt facile (Assez intuitif) | AK4: 1. Tout à fait en désaccord (Friction totale / Inutilisable) | AL4: 5 | AM4: 1 | AN4: 4 | AO4: 4 | AP4: 6 | AQ4: 4. Important | AR4: 4. Important | AS4: 4. Important | AT4: 4. Important | AU4: 5 | AV4: 5 | AW4: 5. Solide (Plusieurs jours de formation ou modules suivis) | AX4: 6 | AY4: 5 | AZ4: 4. Neutre (Le niveau de vérification dépend de la complexité) | BA4: 5 | BB4: 4 | BC4: 6 | BD4: 4 | BE4: Oui | BF4: 7 | BG4: 4. Neutre | BH4: 3 | BI4: 18-25 | BJ4: Femme | BK4: Junior | BL4: Moins de 2 ans | BM4: Audit Financier | BN4: Cabinet international | BO4: 0 | BP4: =IF(ISNUMBER($AI$4),ROUND((((($AI$4-1)*(4/6))+1)),4),"") -> 5 | BQ4: =IF(ISNUMBER($AL$4),8-$AL$4,"") -> 3 | BR4: =IFERROR(8-VALUE(LEFT($AZ$4,1)),"") -> 4 | BS4: =IF(ISNUMBER($BC$4),8-$BC$4,"") -> 2 | BT4: =IF(ISNUMBER($BD$4),8-$BD$4,"") -> 4 | BU4: =IFERROR(ROUND(AVERAGE(VALUE(LEFT($O$4,1)),VALUE(LEFT($P$4,1)),VALUE(LEFT($Q$4,1)),VALUE(LEFT($R$4,1)),VALUE(LEFT($S$4,1)),VALUE(LEFT($T$4,1)),VALUE(LEFT($U$4,1)),VALUE(LEFT($V$4,1)),VALUE(LEFT($W$4,1)),VALUE(LEFT($X$4,1)),VALUE(LEFT($Y$4,1)),VALUE(LEFT($Z$4,1)),VALUE(LEFT($AA$4,1)),VALUE(LEFT($AB$4,1)),VALUE(LEFT($AC$4,1)),VALUE(LEFT($AD$4,1)),VALUE(LEFT($AE$4,1)),VALUE(LEFT($AF$4,1)),VALUE(LEFT($AG$4,1)),VALUE(LEFT($AH$4,1)),$BP$4),4),"") -> 3.3333 | BV4: =IFERROR(ROUND(AVERAGE(VALUE(LEFT($AJ$4,1)),VALUE(LEFT($AK$4,1)),$BQ$4),4),"") -> 3 | BW4: =IFERROR(ROUND(AVERAGE($AM$4,$AN$4,$AO$4,$AP$4),4),"") -> 3.75 | BX4: =IFERROR(ROUND(AVERAGE(VALUE(LEFT($AW$4,1)),$AX$4,$AY$4),4),"") -> 5.3333 | BY4: =IFERROR(ROUND(AVERAGE($BR$4,$BA$4,$BB$4,$BS$4,$BT$4),4),"") -> 3.8 | BZ4: =IF(OR($BK$4="Junior",$BK$4="Stagiaire",$BK$4="Alternant"),"Junior",IF(OR($BK$4="Superviseur",$BK$4="Superviseur ",$BK$4="Senior",$BK$4="Senior Manager",$BK$4="Manager"),"Senior-Manager",IF(OR($BK$4="Associe",$BK$4="Associé"),"Associe","Autre"))) -> Junior | CA4: =AND(NOT(ISNUMBER(SEARCH("Jamais",$B$4))),$BG$4="4. Neutre") -> TRUE | CB4: =VALUE(LEFT(B4,1)) -> 5
A5: 46036.712 | B5: 7. Très fréquemment (Plusieurs fois par jour) | C5: Usage mix des deux | D5: 0 | E5: Version entreprise | F5: Version grand public | G5: Version grand public | H5: 0 | I5: 0 | J5: 0 | K5: Version entreprise | L5: 0 | M5: Automatisation et création de scripts (SQL, VBA), Recherche d'informations ou de points techniques, Analyse de données et génération d'insights, Rédaction (rapports, synthèses, notes, mails), Évaluation du contrôle interne, Préparation de données (format, structuration, harmonisation des valeurs) | N5: De manière VOLONTAIRE (vous avez choisi vous-même) | O5: 5. Très utile | P5: 5. Très utile | Q5: 5. Très utile | R5: 3. Neutre | S5: 5. Très utile | T5: 3. Neutre | U5: 3. Neutre | V5: 3. Neutre | W5: 4. Utile | X5: 5. Très utile | Y5: 5. Très utile | Z5: 4. Utile | AA5: 5. Très utile | AB5: 4. Utile | AC5: 5. Très utile | AD5: 3. Neutre | AE5: 3. Neutre | AF5: 3. Neutre | AG5: 3. Neutre | AH5: 5. Très utile | AI5: 7 | AJ5: 6. Facile (Maîtrise rapide) | AK5: 6. D'accord (S'intègre facilement) | AL5: 4 | AM5: 4 | AN5: 7 | AO5: 5 | AP5: 6 | AQ5: 3. Moyennement important | AR5: 5. Très important | AS5: 4. Important | AT5: 4. Important | AU5: 4 | AV5: 6 | AW5: 3. Faible (Moins de 5 heures de formation au total) | AX5: 5 | AY5: 4 | AZ5: 4. Neutre (Le niveau de vérification dépend de la complexité) | BA5: 4 | BB5: 6 | BC5: 6 | BD5: 4 | BE5: Oui | BF5: 6 | BG5: 4. Neutre | BH5: 5 | BI5: 18-25 | BJ5: Homme | BK5: Junior | BL5: Moins de 2 ans | BM5: Audit IT | BN5: Cabinet international | BO5: 0 | BP5: =IF(ISNUMBER($AI$5),ROUND((((($AI$5-1)*(4/6))+1)),4),"") -> 5 | BQ5: =IF(ISNUMBER($AL$5),8-$AL$5,"") -> 4 | BR5: =IFERROR(8-VALUE(LEFT($AZ$5,1)),"") -> 4 | BS5: =IF(ISNUMBER($BC$5),8-$BC$5,"") -> 2 | BT5: =IF(ISNUMBER($BD$5),8-$BD$5,"") -> 4 | BU5: =IFERROR(ROUND(AVERAGE(VALUE(LEFT($O$5,1)),VALUE(LEFT($P$5,1)),VALUE(LEFT($Q$5,1)),VALUE(LEFT($R$5,1)),VALUE(LEFT($S$5,1)),VALUE(LEFT($T$5,1)),VALUE(LEFT($U$5,1)),VALUE(LEFT($V$5,1)),VALUE(LEFT($W$5,1)),VALUE(LEFT($X$5,1)),VALUE(LEFT($Y$5,1)),VALUE(LEFT($Z$5,1)),VALUE(LEFT($AA$5,1)),VALUE(LEFT($AB$5,1)),VALUE(LEFT($AC$5,1)),VALUE(LEFT($AD$5,1)),VALUE(LEFT($AE$5,1)),VALUE(LEFT($AF$5,1)),VALUE(LEFT($AG$5,1)),VALUE(LEFT($AH$5,1)),$BP$5),4),"") -> 4.0952 | BV5: =IFERROR(ROUND(AVERAGE(VALUE(LEFT($AJ$5,1)),VALUE(LEFT($AK$5,1)),$BQ$5),4),"") -> 5.3333 | BW5: =IFERROR(ROUND(AVERAGE($AM$5,$AN$5,$AO$5,$AP$5),4),"") -> 5.5 | BX5: =IFERROR(ROUND(AVERAGE(VALUE(LEFT($AW$5,1)),$AX$5,$AY$5),4),"") -> 4 | BY5: =IFERROR(ROUND(AVERAGE($BR$5,$BA$5,$BB$5,$BS$5,$BT$5),4),"") -> 4 | BZ5: =IF(OR($BK$5="Junior",$BK$5="Stagiaire",$BK$5="Alternant"),"Junior",IF(OR($BK$5="Superviseur",$BK$5="Superviseur ",$BK$5="Senior",$BK$5="Senior Manager",$BK$5="Manager"),"Senior-Manager",IF(OR($BK$5="Associe",$BK$5="Associé"),"Associe","Autre"))) -> Junior | CA5: =AND(NOT(ISNUMBER(SEARCH("Jamais",$B$5))),$BG$5="4. Neutre") -> TRUE | CB5: =VALUE(LEFT(B5,1)) -> 7
A6: 46036.713 | B6: 5. Régulièrement (Plusieurs fois par semaine) | C6: Outils fournis/agréés par le cabinet (ex: Copilot sécurisé) | D6: 0 | E6: Version entreprise | F6: 0 | G6: 0 | H6: 0 | I6: 0 | J6: 0 | K6: 0 | L6: 0 | M6: Reformulation ou traduction de documents, Préparation de données (format, structuration, harmonisation des valeurs), Recherche d'informations ou de points techniques | N6: De manière VOLONTAIRE (vous avez choisi vous-même) | O6: 5. Très utile | P6: 5. Très utile | Q6: 4. Utile | R6: 5. Très utile | S6: 5. Très utile | T6: 4. Utile | U6: 1. Pas du tout utile | V6: 4. Utile | W6: 4. Utile | X6: 5. Très utile | Y6: 5. Très utile | Z6: 5. Très utile | AA6: 5. Très utile | AB6: 5. Très utile | AC6: 5. Très utile | AD6: 5. Très utile | AE6: 5. Très utile | AF6: 5. Très utile | AG6: 5. Très utile | AH6: 5. Très utile | AI6: 6 | AJ6: 6. Facile (Maîtrise rapide) | AK6: 6. D'accord (S'intègre facilement) | AL6: 3 | AM6: 6 | AN6: 6 | AO6: 6 | AP6: 4 | AQ6: 5. Très important | AR6: 5. Très important | AS6: 5. Très important | AT6: 5. Très important | AU6: 6 | AV6: 7 | AW6: 1. Aucune | AX6: 5 | AY6: 6 | AZ6: 5. Plutôt d'accord (Je vérifie uniquement les points clés) | BA6: 4 | BB6: 6 | BC6: 5 | BD6: 2 | BE6: aucune idée | BF6: 4 | BG6: 4. Neutre | BH6: 5 | BI6: 18-25 | BJ6: Homme | BK6: Stagiaire | BL6: Moins de 2 ans | BM6: Audit Financier | BN6: Cabinet international | BO6: 0 | BP6: =IF(ISNUMBER($AI$6),ROUND((((($AI$6-1)*(4/6))+1)),4),"") -> 4.3333 | BQ6: =IF(ISNUMBER($AL$6),8-$AL$6,"") -> 5 | BR6: =IFERROR(8-VALUE(LEFT($AZ$6,1)),"") -> 3 | BS6: =IF(ISNUMBER($BC$6),8-$BC$6,"") -> 3 | BT6: =IF(ISNUMBER($BD$6),8-$BD$6,"") -> 6 | BU6: =IFERROR(ROUND(AVERAGE(VALUE(LEFT($O$6,1)),VALUE(LEFT($P$6,1)),VALUE(LEFT($Q$6,1)),VALUE(LEFT($R$6,1)),VALUE(LEFT($S$6,1)),VALUE(LEFT($T$6,1)),VALUE(LEFT($U$6,1)),VALUE(LEFT($V$6,1)),VALUE(LEFT($W$6,1)),VALUE(LEFT($X$6,1)),VALUE(LEFT($Y$6,1)),VALUE(LEFT($Z$6,1)),VALUE(LEFT($AA$6,1)),VALUE(LEFT($AB$6,1)),VALUE(LEFT($AC$6,1)),VALUE(LEFT($AD$6,1)),VALUE(LEFT($AE$6,1)),VALUE(LEFT($AF$6,1)),VALUE(LEFT($AG$6,1)),VALUE(LEFT($AH$6,1)),$BP$6),4),"") -> 4.5873 | BV6: =IFERROR(ROUND(AVERAGE(VALUE(LEFT($AJ$6,1)),VALUE(LEFT($AK$6,1)),$BQ$6),4),"") -> 5.6667 | BW6: =IFERROR(ROUND(AVERAGE($AM$6,$AN$6,$AO$6,$AP$6),4),"") -> 5.5 | BX6: =IFERROR(ROUND(AVERAGE(VALUE(LEFT($AW$6,1)),$AX$6,$AY$6),4),"") -> 4 | BY6: =IFERROR(ROUND(AVERAGE($BR$6,$BA$6,$BB$6,$BS$6,$BT$6),4),"") -> 4.4 | BZ6: =IF(OR($BK$6="Junior",$BK$6="Stagiaire",$BK$6="Alternant"),"Junior",IF(OR($BK$6="Superviseur",$BK$6="Superviseur ",$BK$6="Senior",$BK$6="Senior Manager",$BK$6="Manager"),"Senior-Manager",IF(OR($BK$6="Associe",$BK$6="Associé"),"Associe","Autre"))) -> Junior | CA6: =AND(NOT(ISNUMBER(SEARCH("Jamais",$B$6))),$BG$6="4. Neutre") -> TRUE | CB6: =VALUE(LEFT(B6,1)) -> 5
A7: 46036.716 | B7: 5. Régulièrement (Plusieurs fois par semaine) | C7: Outils fournis/agréés par le cabinet (ex: Copilot sécurisé) | D7: 0 | E7: Version entreprise | F7: 0 | G7: 0 | H7: 0 | I7: 0 | J7: 0 | K7: 0 | L7: 0 | M7: Reformulation ou traduction de documents, Rédaction (rapports, synthèses, notes, mails), Préparation de données (format, structuration, harmonisation des valeurs), Correction et mise en cohérence de documents | N7: De manière VOLONTAIRE (vous avez choisi vous-même) | O7: 3. Neutre | P7: 5. Très utile | Q7: 5. Très utile | R7: 3. Neutre | S7: 1. Pas du tout utile | T7: 1. Pas du tout utile | U7: 1. Pas du tout utile | V7: 1. Pas du tout utile | W7: 1. Pas du tout utile | X7: 4. Utile | Y7: 4. Utile | Z7: 5. Très utile | AA7: 5. Très utile | AB7: 3. Neutre | AC7: 1. Pas du tout utile | AD7: 1. Pas du tout utile | AE7: 1. Pas du tout utile | AF7: 1. Pas du tout utile | AG7: 1. Pas du tout utile | AH7: 1. Pas du tout utile | AI7: 5 | AJ7: 5. Plutôt facile (Assez intuitif) | AK7: 5. Plutôt d'accord (S'intègre assez bien) | AL7: 5 | AM7: 5 | AN7: 5 | AO7: 4 | AP7: 2 | AQ7: 5. Très important | AR7: 5. Très important | AS7: 5. Très important | AT7: 5. Très important | AU7: 4 | AV7: 5 | AW7: 4. Moyenne (Environ une journée de formation cumulée) | AX7: 6 | AY7: 6 | AZ7: 2. En désaccord (Je contrôle la quasi-totalité des éléments) | BA7: 6 | BB7: 6 | BC7: 5 | BD7: 2 | BE7: Non | BF7: 4 | BG7: 4. Neutre | BH7: 4 | BI7: 18-25 | BJ7: Femme | BK7: Junior | BL7: Moins de 2 ans | BM7: Audit Financier | BN7: Cabinet international | BO7: 0 | BP7: =IF(ISNUMBER($AI$7),ROUND((((($AI$7-1)*(4/6))+1)),4),"") -> 3.6667 | BQ7: =IF(ISNUMBER($AL$7),8-$AL$7,"") -> 3 | BR7: =IFERROR(8-VALUE(LEFT($AZ$7,1)),"") -> 6 | BS7: =IF(ISNUMBER($BC$7),8-$BC$7,"") -> 3 | BT7: =IF(ISNUMBER($BD$7),8-$BD$7,"") -> 6 | BU7: =IFERROR(ROUND(AVERAGE(VALUE(LEFT($O$7,1)),VALUE(LEFT($P$7,1)),VALUE(LEFT($Q$7,1)),VALUE(LEFT($R$7,1)),VALUE(LEFT($S$7,1)),VALUE(LEFT($T$7,1)),VALUE(LEFT($U$7,1)),VALUE(LEFT($V$7,1)),VALUE(LEFT($W$7,1)),VALUE(LEFT($X$7,1)),VALUE(LEFT($Y$7,1)),VALUE(LEFT($Z$7,1)),VALUE(LEFT($AA$7,1)),VALUE(LEFT($AB$7,1)),VALUE(LEFT($AC$7,1)),VALUE(LEFT($AD$7,1)),VALUE(LEFT($AE$7,1)),VALUE(LEFT($AF$7,1)),VALUE(LEFT($AG$7,1)),VALUE(LEFT($AH$7,1)),$BP$7),4),"") -> 2.4603 | BV7: =IFERROR(ROUND(AVERAGE(VALUE(LEFT($AJ$7,1)),VALUE(LEFT($AK$7,1)),$BQ$7),4),"") -> 4.3333 | BW7: =IFERROR(ROUND(AVERAGE($AM$7,$AN$7,$AO$7,$AP$7),4),"") -> 4 | BX7: =IFERROR(ROUND(AVERAGE(VALUE(LEFT($AW$7,1)),$AX$7,$AY$7),4),"") -> 5.3333 | BY7: =IFERROR(ROUND(AVERAGE($BR$7,$BA$7,$BB$7,$BS$7,$BT$7),4),"") -> 5.4 | BZ7: =IF(OR($BK$7="Junior",$BK$7="Stagiaire",$BK$7="Alternant"),"Junior",IF(OR($BK$7="Superviseur",$BK$7="Superviseur ",$BK$7="Senior",$BK$7="Senior Manager",$BK$7="Manager"),"Senior-Manager",IF(OR($BK$7="Associe",$BK$7="Associé"),"Associe","Autre"))) -> Junior | CA7: =AND(NOT(ISNUMBER(SEARCH("Jamais",$B$7))),$BG$7="4. Neutre") -> TRUE | CB7: =VALUE(LEFT(B7,1)) -> 5
A8: 46036.721 | B8: 3. Rarement (1 à 3 fois par mois) | C8: Outils fournis/agréés par le cabinet (ex: Copilot sécurisé) | D8: 0 | E8: Version entreprise | F8: 0 | G8: 0 | H8: 0 | I8: 0 | J8: 0 | K8: 0 | L8: 0 | M8: Formules Excel, aide pour l'utilisation des outils Microsoft | N8: De manière RECOMMANDÉE (cabinet encourage, mais facultatif) | O8: 3. Neutre | P8: 5. Très utile | Q8: 4. Utile | R8: 4. Utile | S8: 3. Neutre | T8: 1. Pas du tout utile | U8: 1. Pas du tout utile | V8: 1. Pas du tout utile | W8: 3. Neutre | X8: 4. Utile | Y8: 3. Neutre | Z8: 4. Utile | AA8: 4. Utile | AB8: 4. Utile | AC8: 3. Neutre | AD8: 1. Pas du tout utile | AE8: 1. Pas du tout utile | AF8: 1. Pas du tout utile | AG8: 3. Neutre | AH8: 4. Utile | AI8: 5 | AJ8: 6. Facile (Maîtrise rapide) | AK8: 3. Plutôt en désaccord (Demande un effort conscient) | AL8: 6 | AM8: 7 | AN8: 6 | AO8: 6 | AP8: 2 | AQ8: 5. Très important | AR8: 5. Très important | AS8: 4. Important | AT8: 3. Moyennement important | AU8: 6 | AV8: 7 | AW8: 4. Moyenne (Environ une journée de formation cumulée) | AX8: 4 | AY8: 4 | AZ8: 2. En désaccord (Je contrôle la quasi-totalité des éléments) | BA8: 7 | BB8: 5 | BC8: 5 | BD8: 2 | BE8: Oui | BF8: 6 | BG8: 4. Neutre | BH8: 4 | BI8: 26-35 | BJ8: Femme | BK8: Junior | BL8: Moins de 2 ans | BM8: Audit Financier | BN8: Cabinet international | BO8: 0 | BP8: =IF(ISNUMBER($AI$8),ROUND((((($AI$8-1)*(4/6))+1)),4),"") -> 3.6667 | BQ8: =IF(ISNUMBER($AL$8),8-$AL$8,"") -> 2 | BR8: =IFERROR(8-VALUE(LEFT($AZ$8,1)),"") -> 6 | BS8: =IF(ISNUMBER($BC$8),8-$BC$8,"") -> 3 | BT8: =IF(ISNUMBER($BD$8),8-$BD$8,"") -> 6 | BU8: =IFERROR(ROUND(AVERAGE(VALUE(LEFT($O$8,1)),VALUE(LEFT($P$8,1)),VALUE(LEFT($Q$8,1)),VALUE(LEFT($R$8,1)),VALUE(LEFT($S$8,1)),VALUE(LEFT($T$8,1)),VALUE(LEFT($U$8,1)),VALUE(LEFT($V$8,1)),VALUE(LEFT($W$8,1)),VALUE(LEFT($X$8,1)),VALUE(LEFT($Y$8,1)),VALUE(LEFT($Z$8,1)),VALUE(LEFT($AA$8,1)),VALUE(LEFT($AB$8,1)),VALUE(LEFT($AC$8,1)),VALUE(LEFT($AD$8,1)),VALUE(LEFT($AE$8,1)),VALUE(LEFT($AF$8,1)),VALUE(LEFT($AG$8,1)),VALUE(LEFT($AH$8,1)),$BP$8),4),"") -> 2.8889 | BV8: =IFERROR(ROUND(AVERAGE(VALUE(LEFT($AJ$8,1)),VALUE(LEFT($AK$8,1)),$BQ$8),4),"") -> 3.6667 | BW8: =IFERROR(ROUND(AVERAGE($AM$8,$AN$8,$AO$8,$AP$8),4),"") -> 5.25 | BX8: =IFERROR(ROUND(AVERAGE(VALUE(LEFT($AW$8,1)),$AX$8,$AY$8),4),"") -> 4 | BY8: =IFERROR(ROUND(AVERAGE($BR$8,$BA$8,$BB$8,$BS$8,$BT$8),4),"") -> 5.4 | BZ8: =IF(OR($BK$8="Junior",$BK$8="Stagiaire",$BK$8="Alternant"),"Junior",IF(OR($BK$8="Superviseur",$BK$8="Superviseur ",$BK$8="Senior",$BK$8="Senior Manager",$BK$8="Manager"),"Senior-Manager",IF(OR($BK$8="Associe",$BK$8="Associé"),"Associe","Autre"))) -> Junior | CA8: =AND(NOT(ISNUMBER(SEARCH("Jamais",$B$8))),$BG$8="4. Neutre") -> TRUE | CB8: =VALUE(LEFT(B8,1)) -> 3
A9: 46036.725 | B9: 3. Rarement (1 à 3 fois par mois) | C9: Outils fournis/agréés par le cabinet (ex: Copilot sécurisé) | D9: 0 | E9: Version entreprise | F9: 0 | G9: 0 | H9: 0 | I9: 0 | J9: 0 | K9: 0 | L9: 0 | M9: Reformulation ou traduction de documents, Recherche d'informations ou de points techniques | N9: De manière RECOMMANDÉE (cabinet encourage, mais facultatif) | O9: 4. Utile | P9: 4. Utile | Q9: 2. Peu utile | R9: 2. Peu utile | S9: 3. Neutre | T9: 1. Pas du tout utile | U9: 1. Pas du tout utile | V9: 1. Pas du tout utile | W9: 2. Peu utile | X9: 4. Utile | Y9: 4. Utile | Z9: 3. Neutre | AA9: 2. Peu utile | AB9: 2. Peu utile | AC9: 2. Peu utile | AD9: 2. Peu utile | AE9: 1. Pas du tout utile | AF9: 2. Peu utile | AG9: 2. Peu utile | AH9: 4. Utile | AI9: 4 | AJ9: 6. Facile (Maîtrise rapide) | AK9: 5. Plutôt d'accord (S'intègre assez bien) | AL9: 3 | AM9: 7 | AN9: 3 | AO9: 7 | AP9: 7 | AQ9: 5. Très important | AR9: 5. Très important | AS9: 4. Important | AT9: 3. Moyennement important | AU9: 6 | AV9: 5 | AW9: 3. Faible (Moins de 5 heures de formation au total) | AX9: 5 | AY9: 5 | AZ9: 4. Neutre (Le niveau de vérification dépend de la complexité) | BA9: 5 | BB9: 4 | BC9: 5 | BD9: 2 | BE9: Non | BF9: 3 | BG9: 4. Neutre | BH9: 5 | BI9: 18-25 | BJ9: Homme | BK9: Alternant | BL9: Moins de 2 ans | BM9: Audit Financier | BN9: Cabinet international | BO9: 0 | BP9: =IF(ISNUMBER($AI$9),ROUND((((($AI$9-1)*(4/6))+1)),4),"") -> 3 | BQ9: =IF(ISNUMBER($AL$9),8-$AL$9,"") -> 5 | BR9: =IFERROR(8-VALUE(LEFT($AZ$9,1)),"") -> 4 | BS9: =IF(ISNUMBER($BC$9),8-$BC$9,"") -> 3 | BT9: =IF(ISNUMBER($BD$9),8-$BD$9,"") -> 6 | BU9: =IFERROR(ROUND(AVERAGE(VALUE(LEFT($O$9,1)),VALUE(LEFT($P$9,1)),VALUE(LEFT($Q$9,1)),VALUE(LEFT($R$9,1)),VALUE(LEFT($S$9,1)),VALUE(LEFT($T$9,1)),VALUE(LEFT($U$9,1)),VALUE(LEFT($V$9,1)),VALUE(LEFT($W$9,1)),VALUE(LEFT($X$9,1)),VALUE(LEFT($Y$9,1)),VALUE(LEFT($Z$9,1)),VALUE(LEFT($AA$9,1)),VALUE(LEFT($AB$9,1)),VALUE(LEFT($AC$9,1)),VALUE(LEFT($AD$9,1)),VALUE(LEFT($AE$9,1)),VALUE(LEFT($AF$9,1)),VALUE(LEFT($AG$9,1)),VALUE(LEFT($AH$9,1)),$BP$9),4),"") -> 2.4286 | BV9: =IFERROR(ROUND(AVERAGE(VALUE(LEFT($AJ$9,1)),VALUE(LEFT($AK$9,1)),$BQ$9),4),"") -> 5.3333 | BW9: =IFERROR(ROUND(AVERAGE($AM$9,$AN$9,$AO$9,$AP$9),4),"") -> 6 | BX9: =IFERROR(ROUND(AVERAGE(VALUE(LEFT($AW$9,1)),$AX$9,$AY$9),4),"") -> 4.3333 | BY9: =IFERROR(ROUND(AVERAGE($BR$9,$BA$9,$BB$9,$BS$9,$BT$9),4),"") -> 4.4 | BZ9: =IF(OR($BK$9="Junior",$BK$9="Stagiaire",$BK$9="Alternant"),"Junior",IF(OR($BK$9="Superviseur",$BK$9="Superviseur ",$BK$9="Senior",$BK$9="Senior Manager",$BK$9="Manager"),"Senior-Manager",IF(OR($BK$9="Associe",$BK$9="Associé"),"Associe","Autre"))) -> Junior | CA9: =AND(NOT(ISNUMBER(SEARCH("Jamais",$B$9))),$BG$9="4. Neutre") -> TRUE | CB9: =VALUE(LEFT(B9,1)) -> 3
A10: 46036.867 | B10: 4. Parfois (Environ une fois par semaine) | C10: Usage mix des deux | D10: 0 | E10: Version entreprise | F10: Version grand public | G10: 0 | H10: 0 | I10: 0 | J10: 0 | K10: 0 | L10: 0 | M10: Revue d'estimations comptables (provisions, dépréciations), Reformulation ou traduction de documents, Rapprochement/Comparaison de documents, Aide à la décision, Rédaction (rapports, synthèses, notes, mails) | N10: De manière VOLONTAIRE (vous avez choisi vous-même) | O10: 2. Peu utile | P10: 4. Utile | Q10: 5. Très utile | R10: 3. Neutre | S10: 4. Utile | T10: 3. Neutre | U10: 3. Neutre | V10: 4. Utile | W10: 4. Utile | X10: 3. Neutre | Y10: 1. Pas du tout utile | Z10: 1. Pas du tout utile | AA10: 1. Pas du tout utile | AB10: 1. Pas du tout utile | AC10: 1. Pas du tout utile | AD10: 1. Pas du tout utile | AE10: 1. Pas du tout utile | AF10: 1. Pas du tout utile | AG10: 1. Pas du tout utile | AH10: 1. Pas du tout utile | AI10: 7 | AJ10: 7. Très facile (Instinctif / Sans aide) | AK10: 6. D'accord (S'intègre facilement) | AL10: 3 | AM10: 5 | AN10: 7 | AO10: 7 | AP10: 7 | AQ10: 4. Important | AR10: 4. Important | AS10: 4. Important | AT10: 4. Important | AU10: 5 | AV10: 7 | AW10: 6. Approfondie (Parcours certifiant ou auto-formation technique longue) | AX10: 4 | AY10: 4 | AZ10: 1. Pas du tout d’accord (Je vérifie systématiquement chaque détail) | BA10: 6 | BB10: 5 | BC10: 5 | BD10: 6 | BE10: Oui | BF10: 7 | BG10: 4. Neutre | BH10: NA | BI10: 18-25 | BJ10: Femme | BK10: Junior | BL10: Moins de 2 ans | BM10: Audit Financier | BN10: Cabinet international | BO10: 0 | BP10: =IF(ISNUMBER($AI$10),ROUND((((($AI$10-1)*(4/6))+1)),4),"") -> 5 | BQ10: =IF(ISNUMBER($AL$10),8-$AL$10,"") -> 5 | BR10: =IFERROR(8-VALUE(LEFT($AZ$10,1)),"") -> 7 | BS10: =IF(ISNUMBER($BC$10),8-$BC$10,"") -> 3 | BT10: =IF(ISNUMBER($BD$10),8-$BD$10,"") -> 2 | BU10: =IFERROR(ROUND(AVERAGE(VALUE(LEFT($O$10,1)),VALUE(LEFT($P$10,1)),VALUE(LEFT($Q$10,1)),VALUE(LEFT($R$10,1)),VALUE(LEFT($S$10,1)),VALUE(LEFT($T$10,1)),VALUE(LEFT($U$10,1)),VALUE(LEFT($V$10,1)),VALUE(LEFT($W$10,1)),VALUE(LEFT($X$10,1)),VALUE(LEFT($Y$10,1)),VALUE(LEFT($Z$10,1)),VALUE(LEFT($AA$10,1)),VALUE(LEFT($AB$10,1)),VALUE(LEFT($AC$10,1)),VALUE(LEFT($AD$10,1)),VALUE(LEFT($AE$10,1)),VALUE(LEFT($AF$10,1)),VALUE(LEFT($AG$10,1)),VALUE(LEFT($AH$10,1)),$BP$10),4),"") -> 2.381 | BV10: =IFERROR(ROUND(AVERAGE(VALUE(LEFT($AJ$10,1)),VALUE(LEFT($AK$10,1)),$BQ$10),4),"") -> 6 | BW10: =IFERROR(ROUND(AVERAGE($AM$10,$AN$10,$AO$10,$AP$10),4),"") -> 6.5 | BX10: =IFERROR(ROUND(AVERAGE(VALUE(LEFT($AW$10,1)),$AX$10,$AY$10),4),"") -> 4.6667 | BY10: =IFERROR(ROUND(AVERAGE($BR$10,$BA$10,$BB$10,$BS$10,$BT$10),4),"") -> 4.6 | BZ10: =IF(OR($BK$10="Junior",$BK$10="Stagiaire",$BK$10="Alternant"),"Junior",IF(OR($BK$10="Superviseur",$BK$10="Superviseur ",$BK$10="Senior",$BK$10="Senior Manager",$BK$10="Manager"),"Senior-Manager",IF(OR($BK$10="Associe",$BK$10="Associé"),"Associe","Autre"))) -> Junior | CA10: =AND(NOT(ISNUMBER(SEARCH("Jamais",$B$10))),$BG$10="4. Neutre") -> TRUE | CB10: =VALUE(LEFT(B10,1)) -> 4
A11: 46036.891 | B11: 4. Parfois (Environ une fois par semaine) | C11: Outils fournis/agréés par le cabinet (ex: Copilot sécurisé) | D11: 0 | E11: Version entreprise | F11: 0 | G11: 0 | H11: 0 | I11: 0 | J11: 0 | K11: 0 | L11: 0 | M11: Reformulation ou traduction de documents, Recherche d'informations ou de points techniques, Rédaction (rapports, synthèses, notes, mails) | N11: De manière VOLONTAIRE (vous avez choisi vous-même) | O11: 5. Très utile | P11: 4. Utile | Q11: 5. Très utile | R11: 3. Neutre | S11: 4. Utile | T11: 2. Peu utile | U11: 2. Peu utile | V11: 3. Neutre | W11: 3. Neutre | X11: 3. Neutre | Y11: 4. Utile | Z11: 5. Très utile | AA11: 5. Très utile | AB11: 3. Neutre | AC11: 4. Utile | AD11: 2. Peu utile | AE11: 2. Peu utile | AF11: 3. Neutre | AG11: 4. Utile | AH11: 3. Neutre | AI11: 7 | AJ11: 7. Très facile (Instinctif / Sans aide) | AK11: 5. Plutôt d'accord (S'intègre assez bien) | AL11: 3 | AM11: 7 | AN11: 7 | AO11: 1 | AP11: 7 | AQ11: 3. Moyennement important | AR11: 5. Très important | AS11: 1. Pas du tout important | AT11: 4. Important | AU11: 6 | AV11: 7 | AW11: 3. Faible (Moins de 5 heures de formation au total) | AX11: 5 | AY11: 6 | AZ11: 4. Neutre (Le niveau de vérification dépend de la complexité) | BA11: 5 | BB11: 6 | BC11: 2 | BD11: 2 | BE11: Oui | BF11: 7 | BG11: 4. Neutre | BH11: 5 | BI11: 18-25 | BJ11: Homme | BK11: Junior | BL11: Moins de 2 ans | BM11: Audit Financier | BN11: Cabinet local | BO11: 0 | BP11: =IF(ISNUMBER($AI$11),ROUND((((($AI$11-1)*(4/6))+1)),4),"") -> 5 | BQ11: =IF(ISNUMBER($AL$11),8-$AL$11,"") -> 5 | BR11: =IFERROR(8-VALUE(LEFT($AZ$11,1)),"") -> 4 | BS11: =IF(ISNUMBER($BC$11),8-$BC$11,"") -> 6 | BT11: =IF(ISNUMBER($BD$11),8-$BD$11,"") -> 6 | BU11: =IFERROR(ROUND(AVERAGE(VALUE(LEFT($O$11,1)),VALUE(LEFT($P$11,1)),VALUE(LEFT($Q$11,1)),VALUE(LEFT($R$11,1)),VALUE(LEFT($S$11,1)),VALUE(LEFT($T$11,1)),VALUE(LEFT($U$11,1)),VALUE(LEFT($V$11,1)),VALUE(LEFT($W$11,1)),VALUE(LEFT($X$11,1)),VALUE(LEFT($Y$11,1)),VALUE(LEFT($Z$11,1)),VALUE(LEFT($AA$11,1)),VALUE(LEFT($AB$11,1)),VALUE(LEFT($AC$11,1)),VALUE(LEFT($AD$11,1)),VALUE(LEFT($AE$11,1)),VALUE(LEFT($AF$11,1)),VALUE(LEFT($AG$11,1)),VALUE(LEFT($AH$11,1)),$BP$11),4),"") -> 3.5238 | BV11: =IFERROR(ROUND(AVERAGE(VALUE(LEFT($AJ$11,1)),VALUE(LEFT($AK$11,1)),$BQ$11),4),"") -> 5.6667 | BW11: =IFERROR(ROUND(AVERAGE($AM$11,$AN$11,$AO$11,$AP$11),4),"") -> 5.5 | BX11: =IFERROR(ROUND(AVERAGE(VALUE(LEFT($AW$11,1)),$AX$11,$AY$11),4),"") -> 4.6667 | BY11: =IFERROR(ROUND(AVERAGE($BR$11,$BA$11,$BB$11,$BS$11,$BT$11),4),"") -> 5.4 | BZ11: =IF(OR($BK$11="Junior",$BK$11="Stagiaire",$BK$11="Alternant"),"Junior",IF(OR($BK$11="Superviseur",$BK$11="Superviseur ",$BK$11="Senior",$BK$11="Senior Manager",$BK$11="Manager"),"Senior-Manager",IF(OR($BK$11="Associe",$BK$11="Associé"),"Associe","Autre"))) -> Junior | CA11: =AND(NOT(ISNUMBER(SEARCH("Jamais",$B$11))),$BG$11="4. Neutre") -> TRUE | CB11: =VALUE(LEFT(B11,1)) -> 4
A12: 46037.416 | B12: 7. Très fréquemment (Plusieurs fois par jour) | C12: Usage mix des deux | D12: 0 | E12: Version entreprise | F12: Version grand public | G12: Version grand public | H12: 0 | I12: 0 | J12: Version entreprise | K12: Version entreprise | L12: 0 | M12: Évaluation du contrôle interne, Automatisation et création de scripts (SQL, VBA), Reformulation ou traduction de documents, Rédaction (rapports, synthèses, notes, mails) | N12: De manière VOLONTAIRE (vous avez choisi vous-même) | O12: 1. Pas du tout utile | P12: 3. Neutre | Q12: 5. Très utile | R12: 5. Très utile | S12: 5. Très utile | T12: 3. Neutre | U12: 2. Peu utile | V12: 2. Peu utile | W12: 1. Pas du tout utile | X12: 3. Neutre | Y12: 4. Utile | Z12: 4. Utile | AA12: 4. Utile | AB12: 4. Utile | AC12: 5. Très utile | AD12: 2. Peu utile | AE12: 2. Peu utile | AF12: 4. Utile | AG12: 3. Neutre | AH12: 4. Utile | AI12: 5 | AJ12: 7. Très facile (Instinctif / Sans aide) | AK12: 6. D'accord (S'intègre facilement) | AL12: 5 | AM12: 7 | AN12: 7 | AO12: 7 | AP12: 7 | AQ12: 5. Très important | AR12: 5. Très important | AS12: 5. Très important | AT12: 5. Très important | AU12: 4 | AV12: 6 | AW12: 3. Faible (Moins de 5 heures de formation au total) | AX12: 6 | AY12: 6 | AZ12: 4. Neutre (Le niveau de vérification dépend de la complexité) | BA12: 7 | BB12: 7 | BC12: 7 | BD12: 2 | BE12: Oui | BF12: 7 | BG12: 4. Neutre | BH12: 7 | BI12: 18-25 | BJ12: Homme | BK12: Junior | BL12: 2 - 3 ans | BM12: Audit Financier | BN12: Cabinet local | BO12: 0 | BP12: =IF(ISNUMBER($AI$12),ROUND((((($AI$12-1)*(4/6))+1)),4),"") -> 3.6667 | BQ12: =IF(ISNUMBER($AL$12),8-$AL$12,"") -> 3 | BR12: =IFERROR(8-VALUE(LEFT($AZ$12,1)),"") -> 4 | BS12: =IF(ISNUMBER($BC$12),8-$BC$12,"") -> 1 | BT12: =IF(ISNUMBER($BD$12),8-$BD$12,"") -> 6 | BU12: =IFERROR(ROUND(AVERAGE(VALUE(LEFT($O$12,1)),VALUE(LEFT($P$12,1)),VALUE(LEFT($Q$12,1)),VALUE(LEFT($R$12,1)),VALUE(LEFT($S$12,1)),VALUE(LEFT($T$12,1)),VALUE(LEFT($U$12,1)),VALUE(LEFT($V$12,1)),VALUE(LEFT($W$12,1)),VALUE(LEFT($X$12,1)),VALUE(LEFT($Y$12,1)),VALUE(LEFT($Z$12,1)),VALUE(LEFT($AA$12,1)),VALUE(LEFT($AB$12,1)),VALUE(LEFT($AC$12,1)),VALUE(LEFT($AD$12,1)),VALUE(LEFT($AE$12,1)),VALUE(LEFT($AF$12,1)),VALUE(LEFT($AG$12,1)),VALUE(LEFT($AH$12,1)),$BP$12),4),"") -> 3.3175 | BV12: =IFERROR(ROUND(AVERAGE(VALUE(LEFT($AJ$12,1)),VALUE(LEFT($AK$12,1)),$BQ$12),4),"") -> 5.3333 | BW12: =IFERROR(ROUND(AVERAGE($AM$12,$AN$12,$AO$12,$AP$12),4),"") -> 7 | BX12: =IFERROR(ROUND(AVERAGE(VALUE(LEFT($AW$12,1)),$AX$12,$AY$12),4),"") -> 5 | BY12: =IFERROR(ROUND(AVERAGE($BR$12,$BA$12,$BB$12,$BS$12,$BT$12),4),"") -> 5 | BZ12: =IF(OR($BK$12="Junior",$BK$12="Stagiaire",$BK$12="Alternant"),"Junior",IF(OR($BK$12="Superviseur",$BK$12="Superviseur ",$BK$12="Senior",$BK$12="Senior Manager",$BK$12="Manager"),"Senior-Manager",IF(OR($BK$12="Associe",$BK$12="Associé"),"Associe","Autre"))) -> Junior | CA12: =AND(NOT(ISNUMBER(SEARCH("Jamais",$B$12))),$BG$12="4. Neutre") -> TRUE | CB12: =VALUE(LEFT(B12,1)) -> 7
A13: 46037.658 | B13: 7. Très fréquemment (Plusieurs fois par jour) | C13: Usage mix des deux | D13: Version grand public | E13: Version entreprise | F13: Version grand public, Version entreprise | G13: Version entreprise | H13: 0 | I13: Version grand public | J13: Version entreprise | K13: 0 | L13: 0 | M13: Recherche d'informations ou de points techniques, Correction et mise en cohérence de documents, Analyse de données et génération d'insights, Rédaction (rapports, synthèses, notes, mails), Reformulation ou traduction de documents | N13: De manière RECOMMANDÉE (cabinet encourage, mais facultatif) | O13: 1. Pas du tout utile | P13: 4. Utile | Q13: 5. Très utile | R13: 5. Très utile | S13: 5. Très utile | T13: 3. Neutre | U13: 3. Neutre | V13: 3. Neutre | W13: 4. Utile | X13: 3. Neutre | Y13: 3. Neutre | Z13: 4. Utile | AA13: 5. Très utile | AB13: 4. Utile | AC13: 4. Utile | AD13: 3. Neutre | AE13: 3. Neutre | AF13: 3. Neutre | AG13: 3. Neutre | AH13: 3. Neutre | AI13: 7 | AJ13: 7. Très facile (Instinctif / Sans aide) | AK13: 7. Tout à fait d'accord (Automatisme quotidien) | AL13: 2 | AM13: 7 | AN13: 7 | AO13: 5 | AP13: 6 | AQ13: 5. Très important | AR13: 5. Très important | AS13: 4. Important | AT13: 4. Important | AU13: 1 | AV13: 4 | AW13: 6. Approfondie (Parcours certifiant ou auto-formation technique longue) | AX13: 7 | AY13: 7 | AZ13: 1. Pas du tout d’accord (Je vérifie systématiquement chaque détail) | BA13: 6 | BB13: 6 | BC13: 7 | BD13: 1 | BE13: Oui | BF13: 7 | BG13: 4. Neutre | BH13: 7 | BI13: 26-35 | BJ13: Homme | BK13: Senior Manager | BL13: Plus de 10 ans | BM13: Audit IT | BN13: Cabinet international | BO13: Pour moi l'IA générative est comme un super stagiaire : il ne peut pas être responsable et on doit vérifier son travail (car il y a probablement des erreurs). Le plus grand risque selon moi est pour les personnes avec peu d'expérience "métier", qui vont s'appuyer sur l'IA sans être en capacité d'identifier les erreurs. | BP13: =IF(ISNUMBER($AI$13),ROUND((((($AI$13-1)*(4/6))+1)),4),"") -> 5 | BQ13: =IF(ISNUMBER($AL$13),8-$AL$13,"") -> 6 | BR13: =IFERROR(8-VALUE(LEFT($AZ$13,1)),"") -> 7 | BS13: =IF(ISNUMBER($BC$13),8-$BC$13,"") -> 1 | BT13: =IF(ISNUMBER($BD$13),8-$BD$13,"") -> 7 | BU13: =IFERROR(ROUND(AVERAGE(VALUE(LEFT($O$13,1)),VALUE(LEFT($P$13,1)),VALUE(LEFT($Q$13,1)),VALUE(LEFT($R$13,1)),VALUE(LEFT($S$13,1)),VALUE(LEFT($T$13,1)),VALUE(LEFT($U$13,1)),VALUE(LEFT($V$13,1)),VALUE(LEFT($W$13,1)),VALUE(LEFT($X$13,1)),VALUE(LEFT($Y$13,1)),VALUE(LEFT($Z$13,1)),VALUE(LEFT($AA$13,1)),VALUE(LEFT($AB$13,1)),VALUE(LEFT($AC$13,1)),VALUE(LEFT($AD$13,1)),VALUE(LEFT($AE$13,1)),VALUE(LEFT($AF$13,1)),VALUE(LEFT($AG$13,1)),VALUE(LEFT($AH$13,1)),$BP$13),4),"") -> 3.619 | BV13: =IFERROR(ROUND(AVERAGE(VALUE(LEFT($AJ$13,1)),VALUE(LEFT($AK$13,1)),$BQ$13),4),"") -> 6.6667 | BW13: =IFERROR(ROUND(AVERAGE($AM$13,$AN$13,$AO$13,$AP$13),4),"") -> 6.25 | BX13: =IFERROR(ROUND(AVERAGE(VALUE(LEFT($AW$13,1)),$AX$13,$AY$13),4),"") -> 6.6667 | BY13: =IFERROR(ROUND(AVERAGE($BR$13,$BA$13,$BB$13,$BS$13,$BT$13),4),"") -> 5.4 | BZ13: =IF(OR($BK$13="Junior",$BK$13="Stagiaire",$BK$13="Alternant"),"Junior",IF(OR($BK$13="Superviseur",$BK$13="Superviseur ",$BK$13="Senior",$BK$13="Senior Manager",$BK$13="Manager"),"Senior-Manager",IF(OR($BK$13="Associe",$BK$13="Associé"),"Associe","Autre"))) -> Senior-Manager | CA13: =AND(NOT(ISNUMBER(SEARCH("Jamais",$B$13))),$BG$13="4. Neutre") -> TRUE | CB13: =VALUE(LEFT(B13,1)) -> 7
A14: 46038.388 | B14: 6. Quotidiennement (Une fois par jour) | C14: Outils fournis/agréés par le cabinet (ex: Copilot sécurisé) | D14: 0 | E14: Version entreprise | F14: 0 | G14: 0 | H14: 0 | I14: 0 | J14: 0 | K14: 0 | L14: 0 | M14: Reformulation ou traduction de documents, Rédaction (rapports, synthèses, notes, mails), Automatisation et création de scripts (SQL, VBA) | N14: De manière RECOMMANDÉE (cabinet encourage, mais facultatif) | O14: 5. Très utile | P14: 5. Très utile | Q14: 5. Très utile | R14: 3. Neutre | S14: 5. Très utile | T14: 2. Peu utile | U14: 2. Peu utile | V14: 2. Peu utile | W14: 3. Neutre | X14: 4. Utile | Y14: 3. Neutre | Z14: 5. Très utile | AA14: 5. Très utile | AB14: 4. Utile | AC14: 5. Très utile | AD14: 3. Neutre | AE14: 1. Pas du tout utile | AF14: 2. Peu utile | AG14: 3. Neutre | AH14: 4. Utile | AI14: 6 | AJ14: 7. Très facile (Instinctif / Sans aide) | AK14: 6. D'accord (S'intègre facilement) | AL14: 2 | AM14: 7 | AN14: 4 | AO14: 7 | AP14: 6 | AQ14: 4. Important | AR14: 5. Très important | AS14: 3. Moyennement important | AT14: 5. Très important | AU14: 4 | AV14: 7 | AW14: 6. Approfondie (Parcours certifiant ou auto-formation technique longue) | AX14: 5 | AY14: 3 | AZ14: 4. Neutre (Le niveau de vérification dépend de la complexité) | BA14: 5 | BB14: 4 | BC14: 6 | BD14: 3 | BE14: Non | BF14: 2 | BG14: 4. Neutre | BH14: 6 | BI14: 18-25 | BJ14: Homme | BK14: Junior | BL14: 6 - 7 ans | BM14: Audit Financier | BN14: Cabinet régional | BO14: 0 | BP14: =IF(ISNUMBER($AI$14),ROUND((((($AI$14-1)*(4/6))+1)),4),"") -> 4.3333 | BQ14: =IF(ISNUMBER($AL$14),8-$AL$14,"") -> 6 | BR14: =IFERROR(8-VALUE(LEFT($AZ$14,1)),"") -> 4 | BS14: =IF(ISNUMBER($BC$14),8-$BC$14,"") -> 2 | BT14: =IF(ISNUMBER($BD$14),8-$BD$14,"") -> 5 | BU14: =IFERROR(ROUND(AVERAGE(VALUE(LEFT($O$14,1)),VALUE(LEFT($P$14,1)),VALUE(LEFT($Q$14,1)),VALUE(LEFT($R$14,1)),VALUE(LEFT($S$14,1)),VALUE(LEFT($T$14,1)),VALUE(LEFT($U$14,1)),VALUE(LEFT($V$14,1)),VALUE(LEFT($W$14,1)),VALUE(LEFT($X$14,1)),VALUE(LEFT($Y$14,1)),VALUE(LEFT($Z$14,1)),VALUE(LEFT($AA$14,1)),VALUE(LEFT($AB$14,1)),VALUE(LEFT($AC$14,1)),VALUE(LEFT($AD$14,1)),VALUE(LEFT($AE$14,1)),VALUE(LEFT($AF$14,1)),VALUE(LEFT($AG$14,1)),VALUE(LEFT($AH$14,1)),$BP$14),4),"") -> 3.5873 | BV14: =IFERROR(ROUND(AVERAGE(VALUE(LEFT($AJ$14,1)),VALUE(LEFT($AK$14,1)),$BQ$14),4),"") -> 6.3333 | BW14: =IFERROR(ROUND(AVERAGE($AM$14,$AN$14,$AO$14,$AP$14),4),"") -> 6 | BX14: =IFERROR(ROUND(AVERAGE(VALUE(LEFT($AW$14,1)),$AX$14,$AY$14),4),"") -> 4.6667 | BY14: =IFERROR(ROUND(AVERAGE($BR$14,$BA$14,$BB$14,$BS$14,$BT$14),4),"") -> 4 | BZ14: =IF(OR($BK$14="Junior",$BK$14="Stagiaire",$BK$14="Alternant"),"Junior",IF(OR($BK$14="Superviseur",$BK$14="Superviseur ",$BK$14="Senior",$BK$14="Senior Manager",$BK$14="Manager"),"Senior-Manager",IF(OR($BK$14="Associe",$BK$14="Associé"),"Associe","Autre"))) -> Junior | CA14: =AND(NOT(ISNUMBER(SEARCH("Jamais",$B$14))),$BG$14="4. Neutre") -> TRUE | CB14: =VALUE(LEFT(B14,1)) -> 6
A15: 46038.983 | B15: 3. Rarement (1 à 3 fois par mois) | C15: Usage mix des deux | D15: 0 | E15: 0 | F15: Version grand public | G15: Version grand public | H15: Version grand public | I15: 0 | J15: 0 | K15: Version entreprise | L15: 0 | M15: Rédaction (rapports, synthèses, notes, mails), Recherche d'informations ou de points techniques, Revue d'estimations comptables (provisions, dépréciations), Évaluation du contrôle interne, Aide à la décision | N15: De manière VOLONTAIRE (vous avez choisi vous-même) | O15: 3. Neutre | P15: 5. Très utile | Q15: 5. Très utile | R15: 4. Utile | S15: 3. Neutre | T15: 2. Peu utile | U15: 2. Peu utile | V15: 4. Utile | W15: 4. Utile | X15: 3. Neutre | Y15: 2. Peu utile | Z15: 4. Utile | AA15: 5. Très utile | AB15: 5. Très utile | AC15: 4. Utile | AD15: 3. Neutre | AE15: 3. Neutre | AF15: 3. Neutre | AG15: 4. Utile | AH15: 3. Neutre | AI15: 4 | AJ15: 4. Ni facile, ni difficile (Prise en main normale) | AK15: 5. Plutôt d'accord (S'intègre assez bien) | AL15: 6 | AM15: 6 | AN15: 7 | AO15: 6 | AP15: 3 | AQ15: 5. Très important | AR15: 5. Très important | AS15: 3. Moyennement important | AT15: 3. Moyennement important | AU15: 4 | AV15: 5 | AW15: 5. Solide (Plusieurs jours de formation ou modules suivis) | AX15: 6 | AY15: 6 | AZ15: 4. Neutre (Le niveau de vérification dépend de la complexité) | BA15: 6 | BB15: 4 | BC15: 3 | BD15: 5 | BE15: Non | BF15: 7 | BG15: 4. Neutre | BH15: 3 | BI15: 18-25 | BJ15: Femme | BK15: Junior | BL15: 2 - 3 ans | BM15: Audit Financier | BN15: Cabinet international | BO15: 0 | BP15: =IF(ISNUMBER($AI$15),ROUND((((($AI$15-1)*(4/6))+1)),4),"") -> 3 | BQ15: =IF(ISNUMBER($AL$15),8-$AL$15,"") -> 2 | BR15: =IFERROR(8-VALUE(LEFT($AZ$15,1)),"") -> 4 | BS15: =IF(ISNUMBER($BC$15),8-$BC$15,"") -> 5 | BT15: =IF(ISNUMBER($BD$15),8-$BD$15,"") -> 3 | BU15: =IFERROR(ROUND(AVERAGE(VALUE(LEFT($O$15,1)),VALUE(LEFT($P$15,1)),VALUE(LEFT($Q$15,1)),VALUE(LEFT($R$15,1)),VALUE(LEFT($S$15,1)),VALUE(LEFT($T$15,1)),VALUE(LEFT($U$15,1)),VALUE(LEFT($V$15,1)),VALUE(LEFT($W$15,1)),VALUE(LEFT($X$15,1)),VALUE(LEFT($Y$15,1)),VALUE(LEFT($Z$15,1)),VALUE(LEFT($AA$15,1)),VALUE(LEFT($AB$15,1)),VALUE(LEFT($AC$15,1)),VALUE(LEFT($AD$15,1)),VALUE(LEFT($AE$15,1)),VALUE(LEFT($AF$15,1)),VALUE(LEFT($AG$15,1)),VALUE(LEFT($AH$15,1)),$BP$15),4),"") -> 3.5238 | BV15: =IFERROR(ROUND(AVERAGE(VALUE(LEFT($AJ$15,1)),VALUE(LEFT($AK$15,1)),$BQ$15),4),"") -> 3.6667 | BW15: =IFERROR(ROUND(AVERAGE($AM$15,$AN$15,$AO$15,$AP$15),4),"") -> 5.5 | BX15: =IFERROR(ROUND(AVERAGE(VALUE(LEFT($AW$15,1)),$AX$15,$AY$15),4),"") -> 5.6667 | BY15: =IFERROR(ROUND(AVERAGE($BR$15,$BA$15,$BB$15,$BS$15,$BT$15),4),"") -> 4.4 | BZ15: =IF(OR($BK$15="Junior",$BK$15="Stagiaire",$BK$15="Alternant"),"Junior",IF(OR($BK$15="Superviseur",$BK$15="Superviseur ",$BK$15="Senior",$BK$15="Senior Manager",$BK$15="Manager"),"Senior-Manager",IF(OR($BK$15="Associe",$BK$15="Associé"),"Associe","Autre"))) -> Junior | CA15: =AND(NOT(ISNUMBER(SEARCH("Jamais",$B$15))),$BG$15="4. Neutre") -> TRUE | CB15: =VALUE(LEFT(B15,1)) -> 3
A16: 46039.411 | B16: 7. Très fréquemment (Plusieurs fois par jour) | C16: Outils fournis/agréés par le cabinet (ex: Copilot sécurisé) | D16: 0 | E16: Version entreprise | F16: 0 | G16: 0 | H16: 0 | I16: 0 | J16: 0 | K16: Version entreprise | L16: 0 | M16: Reformulation ou traduction de documents, Rédaction (rapports, synthèses, notes, mails), Automatisation et création de scripts (SQL, VBA) | N16: De manière VOLONTAIRE (vous avez choisi vous-même) | O16: 4. Utile | P16: 5. Très utile | Q16: 4. Utile | R16: 2. Peu utile | S16: 5. Très utile | T16: 3. Neutre | U16: 3. Neutre | V16: 2. Peu utile | W16: 3. Neutre | X16: 4. Utile | Y16: 4. Utile | Z16: 3. Neutre | AA16: 3. Neutre | AB16: 2. Peu utile | AC16: 5. Très utile | AD16: 3. Neutre | AE16: 2. Peu utile | AF16: 2. Peu utile | AG16: 2. Peu utile | AH16: 4. Utile | AI16: 5 | AJ16: 6. Facile (Maîtrise rapide) | AK16: 6. D'accord (S'intègre facilement) | AL16: 3 | AM16: 7 | AN16: 7 | AO16: 3 | AP16: 7 | AQ16: 4. Important | AR16: 5. Très important | AS16: 3. Moyennement important | AT16: 4. Important | AU16: 5 | AV16: 7 | AW16: 4. Moyenne (Environ une journée de formation cumulée) | AX16: 6 | AY16: 6 | AZ16: 3. Plutôt en désaccord (Je procède à une revue importante) | BA16: 4 | BB16: 5 | BC16: 4 | BD16: 5 | BE16: Oui | BF16: 5 | BG16: 4. Neutre | BH16: 6 | BI16: 26-35 | BJ16: Homme | BK16: Senior | BL16: 4 - 5 ans | BM16: Audit IT | BN16: Cabinet international | BO16: 0 | BP16: =IF(ISNUMBER($AI$16),ROUND((((($AI$16-1)*(4/6))+1)),4),"") -> 3.6667 | BQ16: =IF(ISNUMBER($AL$16),8-$AL$16,"") -> 5 | BR16: =IFERROR(8-VALUE(LEFT($AZ$16,1)),"") -> 5 | BS16: =IF(ISNUMBER($BC$16),8-$BC$16,"") -> 4 | BT16: =IF(ISNUMBER($BD$16),8-$BD$16,"") -> 3 | BU16: =IFERROR(ROUND(AVERAGE(VALUE(LEFT($O$16,1)),VALUE(LEFT($P$16,1)),VALUE(LEFT($Q$16,1)),VALUE(LEFT($R$16,1)),VALUE(LEFT($S$16,1)),VALUE(LEFT($T$16,1)),VALUE(LEFT($U$16,1)),VALUE(LEFT($V$16,1)),VALUE(LEFT($W$16,1)),VALUE(LEFT($X$16,1)),VALUE(LEFT($Y$16,1)),VALUE(LEFT($Z$16,1)),VALUE(LEFT($AA$16,1)),VALUE(LEFT($AB$16,1)),VALUE(LEFT($AC$16,1)),VALUE(LEFT($AD$16,1)),VALUE(LEFT($AE$16,1)),VALUE(LEFT($AF$16,1)),VALUE(LEFT($AG$16,1)),VALUE(LEFT($AH$16,1)),$BP$16),4),"") -> 3.2698 | BV16: =IFERROR(ROUND(AVERAGE(VALUE(LEFT($AJ$16,1)),VALUE(LEFT($AK$16,1)),$BQ$16),4),"") -> 5.6667 | BW16: =IFERROR(ROUND(AVERAGE($AM$16,$AN$16,$AO$16,$AP$16),4),"") -> 6 | BX16: =IFERROR(ROUND(AVERAGE(VALUE(LEFT($AW$16,1)),$AX$16,$AY$16),4),"") -> 5.3333 | BY16: =IFERROR(ROUND(AVERAGE($BR$16,$BA$16,$BB$16,$BS$16,$BT$16),4),"") -> 4.2 | BZ16: =IF(OR($BK$16="Junior",$BK$16="Stagiaire",$BK$16="Alternant"),"Junior",IF(OR($BK$16="Superviseur",$BK$16="Superviseur ",$BK$16="Senior",$BK$16="Senior Manager",$BK$16="Manager"),"Senior-Manager",IF(OR($BK$16="Associe",$BK$16="Associé"),"Associe","Autre"))) -> Senior-Manager | CA16: =AND(NOT(ISNUMBER(SEARCH("Jamais",$B$16))),$BG$16="4. Neutre") -> TRUE | CB16: =VALUE(LEFT(B16,1)) -> 7
A17: 46040.715 | B17: 5. Régulièrement (Plusieurs fois par semaine) | C17: Outils grand public (ex: ChatGPT, Gemini ) | D17: Version grand public | E17: Version grand public | F17: Version entreprise | G17: Version grand public | H17: Version grand public | I17: Version grand public | J17: Version grand public | K17: Version entreprise | L17: Version grand public | M17: Rapprochement/Comparaison de documents, Reformulation ou traduction de documents, Correction et mise en cohérence de documents, Évaluation du contrôle interne, Préparation de données (format, structuration, harmonisation des valeurs), Recherche d'informations ou de points techniques, Rédaction (rapports, synthèses, notes, mails) | N17: De manière VOLONTAIRE (vous avez choisi vous-même) | O17: 4. Utile | P17: 5. Très utile | Q17: 4. Utile | R17: 5. Très utile | S17: 3. Neutre | T17: 4. Utile | U17: 1. Pas du tout utile | V17: 3. Neutre | W17: 5. Très utile | X17: 5. Très utile | Y17: 5. Très utile | Z17: 5. Très utile | AA17: 4. Utile | AB17: 5. Très utile | AC17: 3. Neutre | AD17: 3. Neutre | AE17: 1. Pas du tout utile | AF17: 2. Peu utile | AG17: 4. Utile | AH17: 4. Utile | AI17: 6 | AJ17: 5. Plutôt facile (Assez intuitif) | AK17: 5. Plutôt d'accord (S'intègre assez bien) | AL17: 6 | AM17: 5 | AN17: 4 | AO17: 3 | AP17: 2 | AQ17: 5. Très important | AR17: 5. Très important | AS17: 4. Important | AT17: 4. Important | AU17: 2 | AV17: 4 | AW17: 4. Moyenne (Environ une journée de formation cumulée) | AX17: 5 | AY17: 5 | AZ17: 2. En désaccord (Je contrôle la quasi-totalité des éléments) | BA17: 6 | BB17: 6 | BC17: 7 | BD17: 6 | BE17: Oui | BF17: 6 | BG17: 4. Neutre | BH17: 6 | BI17: 26-35 | BJ17: Homme | BK17: Senior | BL17: 2 - 3 ans | BM17: Audit Financier | BN17: Cabinet international | BO17: 0 | BP17: =IF(ISNUMBER($AI$17),ROUND((((($AI$17-1)*(4/6))+1)),4),"") -> 4.3333 | BQ17: =IF(ISNUMBER($AL$17),8-$AL$17,"") -> 2 | BR17: =IFERROR(8-VALUE(LEFT($AZ$17,1)),"") -> 6 | BS17: =IF(ISNUMBER($BC$17),8-$BC$17,"") -> 1 | BT17: =IF(ISNUMBER($BD$17),8-$BD$17,"") -> 2 | BU17: =IFERROR(ROUND(AVERAGE(VALUE(LEFT($O$17,1)),VALUE(LEFT($P$17,1)),VALUE(LEFT($Q$17,1)),VALUE(LEFT($R$17,1)),VALUE(LEFT($S$17,1)),VALUE(LEFT($T$17,1)),VALUE(LEFT($U$17,1)),VALUE(LEFT($V$17,1)),VALUE(LEFT($W$17,1)),VALUE(LEFT($X$17,1)),VALUE(LEFT($Y$17,1)),VALUE(LEFT($Z$17,1)),VALUE(LEFT($AA$17,1)),VALUE(LEFT($AB$17,1)),VALUE(LEFT($AC$17,1)),VALUE(LEFT($AD$17,1)),VALUE(LEFT($AE$17,1)),VALUE(LEFT($AF$17,1)),VALUE(LEFT($AG$17,1)),VALUE(LEFT($AH$17,1)),$BP$17),4),"") -> 3.7778 | BV17: =IFERROR(ROUND(AVERAGE(VALUE(LEFT($AJ$17,1)),VALUE(LEFT($AK$17,1)),$BQ$17),4),"") -> 4 | BW17: =IFERROR(ROUND(AVERAGE($AM$17,$AN$17,$AO$17,$AP$17),4),"") -> 3.5 | BX17: =IFERROR(ROUND(AVERAGE(VALUE(LEFT($AW$17,1)),$AX$17,$AY$17),4),"") -> 4.6667 | BY17: =IFERROR(ROUND(AVERAGE($BR$17,$BA$17,$BB$17,$BS$17,$BT$17),4),"") -> 4.2 | BZ17: =IF(OR($BK$17="Junior",$BK$17="Stagiaire",$BK$17="Alternant"),"Junior",IF(OR($BK$17="Superviseur",$BK$17="Superviseur ",$BK$17="Senior",$BK$17="Senior Manager",$BK$17="Manager"),"Senior-Manager",IF(OR($BK$17="Associe",$BK$17="Associé"),"Associe","Autre"))) -> Senior-Manager | CA17: =AND(NOT(ISNUMBER(SEARCH("Jamais",$B$17))),$BG$17="4. Neutre") -> TRUE | CB17: =VALUE(LEFT(B17,1)) -> 5
A18: 46042.408 | B18: 4. Parfois (Environ une fois par semaine) | C18: Outils fournis/agréés par le cabinet (ex: Copilot sécurisé) | D18: 0 | E18: Version entreprise | F18: 0 | G18: Version grand public | H18: 0 | I18: 0 | J18: 0 | K18: 0 | L18: 0 | M18: Rédaction (rapports, synthèses, notes, mails), Reformulation ou traduction de documents, Recherche d'informations ou de points techniques | N18: De manière VOLONTAIRE (vous avez choisi vous-même) | O18: 4. Utile | P18: 4. Utile | Q18: 4. Utile | R18: 4. Utile | S18: 3. Neutre | T18: 4. Utile | U18: 2. Peu utile | V18: 4. Utile | W18: 3. Neutre | X18: 3. Neutre | Y18: 4. Utile | Z18: 4. Utile | AA18: 4. Utile | AB18: 4. Utile | AC18: 3. Neutre | AD18: 4. Utile | AE18: 2. Peu utile | AF18: 4. Utile | AG18: 3. Neutre | AH18: 3. Neutre | AI18: 4 | AJ18: 4. Ni facile, ni difficile (Prise en main normale) | AK18: 2. En désaccord (Difficile à intégrer au métier) | AL18: 6 | AM18: 7 | AN18: 7 | AO18: 3 | AP18: 5 | AQ18: 5. Très important | AR18: 5. Très important | AS18: 4. Important | AT18: 3. Moyennement important | AU18: 6 | AV18: 7 | AW18: 6. Approfondie (Parcours certifiant ou auto-formation technique longue) | AX18: 5 | AY18: 5 | AZ18: 3. Plutôt en désaccord (Je procède à une revue importante) | BA18: 6 | BB18: 4 | BC18: 5 | BD18: 2 | BE18: Conditionné à la politique du cabinet | BF18: 6 | BG18: 4. Neutre | BH18: 5 | BI18: 26-35 | BJ18: Homme | BK18: Superviseur | BL18: 6 - 7 ans | BM18: Audit Financier | BN18: National et membre d'un réseau | BO18: 0 | BP18: =IF(ISNUMBER($AI$18),ROUND((((($AI$18-1)*(4/6))+1)),4),"") -> 3 | BQ18: =IF(ISNUMBER($AL$18),8-$AL$18,"") -> 2 | BR18: =IFERROR(8-VALUE(LEFT($AZ$18,1)),"") -> 5 | BS18: =IF(ISNUMBER($BC$18),8-$BC$18,"") -> 3 | BT18: =IF(ISNUMBER($BD$18),8-$BD$18,"") -> 6 | BU18: =IFERROR(ROUND(AVERAGE(VALUE(LEFT($O$18,1)),VALUE(LEFT($P$18,1)),VALUE(LEFT($Q$18,1)),VALUE(LEFT($R$18,1)),VALUE(LEFT($S$18,1)),VALUE(LEFT($T$18,1)),VALUE(LEFT($U$18,1)),VALUE(LEFT($V$18,1)),VALUE(LEFT($W$18,1)),VALUE(LEFT($X$18,1)),VALUE(LEFT($Y$18,1)),VALUE(LEFT($Z$18,1)),VALUE(LEFT($AA$18,1)),VALUE(LEFT($AB$18,1)),VALUE(LEFT($AC$18,1)),VALUE(LEFT($AD$18,1)),VALUE(LEFT($AE$18,1)),VALUE(LEFT($AF$18,1)),VALUE(LEFT($AG$18,1)),VALUE(LEFT($AH$18,1)),$BP$18),4),"") -> 3.4762 | BV18: =IFERROR(ROUND(AVERAGE(VALUE(LEFT($AJ$18,1)),VALUE(LEFT($AK$18,1)),$BQ$18),4),"") -> 2.6667 | BW18: =IFERROR(ROUND(AVERAGE($AM$18,$AN$18,$AO$18,$AP$18),4),"") -> 5.5 | BX18: =IFERROR(ROUND(AVERAGE(VALUE(LEFT($AW$18,1)),$AX$18,$AY$18),4),"") -> 5.3333 | BY18: =IFERROR(ROUND(AVERAGE($BR$18,$BA$18,$BB$18,$BS$18,$BT$18),4),"") -> 4.8 | BZ18: =IF(OR($BK$18="Junior",$BK$18="Stagiaire",$BK$18="Alternant"),"Junior",IF(OR($BK$18="Superviseur",$BK$18="Superviseur ",$BK$18="Senior",$BK$18="Senior Manager",$BK$18="Manager"),"Senior-Manager",IF(OR($BK$18="Associe",$BK$18="Associé"),"Associe","Autre"))) -> Senior-Manager | CA18: =AND(NOT(ISNUMBER(SEARCH("Jamais",$B$18))),$BG$18="4. Neutre") -> TRUE | CB18: =VALUE(LEFT(B18,1)) -> 4
A19: 46043.86 | B19: 5. Régulièrement (Plusieurs fois par semaine) | C19: Outils grand public (ex: ChatGPT, Gemini ) | D19: 0 | E19: 0 | F19: Version entreprise | G19: 0 | H19: 0 | I19: 0 | J19: 0 | K19: 0 | L19: 0 | M19: Rédaction (rapports, synthèses, notes, mails), Analyse de données et génération d'insights, Reformulation ou traduction de documents, Recherche d'informations ou de points techniques | N19: De manière RECOMMANDÉE (cabinet encourage, mais facultatif) | O19: 4. Utile | P19: 4. Utile | Q19: 5. Très utile | R19: 2. Peu utile | S19: 3. Neutre | T19: 3. Neutre | U19: 3. Neutre | V19: 2. Peu utile | W19: 2. Peu utile | X19: 5. Très utile | Y19: 5. Très utile | Z19: 5. Très utile | AA19: 5. Très utile | AB19: 3. Neutre | AC19: 3. Neutre | AD19: 3. Neutre | AE19: 3. Neutre | AF19: 3. Neutre | AG19: 2. Peu utile | AH19: 5. Très utile | AI19: 6 | AJ19: 7. Très facile (Instinctif / Sans aide) | AK19: 6. D'accord (S'intègre facilement) | AL19: 3 | AM19: 5 | AN19: 6 | AO19: 5 | AP19: 2 | AQ19: 4. Important | AR19: 5. Très important | AS19: 3. Moyennement important | AT19: 1. Pas du tout important | AU19: 1 | AV19: 7 | AW19: 6. Approfondie (Parcours certifiant ou auto-formation technique longue) | AX19: 5 | AY19: 4 | AZ19: 4. Neutre (Le niveau de vérification dépend de la complexité) | BA19: 5 | BB19: 6 | BC19: 5 | BD19: 3 | BE19: Oui | BF19: 6 | BG19: 4. Neutre | BH19: 4 | BI19: 26-35 | BJ19: Femme | BK19: Senior | BL19: 4 - 5 ans | BM19: Audit Financier, Audit Interne, Audit acquisition | BN19: Cabinet local | BO19: 0 | BP19: =IF(ISNUMBER($AI$19),ROUND((((($AI$19-1)*(4/6))+1)),4),"") -> 4.3333 | BQ19: =IF(ISNUMBER($AL$19),8-$AL$19,"") -> 5 | BR19: =IFERROR(8-VALUE(LEFT($AZ$19,1)),"") -> 4 | BS19: =IF(ISNUMBER($BC$19),8-$BC$19,"") -> 3 | BT19: =IF(ISNUMBER($BD$19),8-$BD$19,"") -> 5 | BU19: =IFERROR(ROUND(AVERAGE(VALUE(LEFT($O$19,1)),VALUE(LEFT($P$19,1)),VALUE(LEFT($Q$19,1)),VALUE(LEFT($R$19,1)),VALUE(LEFT($S$19,1)),VALUE(LEFT($T$19,1)),VALUE(LEFT($U$19,1)),VALUE(LEFT($V$19,1)),VALUE(LEFT($W$19,1)),VALUE(LEFT($X$19,1)),VALUE(LEFT($Y$19,1)),VALUE(LEFT($Z$19,1)),VALUE(LEFT($AA$19,1)),VALUE(LEFT($AB$19,1)),VALUE(LEFT($AC$19,1)),VALUE(LEFT($AD$19,1)),VALUE(LEFT($AE$19,1)),VALUE(LEFT($AF$19,1)),VALUE(LEFT($AG$19,1)),VALUE(LEFT($AH$19,1)),$BP$19),4),"") -> 3.5397 | BV19: =IFERROR(ROUND(AVERAGE(VALUE(LEFT($AJ$19,1)),VALUE(LEFT($AK$19,1)),$BQ$19),4),"") -> 6 | BW19: =IFERROR(ROUND(AVERAGE($AM$19,$AN$19,$AO$19,$AP$19),4),"") -> 4.5 | BX19: =IFERROR(ROUND(AVERAGE(VALUE(LEFT($AW$19,1)),$AX$19,$AY$19),4),"") -> 5 | BY19: =IFERROR(ROUND(AVERAGE($BR$19,$BA$19,$BB$19,$BS$19,$BT$19),4),"") -> 4.6 | BZ19: =IF(OR($BK$19="Junior",$BK$19="Stagiaire",$BK$19="Alternant"),"Junior",IF(OR($BK$19="Superviseur",$BK$19="Superviseur ",$BK$19="Senior",$BK$19="Senior Manager",$BK$19="Manager"),"Senior-Manager",IF(OR($BK$19="Associe",$BK$19="Associé"),"Associe","Autre"))) -> Senior-Manager | CA19: =AND(NOT(ISNUMBER(SEARCH("Jamais",$B$19))),$BG$19="4. Neutre") -> TRUE | CB19: =VALUE(LEFT(B19,1)) -> 5
A20: 46047.149 | B20: 7. Très fréquemment (Plusieurs fois par jour) | C20: Usage mix des deux | D20: 0 | E20: 0 | F20: Version grand public | G20: 0 | H20: 0 | I20: 0 | J20: 0 | K20: 0 | L20: 0 | M20: Correction et mise en cohérence de documents, Rapprochement/Comparaison de documents, Détermination du seuil de signification, Évaluation du contrôle interne, Recherche d'informations ou de points techniques, Rédaction (rapports, synthèses, notes, mails), Préparation de données (format, structuration, harmonisation des valeurs), Automatisation et création de scripts (SQL, VBA), Reformulation ou traduction de documents | N20: De manière VOLONTAIRE (vous avez choisi vous-même) | O20: 3. Neutre | P20: 3. Neutre | Q20: 3. Neutre | R20: 2. Peu utile | S20: 3. Neutre | T20: 3. Neutre | U20: 3. Neutre | V20: 3. Neutre | W20: 1. Pas du tout utile | X20: 3. Neutre | Y20: 3. Neutre | Z20: 3. Neutre | AA20: 3. Neutre | AB20: 1. Pas du tout utile | AC20: 3. Neutre | AD20: 3. Neutre | AE20: 3. Neutre | AF20: 1. Pas du tout utile | AG20: 1. Pas du tout utile | AH20: 3. Neutre | AI20: 7 | AJ20: 6. Facile (Maîtrise rapide) | AK20: 7. Tout à fait d'accord (Automatisme quotidien) | AL20: 2 | AM20: 7 | AN20: 1 | AO20: 7 | AP20: 7 | AQ20: 3. Moyennement important | AR20: 3. Moyennement important | AS20: 1. Pas du tout important | AT20: 1. Pas du tout important | AU20: 7 | AV20: 7 | AW20: 4. Moyenne (Environ une journée de formation cumulée) | AX20: 7 | AY20: 7 | AZ20: 4. Neutre (Le niveau de vérification dépend de la complexité) | BA20: 4 | BB20: 7 | BC20: 7 | BD20: 1 | BE20: Non | BF20: 7 | BG20: 4. Neutre | BH20: 7 | BI20: 46-55 | BJ20: Homme | BK20: Manager | BL20: Plus de 10 ans | BM20: Audit Financier, Audit IT, Audit Interne | BN20: Cabinet international | BO20: 0 | BP20: =IF(ISNUMBER($AI$20),ROUND((((($AI$20-1)*(4/6))+1)),4),"") -> 5 | BQ20: =IF(ISNUMBER($AL$20),8-$AL$20,"") -> 6 | BR20: =IFERROR(8-VALUE(LEFT($AZ$20,1)),"") -> 4 | BS20: =IF(ISNUMBER($BC$20),8-$BC$20,"") -> 1 | BT20: =IF(ISNUMBER($BD$20),8-$BD$20,"") -> 7 | BU20: =IFERROR(ROUND(AVERAGE(VALUE(LEFT($O$20,1)),VALUE(LEFT($P$20,1)),VALUE(LEFT($Q$20,1)),VALUE(LEFT($R$20,1)),VALUE(LEFT($S$20,1)),VALUE(LEFT($T$20,1)),VALUE(LEFT($U$20,1)),VALUE(LEFT($V$20,1)),VALUE(LEFT($W$20,1)),VALUE(LEFT($X$20,1)),VALUE(LEFT($Y$20,1)),VALUE(LEFT($Z$20,1)),VALUE(LEFT($AA$20,1)),VALUE(LEFT($AB$20,1)),VALUE(LEFT($AC$20,1)),VALUE(LEFT($AD$20,1)),VALUE(LEFT($AE$20,1)),VALUE(LEFT($AF$20,1)),VALUE(LEFT($AG$20,1)),VALUE(LEFT($AH$20,1)),$BP$20),4),"") -> 2.6667 | BV20: =IFERROR(ROUND(AVERAGE(VALUE(LEFT($AJ$20,1)),VALUE(LEFT($AK$20,1)),$BQ$20),4),"") -> 6.3333 | BW20: =IFERROR(ROUND(AVERAGE($AM$20,$AN$20,$AO$20,$AP$20),4),"") -> 5.5 | BX20: =IFERROR(ROUND(AVERAGE(VALUE(LEFT($AW$20,1)),$AX$20,$AY$20),4),"") -> 6 | BY20: =IFERROR(ROUND(AVERAGE($BR$20,$BA$20,$BB$20,$BS$20,$BT$20),4),"") -> 4.6 | BZ20: =IF(OR($BK$20="Junior",$BK$20="Stagiaire",$BK$20="Alternant"),"Junior",IF(OR($BK$20="Superviseur",$BK$20="Superviseur ",$BK$20="Senior",$BK$20="Senior Manager",$BK$20="Manager"),"Senior-Manager",IF(OR($BK$20="Associe",$BK$20="Associé"),"Associe","Autre"))) -> Senior-Manager | CA20: =AND(NOT(ISNUMBER(SEARCH("Jamais",$B$20))),$BG$20="4. Neutre") -> TRUE | CB20: =VALUE(LEFT(B20,1)) -> 7
